Workbook

Sheet Resumen
A1: UNMdP Map · Ciencias Económicas y Sociales
A3: Carrera | B3: Plan | C3: Materias | D3: Aprobadas | E3: Cursadas aprobadas | F3: Puedo cursar | G3: Bloqueadas
A4: Contador Público | B4: Plan E (2005) · OCS 446/2018 | C4: =COUNTA('Contador Público'!F2:F46) -> 45 | D4: =COUNTIF('Contador Público'!Q2:Q46,"Aprobada") -> 0 | E4: =COUNTIF('Contador Público'!Q2:Q46,"Cursada aprobada") -> 0 | F4: =COUNTIF('Contador Público'!R2:R46,"Sí") -> 16 | G4: =COUNTIF('Contador Público'!R2:R46,"No") -> 29
A5: Licenciatura en Administración | B5: Plan C (2005) · OCS 881/2004 | C5: =COUNTA('Lic. Administración'!F2:F46) -> 45 | D5: =COUNTIF('Lic. Administración'!Q2:Q46,"Aprobada") -> 0 | E5: =COUNTIF('Lic. Administración'!Q2:Q46,"Cursada aprobada") -> 0 | F5: =COUNTIF('Lic. Administración'!R2:R46,"Sí") -> 15 | G5: =COUNTIF('Lic. Administración'!R2:R46,"No") -> 30
A6: Licenciatura en Economía | B6: Plan E (2005) · RM 1281/2019 | C6: =COUNTA('Lic. Economía'!F2:F46) -> 45 | D6: =COUNTIF('Lic. Economía'!Q2:Q46,"Aprobada") -> 0 | E6: =COUNTIF('Lic. Economía'!Q2:Q46,"Cursada aprobada") -> 0 | F6: =COUNTIF('Lic. Economía'!R2:R46,"Sí") -> 18 | G6: =COUNTIF('Lic. Economía'!R2:R46,"No") -> 27
A7: Licenciatura en Turismo | B7: Plan E (2005) · OCS 370/2004 y 513/2009 | C7: =COUNTA('Lic. Turismo'!F2:F46) -> 45 | D7: =COUNTIF('Lic. Turismo'!Q2:Q46,"Aprobada") -> 0 | E7: =COUNTIF('Lic. Turismo'!Q2:Q46,"Cursada aprobada") -> 0 | F7: =COUNTIF('Lic. Turismo'!R2:R46,"Sí") -> 23 | G7: =COUNTIF('Lic. Turismo'!R2:R46,"No") -> 22
A8: Profesorado Universitario en Economía | B8: OCA 2344/2011 y 125/2018 | C8: =COUNTA('Prof. Economía'!F2:F51) -> 50 | D8: =COUNTIF('Prof. Economía'!Q2:Q51,"Aprobada") -> 0 | E8: =COUNTIF('Prof. Economía'!Q2:Q51,"Cursada aprobada") -> 0 | F8: =COUNTIF('Prof. Economía'!R2:R51,"Sí") -> 17 | G8: =COUNTIF('Prof. Economía'!R2:R51,"No") -> 33
A9: Tecnicatura Universitaria Contable | B9: RM 435/2020 | C9: =COUNTA('Tec. Contable'!F2:F25) -> 24 | D9: =COUNTIF('Tec. Contable'!Q2:Q25,"Aprobada") -> 0 | E9: =COUNTIF('Tec. Contable'!Q2:Q25,"Cursada aprobada") -> 0 | F9: =COUNTIF('Tec. Contable'!R2:R25,"Sí") -> 4 | G9: =COUNTIF('Tec. Contable'!R2:R25,"No") -> 20
A10: Tecnicatura Universitaria en Comercialización | B10: OCS 1569/2015 · RM 875/2016 | C10: =COUNTA('Tec. Comercialización'!F2:F26) -> 25 | D10: =COUNTIF('Tec. Comercialización'!Q2:Q26,"Aprobada") -> 0 | E10: =COUNTIF('Tec. Comercialización'!Q2:Q26,"Cursada aprobada") -> 0 | F10: =COUNTIF('Tec. Comercialización'!R2:R26,"Sí") -> 6 | G10: =COUNTIF('Tec. Comercialización'!R2:R26,"No") -> 19
A11: Tecnicatura Universitaria en Comercio Exterior | B11: OCS 2226/2016 · RM 2625/2017 | C11: =COUNTA('Tec. Comercio Exterior'!F2:F26) -> 25 | D11: =COUNTIF('Tec. Comercio Exterior'!Q2:Q26,"Aprobada") -> 0 | E11: =COUNTIF('Tec. Comercio Exterior'!Q2:Q26,"Cursada aprobada") -> 0 | F11: =COUNTIF('Tec. Comercio Exterior'!R2:R26,"Sí") -> 6 | G11: =COUNTIF('Tec. Comercio Exterior'!R2:R26,"No") -> 19
A12: Tecnicatura Universitaria en Periodismo Digital | B12: OCS 2322/2017 | C12: =COUNTA('Tec. Periodismo Digital'!F2:F26) -> 25 | D12: =COUNTIF('Tec. Periodismo Digital'!Q2:Q26,"Aprobada") -> 0 | E12: =COUNTIF('Tec. Periodismo Digital'!Q2:Q26,"Cursada aprobada") -> 0 | F12: =COUNTIF('Tec. Periodismo Digital'!R2:R26,"Sí") -> 10 | G12: =COUNTIF('Tec. Periodismo Digital'!R2:R26,"No") -> 15
A13: Tecnicatura Universitaria en Turismo | B13: OCA 1902/2015 · RM 518/2017 | C13: =COUNTA('Tec. Turismo'!F2:F29) -> 28 | D13: =COUNTIF('Tec. Turismo'!Q2:Q29,"Aprobada") -> 0 | E13: =COUNTIF('Tec. Turismo'!Q2:Q29,"Cursada aprobada") -> 0 | F13: =COUNTIF('Tec. Turismo'!R2:R29,"Sí") -> 8 | G13: =COUNTIF('Tec. Turismo'!R2:R29,"No") -> 20
A15: Para cursar, las correlativas tienen que tener: | B15: La cursada aprobada
A17: Cómo usar: en la hoja de tu carrera cambiá la columna Estado (texto azul): No cursada, Cursada aprobada o Aprobada.
A18: ¿Puedo cursar? muestra Sí cuando las correlativas cumplen la regla elegida arriba (celda amarilla).
A19: ¿Puedo rendir el final? aparece en las materias con la cursada aprobada: Sí cuando todas sus correlativas están Aprobada.
A20: Una materia nunca puede estar Aprobada si alguna correlativa no lo está. La columna Correlativas a revisar marca en rojo esos casos.
A21: La cursada aprobada tiene un año de vigencia (OCA 357/2025).
A22: Los códigos de correlativas que no figuran en el plan no se tienen en cuenta (tienen un comentario).
A23: Fuente: planes de estudio publicados en eco.mdp.edu.ar (clic en el nombre de la carrera). Verificá con la facultad.

Sheet Contador Público
A1: Ciclo | B1: Orientación / Grupo | C1: Año | D1: Cuat. | E1: Área | F1: Cód. | G1: Denominación | H1: Grupo | I1: Hs/s | J1: Hs Bim | K1: Hs Cuat | L1: Corr. 1 | M1: Corr. 2 | N1: Corr. 3 | O1: Corr. 4 | P1: Corr. 5 | Q1: Estado | R1: ¿Puedo cursar? | S1: Correlativas pendientes | T1: ¿Puedo rendir el final? | U1: Correlativas a revisar
A2: Ciclo básico | C2: 1 | D2: 1 | E2: EC | F2: 101 | G2: Introducción a la Economía | H2: I | I2: 6 | K2: 96 | Q2: No cursada | R2: =IF(Q2="Aprobada","Ya aprobada",IF(Q2="Cursada aprobada","Ya cursada",IF(AND(OR(L2="",COUNTIF($F$2:$F$46,L2)=0,COUNTIFS($F$2:$F$46,L2,$Q$2:$Q$46,"Aprobada")>0,AND(Resumen!$B$15="La cursada aprobada",COUNTIFS($F$2:$F$46,L2,$Q$2:$Q$46,"Cursada aprobada")>0)),OR(M2="",COUNTIF($F$2:$F$46,M2)=0,COUNTIFS($F$2:$F$46,M2,$Q$2:$Q$46,"Aprobada")>0,AND(Resumen!$B$15="La cursada aprobada",COUNTIFS($F$2:$F$46,M2,$Q$2:$Q$46,"Cursada aprobada")>0)),OR(N2="",COUNTIF($F$2:$F$46,N2)=0,COUNTIFS($F$2:$F$46,N2,$Q$2:$Q$46,"Aprobada")>0,AND(Resumen!$B$15="La cursada aprobada",COUNTIFS($F$2:$F$46,N2,$Q$2:$Q$46,"Cursada aprobada")>0)),OR(O2="",COUNTIF($F$2:$F$46,O2)=0,COUNTIFS($F$2:$F$46,O2,$Q$2:$Q$46,"Aprobada")>0,AND(Resumen!$B$15="La cursada aprobada",COUNTIFS($F$2:$F$46,O2,$Q$2:$Q$46,"Cursada aprobada")>0)),OR(P2="",COUNTIF($F$2:$F$46,P2)=0,COUNTIFS($F$2:$F$46,P2,$Q$2:$Q$46,"Aprobada")>0,AND(Resumen!$B$15="La cursada aprobada",COUNTIFS($F$2:$F$46,P2,$Q$2:$Q$46,"Cursada aprobada")>0))),"Sí","No"))) -> Sí | S2: =TRIM(IF(NOT(OR(L2="",COUNTIF($F$2:$F$46,L2)=0,COUNTIFS($F$2:$F$46,L2,$Q$2:$Q$46,"Aprobada")>0,AND(Resumen!$B$15="La cursada aprobada",COUNTIFS($F$2:$F$46,L2,$Q$2:$Q$46,"Cursada aprobada")>0))),L2&" ","")&IF(NOT(OR(M2="",COUNTIF($F$2:$F$46,M2)=0,COUNTIFS($F$2:$F$46,M2,$Q$2:$Q$46,"Aprobada")>0,AND(Resumen!$B$15="La cursada aprobada",COUNTIFS($F$2:$F$46,M2,$Q$2:$Q$46,"Cursada aprobada")>0))),M2&" ","")&IF(NOT(OR(N2="",COUNTIF($F$2:$F$46,N2)=0,COUNTIFS($F$2:$F$46,N2,$Q$2:$Q$46,"Aprobada")>0,AND(Resumen!$B$15="La cursada aprobada",COUNTIFS($F$2:$F$46,N2,$Q$2:$Q$46,"Cursada aprobada")>0))),N2&" ","")&IF(NOT(OR(O2="",COUNTIF($F$2:$F$46,O2)=0,COUNTIFS($F$2:$F$46,O2,$Q$2:$Q$46,"Aprobada")>0,AND(Resumen!$B$15="La cursada aprobada",COUNTIFS($F$2:$F$46,O2,$Q$2:$Q$46,"Cursada aprobada")>0))),O2&" ","")&IF(NOT(OR(P2="",COUNTIF($F$2:$F$46,P2)=0,COUNTIFS($F$2:$F$46,P2,$Q$2:$Q$46,"Aprobada")>0,AND(Resumen!$B$15="La cursada aprobada",COUNTIFS($F$2:$F$46,P2,$Q$2:$Q$46,"Cursada aprobada")>0))),P2&" ","")) | T2: =IF(Q2="Cursada aprobada",IF(AND(OR(L2="",COUNTIF($F$2:$F$46,L2)=0,COUNTIFS($F$2:$F$46,L2,$Q$2:$Q$46,"Aprobada")>0),OR(M2="",COUNTIF($F$2:$F$46,M2)=0,COUNTIFS($F$2:$F$46,M2,$Q$2:$Q$46,"Aprobada")>0),OR(N2="",COUNTIF($F$2:$F$46,N2)=0,COUNTIFS($F$2:$F$46,N2,$Q$2:$Q$46,"Aprobada")>0),OR(O2="",COUNTIF($F$2:$F$46,O2)=0,COUNTIFS($F$2:$F$46,O2,$Q$2:$Q$46,"Aprobada")>0),OR(P2="",COUNTIF($F$2:$F$46,P2)=0,COUNTIFS($F$2:$F$46,P2,$Q$2:$Q$46,"Aprobada")>0)),"Sí","No"),"") | U2: =IF(Q2="Aprobada",TRIM(IF(NOT(OR(L2="",COUNTIF($F$2:$F$46,L2)=0,COUNTIFS($F$2:$F$46,L2,$Q$2:$Q$46,"Aprobada")>0)),L2&" ","")&IF(NOT(OR(M2="",COUNTIF($F$2:$F$46,M2)=0,COUNTIFS($F$2:$F$46,M2,$Q$2:$Q$46,"Aprobada")>0)),M2&" ","")&IF(NOT(OR(N2="",COUNTIF($F$2:$F$46,N2)=0,COUNTIFS($F$2:$F$46,N2,$Q$2:$Q$46,"Aprobada")>0)),N2&" ","")&IF(NOT(OR(O2="",COUNTIF($F$2:$F$46,O2)=0,COUNTIFS($F$2:$F$46,O2,$Q$2:$Q$46,"Aprobada")>0)),O2&" ","")&IF(NOT(OR(P2="",COUNTIF($F$2:$F$46,P2)=0,COUNTIFS($F$2:$F$46,P2,$Q$2:$Q$46,"Aprobada")>0)),P2&" ","")),IF(Q2="Cursada aprobada",TRIM(IF(NOT(OR(L2="",COUNTIF($F$2:$F$46,L2)=0,COUNTIFS($F$2:$F$46,L2,$Q$2:$Q$46,"Aprobada")>0,AND(Resumen!$B$15="La cursada aprobada",COUNTIFS($F$2:$F$46,L2,$Q$2:$Q$46,"Cursada aprobada")>0))),L2&" ","")&IF(NOT(OR(M2="",COUNTIF($F$2:$F$46,M2)=0,COUNTIFS($F$2:$F$46,M2,$Q$2:$Q$46,"Aprobada")>0,AND(Resumen!$B$15="La cursada aprobada",COUNTIFS($F$2:$F$46,M2,$Q$2:$Q$46,"Cursada aprobada")>0))),M2&" ","")&IF(NOT(OR(N2="",COUNTIF($F$2:$F$46,N2)=0,COUNTIFS($F$2:$F$46,N2,$Q$2:$Q$46,"Aprobada")>0,AND(Resumen!$B$15="La cursada aprobada",COUNTIFS($F$2:$F$46,N2,$Q$2:$Q$46,"Cursada aprobada")>0))),N2&" ","")&IF(NOT(OR(O2="",COUNTIF($F$2:$F$46,O2)=0,COUNTIFS($F$2:$F$46,O2,$Q$2:$Q$46,"Aprobada")>0,AND(Resumen!$B$15="La cursada aprobada",COUNTIFS($F$2:$F$46,O2,$Q$2:$Q$46,"Cursada aprobada")>0))),O2&" ","")&IF(NOT(OR(P2="",COUNTIF($F$2:$F$46,P2)=0,COUNTIFS($F$2:$F$46,P2,$Q$2:$Q$46,"Aprobada")>0,AND(Resumen!$B$15="La cursada aprobada",COUNTIFS($F$2:$F$46,P2,$Q$2:$Q$46,"Cursada aprobada")>0))),P2&" ","")),""))
A3: Ciclo básico | C3: 1 | D3: 1 | E3: AD | F3: 104 | G3: Principios de Administración | H3: I | I3: 6 | K3: 96 | Q3: No cursada | R3: =IF(Q3="Aprobada","Ya aprobada",IF(Q3="Cursada aprobada","Ya cursada",IF(AND(OR(L3="",COUNTIF($F$2:$F$46,L3)=0,COUNTIFS($F$2:$F$46,L3,$Q$2:$Q$46,"Aprobada")>0,AND(Resumen!$B$15="La cursada aprobada",COUNTIFS($F$2:$F$46,L3,$Q$2:$Q$46,"Cursada aprobada")>0)),OR(M3="",COUNTIF($F$2:$F$46,M3)=0,COUNTIFS($F$2:$F$46,M3,$Q$2:$Q$46,"Aprobada")>0,AND(Resumen!$B$15="La cursada aprobada",COUNTIFS($F$2:$F$46,M3,$Q$2:$Q$46,"Cursada aprobada")>0)),OR(N3="",COUNTIF($F$2:$F$46,N3)=0,COUNTIFS($F$2:$F$46,N3,$Q$2:$Q$46,"Aprobada")>0,AND(Resumen!$B$15="La cursada aprobada",COUNTIFS($F$2:$F$46,N3,$Q$2:$Q$46,"Cursada aprobada")>0)),OR(O3="",COUNTIF($F$2:$F$46,O3)=0,COUNTIFS($F$2:$F$46,O3,$Q$2:$Q$46,"Aprobada")>0,AND(Resumen!$B$15="La cursada aprobada",COUNTIFS($F$2:$F$46,O3,$Q$2:$Q$46,"Cursada aprobada")>0)),OR(P3="",COUNTIF($F$2:$F$46,P3)=0,COUNTIFS($F$2:$F$46,P3,$Q$2:$Q$46,"Aprobada")>0,AND(Resumen!$B$15="La cursada aprobada",COUNTIFS($F$2:$F$46,P3,$Q$2:$Q$46,"Cursada aprobada")>0))),"Sí","No"))) -> Sí | S3: =TRIM(IF(NOT(OR(L3="",COUNTIF($F$2:$F$46,L3)=0,COUNTIFS($F$2:$F$46,L3,$Q$2:$Q$46,"Aprobada")>0,AND(Resumen!$B$15="La cursada aprobada",COUNTIFS($F$2:$F$46,L3,$Q$2:$Q$46,"Cursada aprobada")>0))),L3&" ","")&IF(NOT(OR(M3="",COUNTIF($F$2:$F$46,M3)=0,COUNTIFS($F$2:$F$46,M3,$Q$2:$Q$46,"Aprobada")>0,AND(Resumen!$B$15="La cursada aprobada",COUNTIFS($F$2:$F$46,M3,$Q$2:$Q$46,"Cursada aprobada")>0))),M3&" ","")&IF(NOT(OR(N3="",COUNTIF($F$2:$F$46,N3)=0,COUNTIFS($F$2:$F$46,N3,$Q$2:$Q$46,"Aprobada")>0,AND(Resumen!$B$15="La cursada aprobada",COUNTIFS($F$2:$F$46,N3,$Q$2:$Q$46,"Cursada aprobada")>0))),N3&" ","")&IF(NOT(OR(O3="",COUNTIF($F$2:$F$46,O3)=0,COUNTIFS($F$2:$F$46,O3,$Q$2:$Q$46,"Aprobada")>0,AND(Resumen!$B$15="La cursada aprobada",COUNTIFS($F$2:$F$46,O3,$Q$2:$Q$46,"Cursada aprobada")>0))),O3&" ","")&IF(NOT(OR(P3="",COUNTIF($F$2:$F$46,P3)=0,COUNTIFS($F$2:$F$46,P3,$Q$2:$Q$46,"Aprobada")>0,AND(Resumen!$B$15="La cursada aprobada",COUNTIFS($F$2:$F$46,P3,$Q$2:$Q$46,"Cursada aprobada")>0))),P3&" ","")) | T3: =IF(Q3="Cursada aprobada",IF(AND(OR(L3="",COUNTIF($F$2:$F$46,L3)=0,COUNTIFS($F$2:$F$46,L3,$Q$2:$Q$46,"Aprobada")>0),OR(M3="",COUNTIF($F$2:$F$46,M3)=0,COUNTIFS($F$2:$F$46,M3,$Q$2:$Q$46,"Aprobada")>0),OR(N3="",COUNTIF($F$2:$F$46,N3)=0,COUNTIFS($F$2:$F$46,N3,$Q$2:$Q$46,"Aprobada")>0),OR(O3="",COUNTIF($F$2:$F$46,O3)=0,COUNTIFS($F$2:$F$46,O3,$Q$2:$Q$46,"Aprobada")>0),OR(P3="",COUNTIF($F$2:$F$46,P3)=0,COUNTIFS($F$2:$F$46,P3,$Q$2:$Q$46,"Aprobada")>0)),"Sí","No"),"") | U3: =IF(Q3="Aprobada",TRIM(IF(NOT(OR(L3="",COUNTIF($F$2:$F$46,L3)=0,COUNTIFS($F$2:$F$46,L3,$Q$2:$Q$46,"Aprobada")>0)),L3&" ","")&IF(NOT(OR(M3="",COUNTIF($F$2:$F$46,M3)=0,COUNTIFS($F$2:$F$46,M3,$Q$2:$Q$46,"Aprobada")>0)),M3&" ","")&IF(NOT(OR(N3="",COUNTIF($F$2:$F$46,N3)=0,COUNTIFS($F$2:$F$46,N3,$Q$2:$Q$46,"Aprobada")>0)),N3&" ","")&IF(NOT(OR(O3="",COUNTIF($F$2:$F$46,O3)=0,COUNTIFS($F$2:$F$46,O3,$Q$2:$Q$46,"Aprobada")>0)),O3&" ","")&IF(NOT(OR(P3="",COUNTIF($F$2:$F$46,P3)=0,COUNTIFS($F$2:$F$46,P3,$Q$2:$Q$46,"Aprobada")>0)),P3&" ","")),IF(Q3="Cursada aprobada",TRIM(IF(NOT(OR(L3="",COUNTIF($F$2:$F$46,L3)=0,COUNTIFS($F$2:$F$46,L3,$Q$2:$Q$46,"Aprobada")>0,AND(Resumen!$B$15="La cursada aprobada",COUNTIFS($F$2:$F$46,L3,$Q$2:$Q$46,"Cursada aprobada")>0))),L3&" ","")&IF(NOT(OR(M3="",COUNTIF($F$2:$F$46,M3)=0,COUNTIFS($F$2:$F$46,M3,$Q$2:$Q$46,"Aprobada")>0,AND(Resumen!$B$15="La cursada aprobada",COUNTIFS($F$2:$F$46,M3,$Q$2:$Q$46,"Cursada aprobada")>0))),M3&" ","")&IF(NOT(OR(N3="",COUNTIF($F$2:$F$46,N3)=0,COUNTIFS($F$2:$F$46,N3,$Q$2:$Q$46,"Aprobada")>0,AND(Resumen!$B$15="La cursada aprobada",COUNTIFS($F$2:$F$46,N3,$Q$2:$Q$46,"Cursada aprobada")>0))),N3&" ","")&IF(NOT(OR(O3="",COUNTIF($F$2:$F$46,O3)=0,COUNTIFS($F$2:$F$46,O3,$Q$2:$Q$46,"Aprobada")>0,AND(Resumen!$B$15="La cursada aprobada",COUNTIFS($F$2:$F$46,O3,$Q$2:$Q$46,"Cursada aprobada")>0))),O3&" ","")&IF(NOT(OR(P3="",COUNTIF($F$2:$F$46,P3)=0,COUNTIFS($F$2:$F$46,P3,$Q$2:$Q$46,"Aprobada")>0,AND(Resumen!$B$15="La cursada aprobada",COUNTIFS($F$2:$F$46,P3,$Q$2:$Q$46,"Cursada aprobada")>0))),P3&" ","")),""))
A4: Ciclo básico | C4: 1 | D4: 1 | E4: MA | F4: 102 | G4: Matemática I | H4: I | I4: 6 | K4: 96 | Q4: No cursada | R4: =IF(Q4="Aprobada","Ya aprobada",IF(Q4="Cursada aprobada","Ya cursada",IF(AND(OR(L4="",COUNTIF($F$2:$F$46,L4)=0,COUNTIFS($F$2:$F$46,L4,$Q$2:$Q$46,"Aprobada")>0,AND(Resumen!$B$15="La cursada aprobada",COUNTIFS($F$2:$F$46,L4,$Q$2:$Q$46,"Cursada aprobada")>0)),OR(M4="",COUNTIF($F$2:$F$46,M4)=0,COUNTIFS($F$2:$F$46,M4,$Q$2:$Q$46,"Aprobada")>0,AND(Resumen!$B$15="La cursada aprobada",COUNTIFS($F$2:$F$46,M4,$Q$2:$Q$46,"Cursada aprobada")>0)),OR(N4="",COUNTIF($F$2:$F$46,N4)=0,COUNTIFS($F$2:$F$46,N4,$Q$2:$Q$46,"Aprobada")>0,AND(Resumen!$B$15="La cursada aprobada",COUNTIFS($F$2:$F$46,N4,$Q$2:$Q$46,"Cursada aprobada")>0)),OR(O4="",COUNTIF($F$2:$F$46,O4)=0,COUNTIFS($F$2:$F$46,O4,$Q$2:$Q$46,"Aprobada")>0,AND(Resumen!$B$15="La cursada aprobada",COUNTIFS($F$2:$F$46,O4,$Q$2:$Q$46,"Cursada aprobada")>0)),OR(P4="",COUNTIF($F$2:$F$46,P4)=0,COUNTIFS($F$2:$F$46,P4,$Q$2:$Q$46,"Aprobada")>0,AND(Resumen!$B$15="La cursada aprobada",COUNTIFS($F$2:$F$46,P4,$Q$2:$Q$46,"Cursada aprobada")>0))),"Sí","No"))) -> Sí | S4: =TRIM(IF(NOT(OR(L4="",COUNTIF($F$2:$F$46,L4)=0,COUNTIFS($F$2:$F$46,L4,$Q$2:$Q$46,"Aprobada")>0,AND(Resumen!$B$15="La cursada aprobada",COUNTIFS($F$2:$F$46,L4,$Q$2:$Q$46,"Cursada aprobada")>0))),L4&" ","")&IF(NOT(OR(M4="",COUNTIF($F$2:$F$46,M4)=0,COUNTIFS($F$2:$F$46,M4,$Q$2:$Q$46,"Aprobada")>0,AND(Resumen!$B$15="La cursada aprobada",COUNTIFS($F$2:$F$46,M4,$Q$2:$Q$46,"Cursada aprobada")>0))),M4&" ","")&IF(NOT(OR(N4="",COUNTIF($F$2:$F$46,N4)=0,COUNTIFS($F$2:$F$46,N4,$Q$2:$Q$46,"Aprobada")>0,AND(Resumen!$B$15="La cursada aprobada",COUNTIFS($F$2:$F$46,N4,$Q$2:$Q$46,"Cursada aprobada")>0))),N4&" ","")&IF(NOT(OR(O4="",COUNTIF($F$2:$F$46,O4)=0,COUNTIFS($F$2:$F$46,O4,$Q$2:$Q$46,"Aprobada")>0,AND(Resumen!$B$15="La cursada aprobada",COUNTIFS($F$2:$F$46,O4,$Q$2:$Q$46,"Cursada aprobada")>0))),O4&" ","")&IF(NOT(OR(P4="",COUNTIF($F$2:$F$46,P4)=0,COUNTIFS($F$2:$F$46,P4,$Q$2:$Q$46,"Aprobada")>0,AND(Resumen!$B$15="La cursada aprobada",COUNTIFS($F$2:$F$46,P4,$Q$2:$Q$46,"Cursada aprobada")>0))),P4&" ","")) | T4: =IF(Q4="Cursada aprobada",IF(AND(OR(L4="",COUNTIF($F$2:$F$46,L4)=0,COUNTIFS($F$2:$F$46,L4,$Q$2:$Q$46,"Aprobada")>0),OR(M4="",COUNTIF($F$2:$F$46,M4)=0,COUNTIFS($F$2:$F$46,M4,$Q$2:$Q$46,"Aprobada")>0),OR(N4="",COUNTIF($F$2:$F$46,N4)=0,COUNTIFS($F$2:$F$46,N4,$Q$2:$Q$46,"Aprobada")>0),OR(O4="",COUNTIF($F$2:$F$46,O4)=0,COUNTIFS($F$2:$F$46,O4,$Q$2:$Q$46,"Aprobada")>0),OR(P4="",COUNTIF($F$2:$F$46,P4)=0,COUNTIFS($F$2:$F$46,P4,$Q$2:$Q$46,"Aprobada")>0)),"Sí","No"),"") | U4: =IF(Q4="Aprobada",TRIM(IF(NOT(OR(L4="",COUNTIF($F$2:$F$46,L4)=0,COUNTIFS($F$2:$F$46,L4,$Q$2:$Q$46,"Aprobada")>0)),L4&" ","")&IF(NOT(OR(M4="",COUNTIF($F$2:$F$46,M4)=0,COUNTIFS($F$2:$F$46,M4,$Q$2:$Q$46,"Aprobada")>0)),M4&" ","")&IF(NOT(OR(N4="",COUNTIF($F$2:$F$46,N4)=0,COUNTIFS($F$2:$F$46,N4,$Q$2:$Q$46,"Aprobada")>0)),N4&" ","")&IF(NOT(OR(O4="",COUNTIF($F$2:$F$46,O4)=0,COUNTIFS($F$2:$F$46,O4,$Q$2:$Q$46,"Aprobada")>0)),O4&" ","")&IF(NOT(OR(P4="",COUNTIF($F$2:$F$46,P4)=0,COUNTIFS($F$2:$F$46,P4,$Q$2:$Q$46,"Aprobada")>0)),P4&" ","")),IF(Q4="Cursada aprobada",TRIM(IF(NOT(OR(L4="",COUNTIF($F$2:$F$46,L4)=0,COUNTIFS($F$2:$F$46,L4,$Q$2:$Q$46,"Aprobada")>0,AND(Resumen!$B$15="La cursada aprobada",COUNTIFS($F$2:$F$46,L4,$Q$2:$Q$46,"Cursada aprobada")>0))),L4&" ","")&IF(NOT(OR(M4="",COUNTIF($F$2:$F$46,M4)=0,COUNTIFS($F$2:$F$46,M4,$Q$2:$Q$46,"Aprobada")>0,AND(Resumen!$B$15="La cursada aprobada",COUNTIFS($F$2:$F$46,M4,$Q$2:$Q$46,"Cursada aprobada")>0))),M4&" ","")&IF(NOT(OR(N4="",COUNTIF($F$2:$F$46,N4)=0,COUNTIFS($F$2:$F$46,N4,$Q$2:$Q$46,"Aprobada")>0,AND(Resumen!$B$15="La cursada aprobada",COUNTIFS($F$2:$F$46,N4,$Q$2:$Q$46,"Cursada aprobada")>0))),N4&" ","")&IF(NOT(OR(O4="",COUNTIF($F$2:$F$46,O4)=0,COUNTIFS($F$2:$F$46,O4,$Q$2:$Q$46,"Aprobada")>0,AND(Resumen!$B$15="La cursada aprobada",COUNTIFS($F$2:$F$46,O4,$Q$2:$Q$46,"Cursada aprobada")>0))),O4&" ","")&IF(NOT(OR(P4="",COUNTIF($F$2:$F$46,P4)=0,COUNTIFS($F$2:$F$46,P4,$Q$2:$Q$46,"Aprobada")>0,AND(Resumen!$B$15="La cursada aprobada",COUNTIFS($F$2:$F$46,P4,$Q$2:$Q$46,"Cursada aprobada")>0))),P4&" ","")),""))
A5: Ciclo básico | C5: 1 | D5: 2 | E5: CO | F5: 103 | G5: Contabilidad I | H5: I | I5: 6 | K5: 96 | Q5: No cursada | R5: =IF(Q5="Aprobada","Ya aprobada",IF(Q5="Cursada aprobada","Ya cursada",IF(AND(OR(L5="",COUNTIF($F$2:$F$46,L5)=0,COUNTIFS($F$2:$F$46,L5,$Q$2:$Q$46,"Aprobada")>0,AND(Resumen!$B$15="La cursada aprobada",COUNTIFS($F$2:$F$46,L5,$Q$2:$Q$46,"Cursada aprobada")>0)),OR(M5="",COUNTIF($F$2:$F$46,M5)=0,COUNTIFS($F$2:$F$46,M5,$Q$2:$Q$46,"Aprobada")>0,AND(Resumen!$B$15="La cursada aprobada",COUNTIFS($F$2:$F$46,M5,$Q$2:$Q$46,"Cursada aprobada")>0)),OR(N5="",COUNTIF($F$2:$F$46,N5)=0,COUNTIFS($F$2:$F$46,N5,$Q$2:$Q$46,"Aprobada")>0,AND(Resumen!$B$15="La cursada aprobada",COUNTIFS($F$2:$F$46,N5,$Q$2:$Q$46,"Cursada aprobada")>0)),OR(O5="",COUNTIF($F$2:$F$46,O5)=0,COUNTIFS($F$2:$F$46,O5,$Q$2:$Q$46,"Aprobada")>0,AND(Resumen!$B$15="La cursada aprobada",COUNTIFS($F$2:$F$46,O5,$Q$2:$Q$46,"Cursada aprobada")>0)),OR(P5="",COUNTIF($F$2:$F$46,P5)=0,COUNTIFS($F$2:$F$46,P5,$Q$2:$Q$46,"Aprobada")>0,AND(Resumen!$B$15="La cursada aprobada",COUNTIFS($F$2:$F$46,P5,$Q$2:$Q$46,"Cursada aprobada")>0))),"Sí","No"))) -> Sí | S5: =TRIM(IF(NOT(OR(L5="",COUNTIF($F$2:$F$46,L5)=0,COUNTIFS($F$2:$F$46,L5,$Q$2:$Q$46,"Aprobada")>0,AND(Resumen!$B$15="La cursada aprobada",COUNTIFS($F$2:$F$46,L5,$Q$2:$Q$46,"Cursada aprobada")>0))),L5&" ","")&IF(NOT(OR(M5="",COUNTIF($F$2:$F$46,M5)=0,COUNTIFS($F$2:$F$46,M5,$Q$2:$Q$46,"Aprobada")>0,AND(Resumen!$B$15="La cursada aprobada",COUNTIFS($F$2:$F$46,M5,$Q$2:$Q$46,"Cursada aprobada")>0))),M5&" ","")&IF(NOT(OR(N5="",COUNTIF($F$2:$F$46,N5)=0,COUNTIFS($F$2:$F$46,N5,$Q$2:$Q$46,"Aprobada")>0,AND(Resumen!$B$15="La cursada aprobada",COUNTIFS($F$2:$F$46,N5,$Q$2:$Q$46,"Cursada aprobada")>0))),N5&" ","")&IF(NOT(OR(O5="",COUNTIF($F$2:$F$46,O5)=0,COUNTIFS($F$2:$F$46,O5,$Q$2:$Q$46,"Aprobada")>0,AND(Resumen!$B$15="La cursada aprobada",COUNTIFS($F$2:$F$46,O5,$Q$2:$Q$46,"Cursada aprobada")>0))),O5&" ","")&IF(NOT(OR(P5="",COUNTIF($F$2:$F$46,P5)=0,COUNTIFS($F$2:$F$46,P5,$Q$2:$Q$46,"Aprobada")>0,AND(Resumen!$B$15="La cursada aprobada",COUNTIFS($F$2:$F$46,P5,$Q$2:$Q$46,"Cursada aprobada")>0))),P5&" ","")) | T5: =IF(Q5="Cursada aprobada",IF(AND(OR(L5="",COUNTIF($F$2:$F$46,L5)=0,COUNTIFS($F$2:$F$46,L5,$Q$2:$Q$46,"Aprobada")>0),OR(M5="",COUNTIF($F$2:$F$46,M5)=0,COUNTIFS($F$2:$F$46,M5,$Q$2:$Q$46,"Aprobada")>0),OR(N5="",COUNTIF($F$2:$F$46,N5)=0,COUNTIFS($F$2:$F$46,N5,$Q$2:$Q$46,"Aprobada")>0),OR(O5="",COUNTIF($F$2:$F$46,O5)=0,COUNTIFS($F$2:$F$46,O5,$Q$2:$Q$46,"Aprobada")>0),OR(P5="",COUNTIF($F$2:$F$46,P5)=0,COUNTIFS($F$2:$F$46,P5,$Q$2:$Q$46,"Aprobada")>0)),"Sí","No"),"") | U5: =IF(Q5="Aprobada",TRIM(IF(NOT(OR(L5="",COUNTIF($F$2:$F$46,L5)=0,COUNTIFS($F$2:$F$46,L5,$Q$2:$Q$46,"Aprobada")>0)),L5&" ","")&IF(NOT(OR(M5="",COUNTIF($F$2:$F$46,M5)=0,COUNTIFS($F$2:$F$46,M5,$Q$2:$Q$46,"Aprobada")>0)),M5&" ","")&IF(NOT(OR(N5="",COUNTIF($F$2:$F$46,N5)=0,COUNTIFS($F$2:$F$46,N5,$Q$2:$Q$46,"Aprobada")>0)),N5&" ","")&IF(NOT(OR(O5="",COUNTIF($F$2:$F$46,O5)=0,COUNTIFS($F$2:$F$46,O5,$Q$2:$Q$46,"Aprobada")>0)),O5&" ","")&IF(NOT(OR(P5="",COUNTIF($F$2:$F$46,P5)=0,COUNTIFS($F$2:$F$46,P5,$Q$2:$Q$46,"Aprobada")>0)),P5&" ","")),IF(Q5="Cursada aprobada",TRIM(IF(NOT(OR(L5="",COUNTIF($F$2:$F$46,L5)=0,COUNTIFS($F$2:$F$46,L5,$Q$2:$Q$46,"Aprobada")>0,AND(Resumen!$B$15="La cursada aprobada",COUNTIFS($F$2:$F$46,L5,$Q$2:$Q$46,"Cursada aprobada")>0))),L5&" ","")&IF(NOT(OR(M5="",COUNTIF($F$2:$F$46,M5)=0,COUNTIFS($F$2:$F$46,M5,$Q$2:$Q$46,"Aprobada")>0,AND(Resumen!$B$15="La cursada aprobada",COUNTIFS($F$2:$F$46,M5,$Q$2:$Q$46,"Cursada aprobada")>0))),M5&" ","")&IF(NOT(OR(N5="",COUNTIF($F$2:$F$46,N5)=0,COUNTIFS($F$2:$F$46,N5,$Q$2:$Q$46,"Aprobada")>0,AND(Resumen!$B$15="La cursada aprobada",COUNTIFS($F$2:$F$46,N5,$Q$2:$Q$46,"Cursada aprobada")>0))),N5&" ","")&IF(NOT(OR(O5="",COUNTIF($F$2:$F$46,O5)=0,COUNTIFS($F$2:$F$46,O5,$Q$2:$Q$46,"Aprobada")>0,AND(Resumen!$B$15="La cursada aprobada",COUNTIFS($F$2:$F$46,O5,$Q$2:$Q$46,"Cursada aprobada")>0))),O5&" ","")&IF(NOT(OR(P5="",COUNTIF($F$2:$F$46,P5)=0,COUNTIFS($F$2:$F$46,P5,$Q$2:$Q$46,"Aprobada")>0,AND(Resumen!$B$15="La cursada aprobada",COUNTIFS($F$2:$F$46,P5,$Q$2:$Q$46,"Cursada aprobada")>0))),P5&" ","")),""))
A6: Ciclo básico | C6: 1 | D6: 2 | E6: CS | F6: 180 | G6: Historia Económica y Social I | H6: II | I6: 4 | K6: 64 | Q6: No cursada | R6: =IF(Q6="Aprobada","Ya aprobada",IF(Q6="Cursada aprobada","Ya cursada",IF(AND(OR(L6="",COUNTIF($F$2:$F$46,L6)=0,COUNTIFS($F$2:$F$46,L6,$Q$2:$Q$46,"Aprobada")>0,AND(Resumen!$B$15="La cursada aprobada",COUNTIFS($F$2:$F$46,L6,$Q$2:$Q$46,"Cursada aprobada")>0)),OR(M6="",COUNTIF($F$2:$F$46,M6)=0,COUNTIFS($F$2:$F$46,M6,$Q$2:$Q$46,"Aprobada")>0,AND(Resumen!$B$15="La cursada aprobada",COUNTIFS($F$2:$F$46,M6,$Q$2:$Q$46,"Cursada aprobada")>0)),OR(N6="",COUNTIF($F$2:$F$46,N6)=0,COUNTIFS($F$2:$F$46,N6,$Q$2:$Q$46,"Aprobada")>0,AND(Resumen!$B$15="La cursada aprobada",COUNTIFS($F$2:$F$46,N6,$Q$2:$Q$46,"Cursada aprobada")>0)),OR(O6="",COUNTIF($F$2:$F$46,O6)=0,COUNTIFS($F$2:$F$46,O6,$Q$2:$Q$46,"Aprobada")>0,AND(Resumen!$B$15="La cursada aprobada",COUNTIFS($F$2:$F$46,O6,$Q$2:$Q$46,"Cursada aprobada")>0)),OR(P6="",COUNTIF($F$2:$F$46,P6)=0,COUNTIFS($F$2:$F$46,P6,$Q$2:$Q$46,"Aprobada")>0,AND(Resumen!$B$15="La cursada aprobada",COUNTIFS($F$2:$F$46,P6,$Q$2:$Q$46,"Cursada aprobada")>0))),"Sí","No"))) -> Sí | S6: =TRIM(IF(NOT(OR(L6="",COUNTIF($F$2:$F$46,L6)=0,COUNTIFS($F$2:$F$46,L6,$Q$2:$Q$46,"Aprobada")>0,AND(Resumen!$B$15="La cursada aprobada",COUNTIFS($F$2:$F$46,L6,$Q$2:$Q$46,"Cursada aprobada")>0))),L6&" ","")&IF(NOT(OR(M6="",COUNTIF($F$2:$F$46,M6)=0,COUNTIFS($F$2:$F$46,M6,$Q$2:$Q$46,"Aprobada")>0,AND(Resumen!$B$15="La cursada aprobada",COUNTIFS($F$2:$F$46,M6,$Q$2:$Q$46,"Cursada aprobada")>0))),M6&" ","")&IF(NOT(OR(N6="",COUNTIF($F$2:$F$46,N6)=0,COUNTIFS($F$2:$F$46,N6,$Q$2:$Q$46,"Aprobada")>0,AND(Resumen!$B$15="La cursada aprobada",COUNTIFS($F$2:$F$46,N6,$Q$2:$Q$46,"Cursada aprobada")>0))),N6&" ","")&IF(NOT(OR(O6="",COUNTIF($F$2:$F$46,O6)=0,COUNTIFS($F$2:$F$46,O6,$Q$2:$Q$46,"Aprobada")>0,AND(Resumen!$B$15="La cursada aprobada",COUNTIFS($F$2:$F$46,O6,$Q$2:$Q$46,"Cursada aprobada")>0))),O6&" ","")&IF(NOT(OR(P6="",COUNTIF($F$2:$F$46,P6)=0,COUNTIFS($F$2:$F$46,P6,$Q$2:$Q$46,"Aprobada")>0,AND(Resumen!$B$15="La cursada aprobada",COUNTIFS($F$2:$F$46,P6,$Q$2:$Q$46,"Cursada aprobada")>0))),P6&" ","")) | T6: =IF(Q6="Cursada aprobada",IF(AND(OR(L6="",COUNTIF($F$2:$F$46,L6)=0,COUNTIFS($F$2:$F$46,L6,$Q$2:$Q$46,"Aprobada")>0),OR(M6="",COUNTIF($F$2:$F$46,M6)=0,COUNTIFS($F$2:$F$46,M6,$Q$2:$Q$46,"Aprobada")>0),OR(N6="",COUNTIF($F$2:$F$46,N6)=0,COUNTIFS($F$2:$F$46,N6,$Q$2:$Q$46,"Aprobada")>0),OR(O6="",COUNTIF($F$2:$F$46,O6)=0,COUNTIFS($F$2:$F$46,O6,$Q$2:$Q$46,"Aprobada")>0),OR(P6="",COUNTIF($F$2:$F$46,P6)=0,COUNTIFS($F$2:$F$46,P6,$Q$2:$Q$46,"Aprobada")>0)),"Sí","No"),"") | U6: =IF(Q6="Aprobada",TRIM(IF(NOT(OR(L6="",COUNTIF($F$2:$F$46,L6)=0,COUNTIFS($F$2:$F$46,L6,$Q$2:$Q$46,"Aprobada")>0)),L6&" ","")&IF(NOT(OR(M6="",COUNTIF($F$2:$F$46,M6)=0,COUNTIFS($F$2:$F$46,M6,$Q$2:$Q$46,"Aprobada")>0)),M6&" ","")&IF(NOT(OR(N6="",COUNTIF($F$2:$F$46,N6)=0,COUNTIFS($F$2:$F$46,N6,$Q$2:$Q$46,"Aprobada")>0)),N6&" ","")&IF(NOT(OR(O6="",COUNTIF($F$2:$F$46,O6)=0,COUNTIFS($F$2:$F$46,O6,$Q$2:$Q$46,"Aprobada")>0)),O6&" ","")&IF(NOT(OR(P6="",COUNTIF($F$2:$F$46,P6)=0,COUNTIFS($F$2:$F$46,P6,$Q$2:$Q$46,"Aprobada")>0)),P6&" ","")),IF(Q6="Cursada aprobada",TRIM(IF(NOT(OR(L6="",COUNTIF($F$2:$F$46,L6)=0,COUNTIFS($F$2:$F$46,L6,$Q$2:$Q$46,"Aprobada")>0,AND(Resumen!$B$15="La cursada aprobada",COUNTIFS($F$2:$F$46,L6,$Q$2:$Q$46,"Cursada aprobada")>0))),L6&" ","")&IF(NOT(OR(M6="",COUNTIF($F$2:$F$46,M6)=0,COUNTIFS($F$2:$F$46,M6,$Q$2:$Q$46,"Aprobada")>0,AND(Resumen!$B$15="La cursada aprobada",COUNTIFS($F$2:$F$46,M6,$Q$2:$Q$46,"Cursada aprobada")>0))),M6&" ","")&IF(NOT(OR(N6="",COUNTIF($F$2:$F$46,N6)=0,COUNTIFS($F$2:$F$46,N6,$Q$2:$Q$46,"Aprobada")>0,AND(Resumen!$B$15="La cursada aprobada",COUNTIFS($F$2:$F$46,N6,$Q$2:$Q$46,"Cursada aprobada")>0))),N6&" ","")&IF(NOT(OR(O6="",COUNTIF($F$2:$F$46,O6)=0,COUNTIFS($F$2:$F$46,O6,$Q$2:$Q$46,"Aprobada")>0,AND(Resumen!$B$15="La cursada aprobada",COUNTIFS($F$2:$F$46,O6,$Q$2:$Q$46,"Cursada aprobada")>0))),O6&" ","")&IF(NOT(OR(P6="",COUNTIF($F$2:$F$46,P6)=0,COUNTIFS($F$2:$F$46,P6,$Q$2:$Q$46,"Aprobada")>0,AND(Resumen!$B$15="La cursada aprobada",COUNTIFS($F$2:$F$46,P6,$Q$2:$Q$46,"Cursada aprobada")>0))),P6&" ","")),""))
A7: Ciclo básico | C7: 1 | D7: 2 | E7: CS | F7: 205 | G7: Sociología | H7: II | I7: 4 | K7: 64 | Q7: No cursada | R7: =IF(Q7="Aprobada","Ya aprobada",IF(Q7="Cursada aprobada","Ya cursada",IF(AND(OR(L7="",COUNTIF($F$2:$F$46,L7)=0,COUNTIFS($F$2:$F$46,L7,$Q$2:$Q$46,"Aprobada")>0,AND(Resumen!$B$15="La cursada aprobada",COUNTIFS($F$2:$F$46,L7,$Q$2:$Q$46,"Cursada aprobada")>0)),OR(M7="",COUNTIF($F$2:$F$46,M7)=0,COUNTIFS($F$2:$F$46,M7,$Q$2:$Q$46,"Aprobada")>0,AND(Resumen!$B$15="La cursada aprobada",COUNTIFS($F$2:$F$46,M7,$Q$2:$Q$46,"Cursada aprobada")>0)),OR(N7="",COUNTIF($F$2:$F$46,N7)=0,COUNTIFS($F$2:$F$46,N7,$Q$2:$Q$46,"Aprobada")>0,AND(Resumen!$B$15="La cursada aprobada",COUNTIFS($F$2:$F$46,N7,$Q$2:$Q$46,"Cursada aprobada")>0)),OR(O7="",COUNTIF($F$2:$F$46,O7)=0,COUNTIFS($F$2:$F$46,O7,$Q$2:$Q$46,"Aprobada")>0,AND(Resumen!$B$15="La cursada aprobada",COUNTIFS($F$2:$F$46,O7,$Q$2:$Q$46,"Cursada aprobada")>0)),OR(P7="",COUNTIF($F$2:$F$46,P7)=0,COUNTIFS($F$2:$F$46,P7,$Q$2:$Q$46,"Aprobada")>0,AND(Resumen!$B$15="La cursada aprobada",COUNTIFS($F$2:$F$46,P7,$Q$2:$Q$46,"Cursada aprobada")>0))),"Sí","No"))) -> Sí | S7: =TRIM(IF(NOT(OR(L7="",COUNTIF($F$2:$F$46,L7)=0,COUNTIFS($F$2:$F$46,L7,$Q$2:$Q$46,"Aprobada")>0,AND(Resumen!$B$15="La cursada aprobada",COUNTIFS($F$2:$F$46,L7,$Q$2:$Q$46,"Cursada aprobada")>0))),L7&" ","")&IF(NOT(OR(M7="",COUNTIF($F$2:$F$46,M7)=0,COUNTIFS($F$2:$F$46,M7,$Q$2:$Q$46,"Aprobada")>0,AND(Resumen!$B$15="La cursada aprobada",COUNTIFS($F$2:$F$46,M7,$Q$2:$Q$46,"Cursada aprobada")>0))),M7&" ","")&IF(NOT(OR(N7="",COUNTIF($F$2:$F$46,N7)=0,COUNTIFS($F$2:$F$46,N7,$Q$2:$Q$46,"Aprobada")>0,AND(Resumen!$B$15="La cursada aprobada",COUNTIFS($F$2:$F$46,N7,$Q$2:$Q$46,"Cursada aprobada")>0))),N7&" ","")&IF(NOT(OR(O7="",COUNTIF($F$2:$F$46,O7)=0,COUNTIFS($F$2:$F$46,O7,$Q$2:$Q$46,"Aprobada")>0,AND(Resumen!$B$15="La cursada aprobada",COUNTIFS($F$2:$F$46,O7,$Q$2:$Q$46,"Cursada aprobada")>0))),O7&" ","")&IF(NOT(OR(P7="",COUNTIF($F$2:$F$46,P7)=0,COUNTIFS($F$2:$F$46,P7,$Q$2:$Q$46,"Aprobada")>0,AND(Resumen!$B$15="La cursada aprobada",COUNTIFS($F$2:$F$46,P7,$Q$2:$Q$46,"Cursada aprobada")>0))),P7&" ","")) | T7: =IF(Q7="Cursada aprobada",IF(AND(OR(L7="",COUNTIF($F$2:$F$46,L7)=0,COUNTIFS($F$2:$F$46,L7,$Q$2:$Q$46,"Aprobada")>0),OR(M7="",COUNTIF($F$2:$F$46,M7)=0,COUNTIFS($F$2:$F$46,M7,$Q$2:$Q$46,"Aprobada")>0),OR(N7="",COUNTIF($F$2:$F$46,N7)=0,COUNTIFS($F$2:$F$46,N7,$Q$2:$Q$46,"Aprobada")>0),OR(O7="",COUNTIF($F$2:$F$46,O7)=0,COUNTIFS($F$2:$F$46,O7,$Q$2:$Q$46,"Aprobada")>0),OR(P7="",COUNTIF($F$2:$F$46,P7)=0,COUNTIFS($F$2:$F$46,P7,$Q$2:$Q$46,"Aprobada")>0)),"Sí","No"),"") | U7: =IF(Q7="Aprobada",TRIM(IF(NOT(OR(L7="",COUNTIF($F$2:$F$46,L7)=0,COUNTIFS($F$2:$F$46,L7,$Q$2:$Q$46,"Aprobada")>0)),L7&" ","")&IF(NOT(OR(M7="",COUNTIF($F$2:$F$46,M7)=0,COUNTIFS($F$2:$F$46,M7,$Q$2:$Q$46,"Aprobada")>0)),M7&" ","")&IF(NOT(OR(N7="",COUNTIF($F$2:$F$46,N7)=0,COUNTIFS($F$2:$F$46,N7,$Q$2:$Q$46,"Aprobada")>0)),N7&" ","")&IF(NOT(OR(O7="",COUNTIF($F$2:$F$46,O7)=0,COUNTIFS($F$2:$F$46,O7,$Q$2:$Q$46,"Aprobada")>0)),O7&" ","")&IF(NOT(OR(P7="",COUNTIF($F$2:$F$46,P7)=0,COUNTIFS($F$2:$F$46,P7,$Q$2:$Q$46,"Aprobada")>0)),P7&" ","")),IF(Q7="Cursada aprobada",TRIM(IF(NOT(OR(L7="",COUNTIF($F$2:$F$46,L7)=0,COUNTIFS($F$2:$F$46,L7,$Q$2:$Q$46,"Aprobada")>0,AND(Resumen!$B$15="La cursada aprobada",COUNTIFS($F$2:$F$46,L7,$Q$2:$Q$46,"Cursada aprobada")>0))),L7&" ","")&IF(NOT(OR(M7="",COUNTIF($F$2:$F$46,M7)=0,COUNTIFS($F$2:$F$46,M7,$Q$2:$Q$46,"Aprobada")>0,AND(Resumen!$B$15="La cursada aprobada",COUNTIFS($F$2:$F$46,M7,$Q$2:$Q$46,"Cursada aprobada")>0))),M7&" ","")&IF(NOT(OR(N7="",COUNTIF($F$2:$F$46,N7)=0,COUNTIFS($F$2:$F$46,N7,$Q$2:$Q$46,"Aprobada")>0,AND(Resumen!$B$15="La cursada aprobada",COUNTIFS($F$2:$F$46,N7,$Q$2:$Q$46,"Cursada aprobada")>0))),N7&" ","")&IF(NOT(OR(O7="",COUNTIF($F$2:$F$46,O7)=0,COUNTIFS($F$2:$F$46,O7,$Q$2:$Q$46,"Aprobada")>0,AND(Resumen!$B$15="La cursada aprobada",COUNTIFS($F$2:$F$46,O7,$Q$2:$Q$46,"Cursada aprobada")>0))),O7&" ","")&IF(NOT(OR(P7="",COUNTIF($F$2:$F$46,P7)=0,COUNTIFS($F$2:$F$46,P7,$Q$2:$Q$46,"Aprobada")>0,AND(Resumen!$B$15="La cursada aprobada",COUNTIFS($F$2:$F$46,P7,$Q$2:$Q$46,"Cursada aprobada")>0))),P7&" ","")),""))
A8: Ciclo básico | C8: 1 | D8: 2 | E8: MA | F8: 209 | G8: Matemática II | H8: I | I8: 5 | K8: 80 | L8: 102 | Q8: No cursada | R8: =IF(Q8="Aprobada","Ya aprobada",IF(Q8="Cursada aprobada","Ya cursada",IF(AND(OR(L8="",COUNTIF($F$2:$F$46,L8)=0,COUNTIFS($F$2:$F$46,L8,$Q$2:$Q$46,"Aprobada")>0,AND(Resumen!$B$15="La cursada aprobada",COUNTIFS($F$2:$F$46,L8,$Q$2:$Q$46,"Cursada aprobada")>0)),OR(M8="",COUNTIF($F$2:$F$46,M8)=0,COUNTIFS($F$2:$F$46,M8,$Q$2:$Q$46,"Aprobada")>0,AND(Resumen!$B$15="La cursada aprobada",COUNTIFS($F$2:$F$46,M8,$Q$2:$Q$46,"Cursada aprobada")>0)),OR(N8="",COUNTIF($F$2:$F$46,N8)=0,COUNTIFS($F$2:$F$46,N8,$Q$2:$Q$46,"Aprobada")>0,AND(Resumen!$B$15="La cursada aprobada",COUNTIFS($F$2:$F$46,N8,$Q$2:$Q$46,"Cursada aprobada")>0)),OR(O8="",COUNTIF($F$2:$F$46,O8)=0,COUNTIFS($F$2:$F$46,O8,$Q$2:$Q$46,"Aprobada")>0,AND(Resumen!$B$15="La cursada aprobada",COUNTIFS($F$2:$F$46,O8,$Q$2:$Q$46,"Cursada aprobada")>0)),OR(P8="",COUNTIF($F$2:$F$46,P8)=0,COUNTIFS($F$2:$F$46,P8,$Q$2:$Q$46,"Aprobada")>0,AND(Resumen!$B$15="La cursada aprobada",COUNTIFS($F$2:$F$46,P8,$Q$2:$Q$46,"Cursada aprobada")>0))),"Sí","No"))) -> No | S8: =TRIM(IF(NOT(OR(L8="",COUNTIF($F$2:$F$46,L8)=0,COUNTIFS($F$2:$F$46,L8,$Q$2:$Q$46,"Aprobada")>0,AND(Resumen!$B$15="La cursada aprobada",COUNTIFS($F$2:$F$46,L8,$Q$2:$Q$46,"Cursada aprobada")>0))),L8&" ","")&IF(NOT(OR(M8="",COUNTIF($F$2:$F$46,M8)=0,COUNTIFS($F$2:$F$46,M8,$Q$2:$Q$46,"Aprobada")>0,AND(Resumen!$B$15="La cursada aprobada",COUNTIFS($F$2:$F$46,M8,$Q$2:$Q$46,"Cursada aprobada")>0))),M8&" ","")&IF(NOT(OR(N8="",COUNTIF($F$2:$F$46,N8)=0,COUNTIFS($F$2:$F$46,N8,$Q$2:$Q$46,"Aprobada")>0,AND(Resumen!$B$15="La cursada aprobada",COUNTIFS($F$2:$F$46,N8,$Q$2:$Q$46,"Cursada aprobada")>0))),N8&" ","")&IF(NOT(OR(O8="",COUNTIF($F$2:$F$46,O8)=0,COUNTIFS($F$2:$F$46,O8,$Q$2:$Q$46,"Aprobada")>0,AND(Resumen!$B$15="La cursada aprobada",COUNTIFS($F$2:$F$46,O8,$Q$2:$Q$46,"Cursada aprobada")>0))),O8&" ","")&IF(NOT(OR(P8="",COUNTIF($F$2:$F$46,P8)=0,COUNTIFS($F$2:$F$46,P8,$Q$2:$Q$46,"Aprobada")>0,AND(Resumen!$B$15="La cursada aprobada",COUNTIFS($F$2:$F$46,P8,$Q$2:$Q$46,"Cursada aprobada")>0))),P8&" ","")) -> 102 | T8: =IF(Q8="Cursada aprobada",IF(AND(OR(L8="",COUNTIF($F$2:$F$46,L8)=0,COUNTIFS($F$2:$F$46,L8,$Q$2:$Q$46,"Aprobada")>0),OR(M8="",COUNTIF($F$2:$F$46,M8)=0,COUNTIFS($F$2:$F$46,M8,$Q$2:$Q$46,"Aprobada")>0),OR(N8="",COUNTIF($F$2:$F$46,N8)=0,COUNTIFS($F$2:$F$46,N8,$Q$2:$Q$46,"Aprobada")>0),OR(O8="",COUNTIF($F$2:$F$46,O8)=0,COUNTIFS($F$2:$F$46,O8,$Q$2:$Q$46,"Aprobada")>0),OR(P8="",COUNTIF($F$2:$F$46,P8)=0,COUNTIFS($F$2:$F$46,P8,$Q$2:$Q$46,"Aprobada")>0)),"Sí","No"),"") | U8: =IF(Q8="Aprobada",TRIM(IF(NOT(OR(L8="",COUNTIF($F$2:$F$46,L8)=0,COUNTIFS($F$2:$F$46,L8,$Q$2:$Q$46,"Aprobada")>0)),L8&" ","")&IF(NOT(OR(M8="",COUNTIF($F$2:$F$46,M8)=0,COUNTIFS($F$2:$F$46,M8,$Q$2:$Q$46,"Aprobada")>0)),M8&" ","")&IF(NOT(OR(N8="",COUNTIF($F$2:$F$46,N8)=0,COUNTIFS($F$2:$F$46,N8,$Q$2:$Q$46,"Aprobada")>0)),N8&" ","")&IF(NOT(OR(O8="",COUNTIF($F$2:$F$46,O8)=0,COUNTIFS($F$2:$F$46,O8,$Q$2:$Q$46,"Aprobada")>0)),O8&" ","")&IF(NOT(OR(P8="",COUNTIF($F$2:$F$46,P8)=0,COUNTIFS($F$2:$F$46,P8,$Q$2:$Q$46,"Aprobada")>0)),P8&" ","")),IF(Q8="Cursada aprobada",TRIM(IF(NOT(OR(L8="",COUNTIF($F$2:$F$46,L8)=0,COUNTIFS($F$2:$F$46,L8,$Q$2:$Q$46,"Aprobada")>0,AND(Resumen!$B$15="La cursada aprobada",COUNTIFS($F$2:$F$46,L8,$Q$2:$Q$46,"Cursada aprobada")>0))),L8&" ","")&IF(NOT(OR(M8="",COUNTIF($F$2:$F$46,M8)=0,COUNTIFS($F$2:$F$46,M8,$Q$2:$Q$46,"Aprobada")>0,AND(Resumen!$B$15="La cursada aprobada",COUNTIFS($F$2:$F$46,M8,$Q$2:$Q$46,"Cursada aprobada")>0))),M8&" ","")&IF(NOT(OR(N8="",COUNTIF($F$2:$F$46,N8)=0,COUNTIFS($F$2:$F$46,N8,$Q$2:$Q$46,"Aprobada")>0,AND(Resumen!$B$15="La cursada aprobada",COUNTIFS($F$2:$F$46,N8,$Q$2:$Q$46,"Cursada aprobada")>0))),N8&" ","")&IF(NOT(OR(O8="",COUNTIF($F$2:$F$46,O8)=0,COUNTIFS($F$2:$F$46,O8,$Q$2:$Q$46,"Aprobada")>0,AND(Resumen!$B$15="La cursada aprobada",COUNTIFS($F$2:$F$46,O8,$Q$2:$Q$46,"Cursada aprobada")>0))),O8&" ","")&IF(NOT(OR(P8="",COUNTIF($F$2:$F$46,P8)=0,COUNTIFS($F$2:$F$46,P8,$Q$2:$Q$46,"Aprobada")>0,AND(Resumen!$B$15="La cursada aprobada",COUNTIFS($F$2:$F$46,P8,$Q$2:$Q$46,"Cursada aprobada")>0))),P8&" ","")),""))
A9: Ciclo básico | C9: 2 | D9: 1 | E9: EC | F9: 314 | G9: Macroeconomía I | H9: I | I9: 6 | K9: 96 | L9: 101 | M9: 209 | Q9: No cursada | R9: =IF(Q9="Aprobada","Ya aprobada",IF(Q9="Cursada aprobada","Ya cursada",IF(AND(OR(L9="",COUNTIF($F$2:$F$46,L9)=0,COUNTIFS($F$2:$F$46,L9,$Q$2:$Q$46,"Aprobada")>0,AND(Resumen!$B$15="La cursada aprobada",COUNTIFS($F$2:$F$46,L9,$Q$2:$Q$46,"Cursada aprobada")>0)),OR(M9="",COUNTIF($F$2:$F$46,M9)=0,COUNTIFS($F$2:$F$46,M9,$Q$2:$Q$46,"Aprobada")>0,AND(Resumen!$B$15="La cursada aprobada",COUNTIFS($F$2:$F$46,M9,$Q$2:$Q$46,"Cursada aprobada")>0)),OR(N9="",COUNTIF($F$2:$F$46,N9)=0,COUNTIFS($F$2:$F$46,N9,$Q$2:$Q$46,"Aprobada")>0,AND(Resumen!$B$15="La cursada aprobada",COUNTIFS($F$2:$F$46,N9,$Q$2:$Q$46,"Cursada aprobada")>0)),OR(O9="",COUNTIF($F$2:$F$46,O9)=0,COUNTIFS($F$2:$F$46,O9,$Q$2:$Q$46,"Aprobada")>0,AND(Resumen!$B$15="La cursada aprobada",COUNTIFS($F$2:$F$46,O9,$Q$2:$Q$46,"Cursada aprobada")>0)),OR(P9="",COUNTIF($F$2:$F$46,P9)=0,COUNTIFS($F$2:$F$46,P9,$Q$2:$Q$46,"Aprobada")>0,AND(Resumen!$B$15="La cursada aprobada",COUNTIFS($F$2:$F$46,P9,$Q$2:$Q$46,"Cursada aprobada")>0))),"Sí","No"))) -> No | S9: =TRIM(IF(NOT(OR(L9="",COUNTIF($F$2:$F$46,L9)=0,COUNTIFS($F$2:$F$46,L9,$Q$2:$Q$46,"Aprobada")>0,AND(Resumen!$B$15="La cursada aprobada",COUNTIFS($F$2:$F$46,L9,$Q$2:$Q$46,"Cursada aprobada")>0))),L9&" ","")&IF(NOT(OR(M9="",COUNTIF($F$2:$F$46,M9)=0,COUNTIFS($F$2:$F$46,M9,$Q$2:$Q$46,"Aprobada")>0,AND(Resumen!$B$15="La cursada aprobada",COUNTIFS($F$2:$F$46,M9,$Q$2:$Q$46,"Cursada aprobada")>0))),M9&" ","")&IF(NOT(OR(N9="",COUNTIF($F$2:$F$46,N9)=0,COUNTIFS($F$2:$F$46,N9,$Q$2:$Q$46,"Aprobada")>0,AND(Resumen!$B$15="La cursada aprobada",COUNTIFS($F$2:$F$46,N9,$Q$2:$Q$46,"Cursada aprobada")>0))),N9&" ","")&IF(NOT(OR(O9="",COUNTIF($F$2:$F$46,O9)=0,COUNTIFS($F$2:$F$46,O9,$Q$2:$Q$46,"Aprobada")>0,AND(Resumen!$B$15="La cursada aprobada",COUNTIFS($F$2:$F$46,O9,$Q$2:$Q$46,"Cursada aprobada")>0))),O9&" ","")&IF(NOT(OR(P9="",COUNTIF($F$2:$F$46,P9)=0,COUNTIFS($F$2:$F$46,P9,$Q$2:$Q$46,"Aprobada")>0,AND(Resumen!$B$15="La cursada aprobada",COUNTIFS($F$2:$F$46,P9,$Q$2:$Q$46,"Cursada aprobada")>0))),P9&" ","")) -> 101 209 | T9: =IF(Q9="Cursada aprobada",IF(AND(OR(L9="",COUNTIF($F$2:$F$46,L9)=0,COUNTIFS($F$2:$F$46,L9,$Q$2:$Q$46,"Aprobada")>0),OR(M9="",COUNTIF($F$2:$F$46,M9)=0,COUNTIFS($F$2:$F$46,M9,$Q$2:$Q$46,"Aprobada")>0),OR(N9="",COUNTIF($F$2:$F$46,N9)=0,COUNTIFS($F$2:$F$46,N9,$Q$2:$Q$46,"Aprobada")>0),OR(O9="",COUNTIF($F$2:$F$46,O9)=0,COUNTIFS($F$2:$F$46,O9,$Q$2:$Q$46,"Aprobada")>0),OR(P9="",COUNTIF($F$2:$F$46,P9)=0,COUNTIFS($F$2:$F$46,P9,$Q$2:$Q$46,"Aprobada")>0)),"Sí","No"),"") | U9: =IF(Q9="Aprobada",TRIM(IF(NOT(OR(L9="",COUNTIF($F$2:$F$46,L9)=0,COUNTIFS($F$2:$F$46,L9,$Q$2:$Q$46,"Aprobada")>0)),L9&" ","")&IF(NOT(OR(M9="",COUNTIF($F$2:$F$46,M9)=0,COUNTIFS($F$2:$F$46,M9,$Q$2:$Q$46,"Aprobada")>0)),M9&" ","")&IF(NOT(OR(N9="",COUNTIF($F$2:$F$46,N9)=0,COUNTIFS($F$2:$F$46,N9,$Q$2:$Q$46,"Aprobada")>0)),N9&" ","")&IF(NOT(OR(O9="",COUNTIF($F$2:$F$46,O9)=0,COUNTIFS($F$2:$F$46,O9,$Q$2:$Q$46,"Aprobada")>0)),O9&" ","")&IF(NOT(OR(P9="",COUNTIF($F$2:$F$46,P9)=0,COUNTIFS($F$2:$F$46,P9,$Q$2:$Q$46,"Aprobada")>0)),P9&" ","")),IF(Q9="Cursada aprobada",TRIM(IF(NOT(OR(L9="",COUNTIF($F$2:$F$46,L9)=0,COUNTIFS($F$2:$F$46,L9,$Q$2:$Q$46,"Aprobada")>0,AND(Resumen!$B$15="La cursada aprobada",COUNTIFS($F$2:$F$46,L9,$Q$2:$Q$46,"Cursada aprobada")>0))),L9&" ","")&IF(NOT(OR(M9="",COUNTIF($F$2:$F$46,M9)=0,COUNTIFS($F$2:$F$46,M9,$Q$2:$Q$46,"Aprobada")>0,AND(Resumen!$B$15="La cursada aprobada",COUNTIFS($F$2:$F$46,M9,$Q$2:$Q$46,"Cursada aprobada")>0))),M9&" ","")&IF(NOT(OR(N9="",COUNTIF($F$2:$F$46,N9)=0,COUNTIFS($F$2:$F$46,N9,$Q$2:$Q$46,"Aprobada")>0,AND(Resumen!$B$15="La cursada aprobada",COUNTIFS($F$2:$F$46,N9,$Q$2:$Q$46,"Cursada aprobada")>0))),N9&" ","")&IF(NOT(OR(O9="",COUNTIF($F$2:$F$46,O9)=0,COUNTIFS($F$2:$F$46,O9,$Q$2:$Q$46,"Aprobada")>0,AND(Resumen!$B$15="La cursada aprobada",COUNTIFS($F$2:$F$46,O9,$Q$2:$Q$46,"Cursada aprobada")>0))),O9&" ","")&IF(NOT(OR(P9="",COUNTIF($F$2:$F$46,P9)=0,COUNTIFS($F$2:$F$46,P9,$Q$2:$Q$46,"Aprobada")>0,AND(Resumen!$B$15="La cursada aprobada",COUNTIFS($F$2:$F$46,P9,$Q$2:$Q$46,"Cursada aprobada")>0))),P9&" ","")),""))
A10: Ciclo básico | C10: 2 | D10: 1 | E10: AD | F10: 308 | G10: Funciones Organizacionales | H10: I | I10: 6 | K10: 96 | L10: 104 | Q10: No cursada | R10: =IF(Q10="Aprobada","Ya aprobada",IF(Q10="Cursada aprobada","Ya cursada",IF(AND(OR(L10="",COUNTIF($F$2:$F$46,L10)=0,COUNTIFS($F$2:$F$46,L10,$Q$2:$Q$46,"Aprobada")>0,AND(Resumen!$B$15="La cursada aprobada",COUNTIFS($F$2:$F$46,L10,$Q$2:$Q$46,"Cursada aprobada")>0)),OR(M10="",COUNTIF($F$2:$F$46,M10)=0,COUNTIFS($F$2:$F$46,M10,$Q$2:$Q$46,"Aprobada")>0,AND(Resumen!$B$15="La cursada aprobada",COUNTIFS($F$2:$F$46,M10,$Q$2:$Q$46,"Cursada aprobada")>0)),OR(N10="",COUNTIF($F$2:$F$46,N10)=0,COUNTIFS($F$2:$F$46,N10,$Q$2:$Q$46,"Aprobada")>0,AND(Resumen!$B$15="La cursada aprobada",COUNTIFS($F$2:$F$46,N10,$Q$2:$Q$46,"Cursada aprobada")>0)),OR(O10="",COUNTIF($F$2:$F$46,O10)=0,COUNTIFS($F$2:$F$46,O10,$Q$2:$Q$46,"Aprobada")>0,AND(Resumen!$B$15="La cursada aprobada",COUNTIFS($F$2:$F$46,O10,$Q$2:$Q$46,"Cursada aprobada")>0)),OR(P10="",COUNTIF($F$2:$F$46,P10)=0,COUNTIFS($F$2:$F$46,P10,$Q$2:$Q$46,"Aprobada")>0,AND(Resumen!$B$15="La cursada aprobada",COUNTIFS($F$2:$F$46,P10,$Q$2:$Q$46,"Cursada aprobada")>0))),"Sí","No"))) -> No | S10: =TRIM(IF(NOT(OR(L10="",COUNTIF($F$2:$F$46,L10)=0,COUNTIFS($F$2:$F$46,L10,$Q$2:$Q$46,"Aprobada")>0,AND(Resumen!$B$15="La cursada aprobada",COUNTIFS($F$2:$F$46,L10,$Q$2:$Q$46,"Cursada aprobada")>0))),L10&" ","")&IF(NOT(OR(M10="",COUNTIF($F$2:$F$46,M10)=0,COUNTIFS($F$2:$F$46,M10,$Q$2:$Q$46,"Aprobada")>0,AND(Resumen!$B$15="La cursada aprobada",COUNTIFS($F$2:$F$46,M10,$Q$2:$Q$46,"Cursada aprobada")>0))),M10&" ","")&IF(NOT(OR(N10="",COUNTIF($F$2:$F$46,N10)=0,COUNTIFS($F$2:$F$46,N10,$Q$2:$Q$46,"Aprobada")>0,AND(Resumen!$B$15="La cursada aprobada",COUNTIFS($F$2:$F$46,N10,$Q$2:$Q$46,"Cursada aprobada")>0))),N10&" ","")&IF(NOT(OR(O10="",COUNTIF($F$2:$F$46,O10)=0,COUNTIFS($F$2:$F$46,O10,$Q$2:$Q$46,"Aprobada")>0,AND(Resumen!$B$15="La cursada aprobada",COUNTIFS($F$2:$F$46,O10,$Q$2:$Q$46,"Cursada aprobada")>0))),O10&" ","")&IF(NOT(OR(P10="",COUNTIF($F$2:$F$46,P10)=0,COUNTIFS($F$2:$F$46,P10,$Q$2:$Q$46,"Aprobada")>0,AND(Resumen!$B$15="La cursada aprobada",COUNTIFS($F$2:$F$46,P10,$Q$2:$Q$46,"Cursada aprobada")>0))),P10&" ","")) -> 104 | T10: =IF(Q10="Cursada aprobada",IF(AND(OR(L10="",COUNTIF($F$2:$F$46,L10)=0,COUNTIFS($F$2:$F$46,L10,$Q$2:$Q$46,"Aprobada")>0),OR(M10="",COUNTIF($F$2:$F$46,M10)=0,COUNTIFS($F$2:$F$46,M10,$Q$2:$Q$46,"Aprobada")>0),OR(N10="",COUNTIF($F$2:$F$46,N10)=0,COUNTIFS($F$2:$F$46,N10,$Q$2:$Q$46,"Aprobada")>0),OR(O10="",COUNTIF($F$2:$F$46,O10)=0,COUNTIFS($F$2:$F$46,O10,$Q$2:$Q$46,"Aprobada")>0),OR(P10="",COUNTIF($F$2:$F$46,P10)=0,COUNTIFS($F$2:$F$46,P10,$Q$2:$Q$46,"Aprobada")>0)),"Sí","No"),"") | U10: =IF(Q10="Aprobada",TRIM(IF(NOT(OR(L10="",COUNTIF($F$2:$F$46,L10)=0,COUNTIFS($F$2:$F$46,L10,$Q$2:$Q$46,"Aprobada")>0)),L10&" ","")&IF(NOT(OR(M10="",COUNTIF($F$2:$F$46,M10)=0,COUNTIFS($F$2:$F$46,M10,$Q$2:$Q$46,"Aprobada")>0)),M10&" ","")&IF(NOT(OR(N10="",COUNTIF($F$2:$F$46,N10)=0,COUNTIFS($F$2:$F$46,N10,$Q$2:$Q$46,"Aprobada")>0)),N10&" ","")&IF(NOT(OR(O10="",COUNTIF($F$2:$F$46,O10)=0,COUNTIFS($F$2:$F$46,O10,$Q$2:$Q$46,"Aprobada")>0)),O10&" ","")&IF(NOT(OR(P10="",COUNTIF($F$2:$F$46,P10)=0,COUNTIFS($F$2:$F$46,P10,$Q$2:$Q$46,"Aprobada")>0)),P10&" ","")),IF(Q10="Cursada aprobada",TRIM(IF(NOT(OR(L10="",COUNTIF($F$2:$F$46,L10)=0,COUNTIFS($F$2:$F$46,L10,$Q$2:$Q$46,"Aprobada")>0,AND(Resumen!$B$15="La cursada aprobada",COUNTIFS($F$2:$F$46,L10,$Q$2:$Q$46,"Cursada aprobada")>0))),L10&" ","")&IF(NOT(OR(M10="",COUNTIF($F$2:$F$46,M10)=0,COUNTIFS($F$2:$F$46,M10,$Q$2:$Q$46,"Aprobada")>0,AND(Resumen!$B$15="La cursada aprobada",COUNTIFS($F$2:$F$46,M10,$Q$2:$Q$46,"Cursada aprobada")>0))),M10&" ","")&IF(NOT(OR(N10="",COUNTIF($F$2:$F$46,N10)=0,COUNTIFS($F$2:$F$46,N10,$Q$2:$Q$46,"Aprobada")>0,AND(Resumen!$B$15="La cursada aprobada",COUNTIFS($F$2:$F$46,N10,$Q$2:$Q$46,"Cursada aprobada")>0))),N10&" ","")&IF(NOT(OR(O10="",COUNTIF($F$2:$F$46,O10)=0,COUNTIFS($F$2:$F$46,O10,$Q$2:$Q$46,"Aprobada")>0,AND(Resumen!$B$15="La cursada aprobada",COUNTIFS($F$2:$F$46,O10,$Q$2:$Q$46,"Cursada aprobada")>0))),O10&" ","")&IF(NOT(OR(P10="",COUNTIF($F$2:$F$46,P10)=0,COUNTIFS($F$2:$F$46,P10,$Q$2:$Q$46,"Aprobada")>0,AND(Resumen!$B$15="La cursada aprobada",COUNTIFS($F$2:$F$46,P10,$Q$2:$Q$46,"Cursada aprobada")>0))),P10&" ","")),""))
A11: Ciclo básico | C11: 2 | D11: 1 | E11: CS | F11: 280 | G11: Historia Económica y Social II | H11: II | I11: 4 | K11: 64 | L11: 180 | Q11: No cursada | R11: =IF(Q11="Aprobada","Ya aprobada",IF(Q11="Cursada aprobada","Ya cursada",IF(AND(OR(L11="",COUNTIF($F$2:$F$46,L11)=0,COUNTIFS($F$2:$F$46,L11,$Q$2:$Q$46,"Aprobada")>0,AND(Resumen!$B$15="La cursada aprobada",COUNTIFS($F$2:$F$46,L11,$Q$2:$Q$46,"Cursada aprobada")>0)),OR(M11="",COUNTIF($F$2:$F$46,M11)=0,COUNTIFS($F$2:$F$46,M11,$Q$2:$Q$46,"Aprobada")>0,AND(Resumen!$B$15="La cursada aprobada",COUNTIFS($F$2:$F$46,M11,$Q$2:$Q$46,"Cursada aprobada")>0)),OR(N11="",COUNTIF($F$2:$F$46,N11)=0,COUNTIFS($F$2:$F$46,N11,$Q$2:$Q$46,"Aprobada")>0,AND(Resumen!$B$15="La cursada aprobada",COUNTIFS($F$2:$F$46,N11,$Q$2:$Q$46,"Cursada aprobada")>0)),OR(O11="",COUNTIF($F$2:$F$46,O11)=0,COUNTIFS($F$2:$F$46,O11,$Q$2:$Q$46,"Aprobada")>0,AND(Resumen!$B$15="La cursada aprobada",COUNTIFS($F$2:$F$46,O11,$Q$2:$Q$46,"Cursada aprobada")>0)),OR(P11="",COUNTIF($F$2:$F$46,P11)=0,COUNTIFS($F$2:$F$46,P11,$Q$2:$Q$46,"Aprobada")>0,AND(Resumen!$B$15="La cursada aprobada",COUNTIFS($F$2:$F$46,P11,$Q$2:$Q$46,"Cursada aprobada")>0))),"Sí","No"))) -> No | S11: =TRIM(IF(NOT(OR(L11="",COUNTIF($F$2:$F$46,L11)=0,COUNTIFS($F$2:$F$46,L11,$Q$2:$Q$46,"Aprobada")>0,AND(Resumen!$B$15="La cursada aprobada",COUNTIFS($F$2:$F$46,L11,$Q$2:$Q$46,"Cursada aprobada")>0))),L11&" ","")&IF(NOT(OR(M11="",COUNTIF($F$2:$F$46,M11)=0,COUNTIFS($F$2:$F$46,M11,$Q$2:$Q$46,"Aprobada")>0,AND(Resumen!$B$15="La cursada aprobada",COUNTIFS($F$2:$F$46,M11,$Q$2:$Q$46,"Cursada aprobada")>0))),M11&" ","")&IF(NOT(OR(N11="",COUNTIF($F$2:$F$46,N11)=0,COUNTIFS($F$2:$F$46,N11,$Q$2:$Q$46,"Aprobada")>0,AND(Resumen!$B$15="La cursada aprobada",COUNTIFS($F$2:$F$46,N11,$Q$2:$Q$46,"Cursada aprobada")>0))),N11&" ","")&IF(NOT(OR(O11="",COUNTIF($F$2:$F$46,O11)=0,COUNTIFS($F$2:$F$46,O11,$Q$2:$Q$46,"Aprobada")>0,AND(Resumen!$B$15="La cursada aprobada",COUNTIFS($F$2:$F$46,O11,$Q$2:$Q$46,"Cursada aprobada")>0))),O11&" ","")&IF(NOT(OR(P11="",COUNTIF($F$2:$F$46,P11)=0,COUNTIFS($F$2:$F$46,P11,$Q$2:$Q$46,"Aprobada")>0,AND(Resumen!$B$15="La cursada aprobada",COUNTIFS($F$2:$F$46,P11,$Q$2:$Q$46,"Cursada aprobada")>0))),P11&" ","")) -> 180 | T11: =IF(Q11="Cursada aprobada",IF(AND(OR(L11="",COUNTIF($F$2:$F$46,L11)=0,COUNTIFS($F$2:$F$46,L11,$Q$2:$Q$46,"Aprobada")>0),OR(M11="",COUNTIF($F$2:$F$46,M11)=0,COUNTIFS($F$2:$F$46,M11,$Q$2:$Q$46,"Aprobada")>0),OR(N11="",COUNTIF($F$2:$F$46,N11)=0,COUNTIFS($F$2:$F$46,N11,$Q$2:$Q$46,"Aprobada")>0),OR(O11="",COUNTIF($F$2:$F$46,O11)=0,COUNTIFS($F$2:$F$46,O11,$Q$2:$Q$46,"Aprobada")>0),OR(P11="",COUNTIF($F$2:$F$46,P11)=0,COUNTIFS($F$2:$F$46,P11,$Q$2:$Q$46,"Aprobada")>0)),"Sí","No"),"") | U11: =IF(Q11="Aprobada",TRIM(IF(NOT(OR(L11="",COUNTIF($F$2:$F$46,L11)=0,COUNTIFS($F$2:$F$46,L11,$Q$2:$Q$46,"Aprobada")>0)),L11&" ","")&IF(NOT(OR(M11="",COUNTIF($F$2:$F$46,M11)=0,COUNTIFS($F$2:$F$46,M11,$Q$2:$Q$46,"Aprobada")>0)),M11&" ","")&IF(NOT(OR(N11="",COUNTIF($F$2:$F$46,N11)=0,COUNTIFS($F$2:$F$46,N11,$Q$2:$Q$46,"Aprobada")>0)),N11&" ","")&IF(NOT(OR(O11="",COUNTIF($F$2:$F$46,O11)=0,COUNTIFS($F$2:$F$46,O11,$Q$2:$Q$46,"Aprobada")>0)),O11&" ","")&IF(NOT(OR(P11="",COUNTIF($F$2:$F$46,P11)=0,COUNTIFS($F$2:$F$46,P11,$Q$2:$Q$46,"Aprobada")>0)),P11&" ","")),IF(Q11="Cursada aprobada",TRIM(IF(NOT(OR(L11="",COUNTIF($F$2:$F$46,L11)=0,COUNTIFS($F$2:$F$46,L11,$Q$2:$Q$46,"Aprobada")>0,AND(Resumen!$B$15="La cursada aprobada",COUNTIFS($F$2:$F$46,L11,$Q$2:$Q$46,"Cursada aprobada")>0))),L11&" ","")&IF(NOT(OR(M11="",COUNTIF($F$2:$F$46,M11)=0,COUNTIFS($F$2:$F$46,M11,$Q$2:$Q$46,"Aprobada")>0,AND(Resumen!$B$15="La cursada aprobada",COUNTIFS($F$2:$F$46,M11,$Q$2:$Q$46,"Cursada aprobada")>0))),M11&" ","")&IF(NOT(OR(N11="",COUNTIF($F$2:$F$46,N11)=0,COUNTIFS($F$2:$F$46,N11,$Q$2:$Q$46,"Aprobada")>0,AND(Resumen!$B$15="La cursada aprobada",COUNTIFS($F$2:$F$46,N11,$Q$2:$Q$46,"Cursada aprobada")>0))),N11&" ","")&IF(NOT(OR(O11="",COUNTIF($F$2:$F$46,O11)=0,COUNTIFS($F$2:$F$46,O11,$Q$2:$Q$46,"Aprobada")>0,AND(Resumen!$B$15="La cursada aprobada",COUNTIFS($F$2:$F$46,O11,$Q$2:$Q$46,"Cursada aprobada")>0))),O11&" ","")&IF(NOT(OR(P11="",COUNTIF($F$2:$F$46,P11)=0,COUNTIFS($F$2:$F$46,P11,$Q$2:$Q$46,"Aprobada")>0,AND(Resumen!$B$15="La cursada aprobada",COUNTIFS($F$2:$F$46,P11,$Q$2:$Q$46,"Cursada aprobada")>0))),P11&" ","")),""))
A12: Ciclo básico | C12: 2 | D12: 1 | E12: JU | F12: 202 | G12: Derecho Constitucional | H12: II | I12: 4 | J12: 32 | Q12: No cursada | R12: =IF(Q12="Aprobada","Ya aprobada",IF(Q12="Cursada aprobada","Ya cursada",IF(AND(OR(L12="",COUNTIF($F$2:$F$46,L12)=0,COUNTIFS($F$2:$F$46,L12,$Q$2:$Q$46,"Aprobada")>0,AND(Resumen!$B$15="La cursada aprobada",COUNTIFS($F$2:$F$46,L12,$Q$2:$Q$46,"Cursada aprobada")>0)),OR(M12="",COUNTIF($F$2:$F$46,M12)=0,COUNTIFS($F$2:$F$46,M12,$Q$2:$Q$46,"Aprobada")>0,AND(Resumen!$B$15="La cursada aprobada",COUNTIFS($F$2:$F$46,M12,$Q$2:$Q$46,"Cursada aprobada")>0)),OR(N12="",COUNTIF($F$2:$F$46,N12)=0,COUNTIFS($F$2:$F$46,N12,$Q$2:$Q$46,"Aprobada")>0,AND(Resumen!$B$15="La cursada aprobada",COUNTIFS($F$2:$F$46,N12,$Q$2:$Q$46,"Cursada aprobada")>0)),OR(O12="",COUNTIF($F$2:$F$46,O12)=0,COUNTIFS($F$2:$F$46,O12,$Q$2:$Q$46,"Aprobada")>0,AND(Resumen!$B$15="La cursada aprobada",COUNTIFS($F$2:$F$46,O12,$Q$2:$Q$46,"Cursada aprobada")>0)),OR(P12="",COUNTIF($F$2:$F$46,P12)=0,COUNTIFS($F$2:$F$46,P12,$Q$2:$Q$46,"Aprobada")>0,AND(Resumen!$B$15="La cursada aprobada",COUNTIFS($F$2:$F$46,P12,$Q$2:$Q$46,"Cursada aprobada")>0))),"Sí","No"))) -> Sí | S12: =TRIM(IF(NOT(OR(L12="",COUNTIF($F$2:$F$46,L12)=0,COUNTIFS($F$2:$F$46,L12,$Q$2:$Q$46,"Aprobada")>0,AND(Resumen!$B$15="La cursada aprobada",COUNTIFS($F$2:$F$46,L12,$Q$2:$Q$46,"Cursada aprobada")>0))),L12&" ","")&IF(NOT(OR(M12="",COUNTIF($F$2:$F$46,M12)=0,COUNTIFS($F$2:$F$46,M12,$Q$2:$Q$46,"Aprobada")>0,AND(Resumen!$B$15="La cursada aprobada",COUNTIFS($F$2:$F$46,M12,$Q$2:$Q$46,"Cursada aprobada")>0))),M12&" ","")&IF(NOT(OR(N12="",COUNTIF($F$2:$F$46,N12)=0,COUNTIFS($F$2:$F$46,N12,$Q$2:$Q$46,"Aprobada")>0,AND(Resumen!$B$15="La cursada aprobada",COUNTIFS($F$2:$F$46,N12,$Q$2:$Q$46,"Cursada aprobada")>0))),N12&" ","")&IF(NOT(OR(O12="",COUNTIF($F$2:$F$46,O12)=0,COUNTIFS($F$2:$F$46,O12,$Q$2:$Q$46,"Aprobada")>0,AND(Resumen!$B$15="La cursada aprobada",COUNTIFS($F$2:$F$46,O12,$Q$2:$Q$46,"Cursada aprobada")>0))),O12&" ","")&IF(NOT(OR(P12="",COUNTIF($F$2:$F$46,P12)=0,COUNTIFS($F$2:$F$46,P12,$Q$2:$Q$46,"Aprobada")>0,AND(Resumen!$B$15="La cursada aprobada",COUNTIFS($F$2:$F$46,P12,$Q$2:$Q$46,"Cursada aprobada")>0))),P12&" ","")) | T12: =IF(Q12="Cursada aprobada",IF(AND(OR(L12="",COUNTIF($F$2:$F$46,L12)=0,COUNTIFS($F$2:$F$46,L12,$Q$2:$Q$46,"Aprobada")>0),OR(M12="",COUNTIF($F$2:$F$46,M12)=0,COUNTIFS($F$2:$F$46,M12,$Q$2:$Q$46,"Aprobada")>0),OR(N12="",COUNTIF($F$2:$F$46,N12)=0,COUNTIFS($F$2:$F$46,N12,$Q$2:$Q$46,"Aprobada")>0),OR(O12="",COUNTIF($F$2:$F$46,O12)=0,COUNTIFS($F$2:$F$46,O12,$Q$2:$Q$46,"Aprobada")>0),OR(P12="",COUNTIF($F$2:$F$46,P12)=0,COUNTIFS($F$2:$F$46,P12,$Q$2:$Q$46,"Aprobada")>0)),"Sí","No"),"") | U12: =IF(Q12="Aprobada",TRIM(IF(NOT(OR(L12="",COUNTIF($F$2:$F$46,L12)=0,COUNTIFS($F$2:$F$46,L12,$Q$2:$Q$46,"Aprobada")>0)),L12&" ","")&IF(NOT(OR(M12="",COUNTIF($F$2:$F$46,M12)=0,COUNTIFS($F$2:$F$46,M12,$Q$2:$Q$46,"Aprobada")>0)),M12&" ","")&IF(NOT(OR(N12="",COUNTIF($F$2:$F$46,N12)=0,COUNTIFS($F$2:$F$46,N12,$Q$2:$Q$46,"Aprobada")>0)),N12&" ","")&IF(NOT(OR(O12="",COUNTIF($F$2:$F$46,O12)=0,COUNTIFS($F$2:$F$46,O12,$Q$2:$Q$46,"Aprobada")>0)),O12&" ","")&IF(NOT(OR(P12="",COUNTIF($F$2:$F$46,P12)=0,COUNTIFS($F$2:$F$46,P12,$Q$2:$Q$46,"Aprobada")>0)),P12&" ","")),IF(Q12="Cursada aprobada",TRIM(IF(NOT(OR(L12="",COUNTIF($F$2:$F$46,L12)=0,COUNTIFS($F$2:$F$46,L12,$Q$2:$Q$46,"Aprobada")>0,AND(Resumen!$B$15="La cursada aprobada",COUNTIFS($F$2:$F$46,L12,$Q$2:$Q$46,"Cursada aprobada")>0))),L12&" ","")&IF(NOT(OR(M12="",COUNTIF($F$2:$F$46,M12)=0,COUNTIFS($F$2:$F$46,M12,$Q$2:$Q$46,"Aprobada")>0,AND(Resumen!$B$15="La cursada aprobada",COUNTIFS($F$2:$F$46,M12,$Q$2:$Q$46,"Cursada aprobada")>0))),M12&" ","")&IF(NOT(OR(N12="",COUNTIF($F$2:$F$46,N12)=0,COUNTIFS($F$2:$F$46,N12,$Q$2:$Q$46,"Aprobada")>0,AND(Resumen!$B$15="La cursada aprobada",COUNTIFS($F$2:$F$46,N12,$Q$2:$Q$46,"Cursada aprobada")>0))),N12&" ","")&IF(NOT(OR(O12="",COUNTIF($F$2:$F$46,O12)=0,COUNTIFS($F$2:$F$46,O12,$Q$2:$Q$46,"Aprobada")>0,AND(Resumen!$B$15="La cursada aprobada",COUNTIFS($F$2:$F$46,O12,$Q$2:$Q$46,"Cursada aprobada")>0))),O12&" ","")&IF(NOT(OR(P12="",COUNTIF($F$2:$F$46,P12)=0,COUNTIFS($F$2:$F$46,P12,$Q$2:$Q$46,"Aprobada")>0,AND(Resumen!$B$15="La cursada aprobada",COUNTIFS($F$2:$F$46,P12,$Q$2:$Q$46,"Cursada aprobada")>0))),P12&" ","")),""))
A13: Ciclo básico | C13: 2 | D13: 1 | E13: JU | F13: 307 | G13: Derecho Administrativo | H13: II | I13: 4 | J13: 32 | Q13: No cursada | R13: =IF(Q13="Aprobada","Ya aprobada",IF(Q13="Cursada aprobada","Ya cursada",IF(AND(OR(L13="",COUNTIF($F$2:$F$46,L13)=0,COUNTIFS($F$2:$F$46,L13,$Q$2:$Q$46,"Aprobada")>0,AND(Resumen!$B$15="La cursada aprobada",COUNTIFS($F$2:$F$46,L13,$Q$2:$Q$46,"Cursada aprobada")>0)),OR(M13="",COUNTIF($F$2:$F$46,M13)=0,COUNTIFS($F$2:$F$46,M13,$Q$2:$Q$46,"Aprobada")>0,AND(Resumen!$B$15="La cursada aprobada",COUNTIFS($F$2:$F$46,M13,$Q$2:$Q$46,"Cursada aprobada")>0)),OR(N13="",COUNTIF($F$2:$F$46,N13)=0,COUNTIFS($F$2:$F$46,N13,$Q$2:$Q$46,"Aprobada")>0,AND(Resumen!$B$15="La cursada aprobada",COUNTIFS($F$2:$F$46,N13,$Q$2:$Q$46,"Cursada aprobada")>0)),OR(O13="",COUNTIF($F$2:$F$46,O13)=0,COUNTIFS($F$2:$F$46,O13,$Q$2:$Q$46,"Aprobada")>0,AND(Resumen!$B$15="La cursada aprobada",COUNTIFS($F$2:$F$46,O13,$Q$2:$Q$46,"Cursada aprobada")>0)),OR(P13="",COUNTIF($F$2:$F$46,P13)=0,COUNTIFS($F$2:$F$46,P13,$Q$2:$Q$46,"Aprobada")>0,AND(Resumen!$B$15="La cursada aprobada",COUNTIFS($F$2:$F$46,P13,$Q$2:$Q$46,"Cursada aprobada")>0))),"Sí","No"))) -> Sí | S13: =TRIM(IF(NOT(OR(L13="",COUNTIF($F$2:$F$46,L13)=0,COUNTIFS($F$2:$F$46,L13,$Q$2:$Q$46,"Aprobada")>0,AND(Resumen!$B$15="La cursada aprobada",COUNTIFS($F$2:$F$46,L13,$Q$2:$Q$46,"Cursada aprobada")>0))),L13&" ","")&IF(NOT(OR(M13="",COUNTIF($F$2:$F$46,M13)=0,COUNTIFS($F$2:$F$46,M13,$Q$2:$Q$46,"Aprobada")>0,AND(Resumen!$B$15="La cursada aprobada",COUNTIFS($F$2:$F$46,M13,$Q$2:$Q$46,"Cursada aprobada")>0))),M13&" ","")&IF(NOT(OR(N13="",COUNTIF($F$2:$F$46,N13)=0,COUNTIFS($F$2:$F$46,N13,$Q$2:$Q$46,"Aprobada")>0,AND(Resumen!$B$15="La cursada aprobada",COUNTIFS($F$2:$F$46,N13,$Q$2:$Q$46,"Cursada aprobada")>0))),N13&" ","")&IF(NOT(OR(O13="",COUNTIF($F$2:$F$46,O13)=0,COUNTIFS($F$2:$F$46,O13,$Q$2:$Q$46,"Aprobada")>0,AND(Resumen!$B$15="La cursada aprobada",COUNTIFS($F$2:$F$46,O13,$Q$2:$Q$46,"Cursada aprobada")>0))),O13&" ","")&IF(NOT(OR(P13="",COUNTIF($F$2:$F$46,P13)=0,COUNTIFS($F$2:$F$46,P13,$Q$2:$Q$46,"Aprobada")>0,AND(Resumen!$B$15="La cursada aprobada",COUNTIFS($F$2:$F$46,P13,$Q$2:$Q$46,"Cursada aprobada")>0))),P13&" ","")) | T13: =IF(Q13="Cursada aprobada",IF(AND(OR(L13="",COUNTIF($F$2:$F$46,L13)=0,COUNTIFS($F$2:$F$46,L13,$Q$2:$Q$46,"Aprobada")>0),OR(M13="",COUNTIF($F$2:$F$46,M13)=0,COUNTIFS($F$2:$F$46,M13,$Q$2:$Q$46,"Aprobada")>0),OR(N13="",COUNTIF($F$2:$F$46,N13)=0,COUNTIFS($F$2:$F$46,N13,$Q$2:$Q$46,"Aprobada")>0),OR(O13="",COUNTIF($F$2:$F$46,O13)=0,COUNTIFS($F$2:$F$46,O13,$Q$2:$Q$46,"Aprobada")>0),OR(P13="",COUNTIF($F$2:$F$46,P13)=0,COUNTIFS($F$2:$F$46,P13,$Q$2:$Q$46,"Aprobada")>0)),"Sí","No"),"") | U13: =IF(Q13="Aprobada",TRIM(IF(NOT(OR(L13="",COUNTIF($F$2:$F$46,L13)=0,COUNTIFS($F$2:$F$46,L13,$Q$2:$Q$46,"Aprobada")>0)),L13&" ","")&IF(NOT(OR(M13="",COUNTIF($F$2:$F$46,M13)=0,COUNTIFS($F$2:$F$46,M13,$Q$2:$Q$46,"Aprobada")>0)),M13&" ","")&IF(NOT(OR(N13="",COUNTIF($F$2:$F$46,N13)=0,COUNTIFS($F$2:$F$46,N13,$Q$2:$Q$46,"Aprobada")>0)),N13&" ","")&IF(NOT(OR(O13="",COUNTIF($F$2:$F$46,O13)=0,COUNTIFS($F$2:$F$46,O13,$Q$2:$Q$46,"Aprobada")>0)),O13&" ","")&IF(NOT(OR(P13="",COUNTIF($F$2:$F$46,P13)=0,COUNTIFS($F$2:$F$46,P13,$Q$2:$Q$46,"Aprobada")>0)),P13&" ","")),IF(Q13="Cursada aprobada",TRIM(IF(NOT(OR(L13="",COUNTIF($F$2:$F$46,L13)=0,COUNTIFS($F$2:$F$46,L13,$Q$2:$Q$46,"Aprobada")>0,AND(Resumen!$B$15="La cursada aprobada",COUNTIFS($F$2:$F$46,L13,$Q$2:$Q$46,"Cursada aprobada")>0))),L13&" ","")&IF(NOT(OR(M13="",COUNTIF($F$2:$F$46,M13)=0,COUNTIFS($F$2:$F$46,M13,$Q$2:$Q$46,"Aprobada")>0,AND(Resumen!$B$15="La cursada aprobada",COUNTIFS($F$2:$F$46,M13,$Q$2:$Q$46,"Cursada aprobada")>0))),M13&" ","")&IF(NOT(OR(N13="",COUNTIF($F$2:$F$46,N13)=0,COUNTIFS($F$2:$F$46,N13,$Q$2:$Q$46,"Aprobada")>0,AND(Resumen!$B$15="La cursada aprobada",COUNTIFS($F$2:$F$46,N13,$Q$2:$Q$46,"Cursada aprobada")>0))),N13&" ","")&IF(NOT(OR(O13="",COUNTIF($F$2:$F$46,O13)=0,COUNTIFS($F$2:$F$46,O13,$Q$2:$Q$46,"Aprobada")>0,AND(Resumen!$B$15="La cursada aprobada",COUNTIFS($F$2:$F$46,O13,$Q$2:$Q$46,"Cursada aprobada")>0))),O13&" ","")&IF(NOT(OR(P13="",COUNTIF($F$2:$F$46,P13)=0,COUNTIFS($F$2:$F$46,P13,$Q$2:$Q$46,"Aprobada")>0,AND(Resumen!$B$15="La cursada aprobada",COUNTIFS($F$2:$F$46,P13,$Q$2:$Q$46,"Cursada aprobada")>0))),P13&" ","")),""))
A14: Ciclo básico | C14: 2 | D14: 2 | E14: CO | F14: 210 | G14: Contabilidad II | H14: I | I14: 6 | K14: 96 | L14: 103 | Q14: No cursada | R14: =IF(Q14="Aprobada","Ya aprobada",IF(Q14="Cursada aprobada","Ya cursada",IF(AND(OR(L14="",COUNTIF($F$2:$F$46,L14)=0,COUNTIFS($F$2:$F$46,L14,$Q$2:$Q$46,"Aprobada")>0,AND(Resumen!$B$15="La cursada aprobada",COUNTIFS($F$2:$F$46,L14,$Q$2:$Q$46,"Cursada aprobada")>0)),OR(M14="",COUNTIF($F$2:$F$46,M14)=0,COUNTIFS($F$2:$F$46,M14,$Q$2:$Q$46,"Aprobada")>0,AND(Resumen!$B$15="La cursada aprobada",COUNTIFS($F$2:$F$46,M14,$Q$2:$Q$46,"Cursada aprobada")>0)),OR(N14="",COUNTIF($F$2:$F$46,N14)=0,COUNTIFS($F$2:$F$46,N14,$Q$2:$Q$46,"Aprobada")>0,AND(Resumen!$B$15="La cursada aprobada",COUNTIFS($F$2:$F$46,N14,$Q$2:$Q$46,"Cursada aprobada")>0)),OR(O14="",COUNTIF($F$2:$F$46,O14)=0,COUNTIFS($F$2:$F$46,O14,$Q$2:$Q$46,"Aprobada")>0,AND(Resumen!$B$15="La cursada aprobada",COUNTIFS($F$2:$F$46,O14,$Q$2:$Q$46,"Cursada aprobada")>0)),OR(P14="",COUNTIF($F$2:$F$46,P14)=0,COUNTIFS($F$2:$F$46,P14,$Q$2:$Q$46,"Aprobada")>0,AND(Resumen!$B$15="La cursada aprobada",COUNTIFS($F$2:$F$46,P14,$Q$2:$Q$46,"Cursada aprobada")>0))),"Sí","No"))) -> No | S14: =TRIM(IF(NOT(OR(L14="",COUNTIF($F$2:$F$46,L14)=0,COUNTIFS($F$2:$F$46,L14,$Q$2:$Q$46,"Aprobada")>0,AND(Resumen!$B$15="La cursada aprobada",COUNTIFS($F$2:$F$46,L14,$Q$2:$Q$46,"Cursada aprobada")>0))),L14&" ","")&IF(NOT(OR(M14="",COUNTIF($F$2:$F$46,M14)=0,COUNTIFS($F$2:$F$46,M14,$Q$2:$Q$46,"Aprobada")>0,AND(Resumen!$B$15="La cursada aprobada",COUNTIFS($F$2:$F$46,M14,$Q$2:$Q$46,"Cursada aprobada")>0))),M14&" ","")&IF(NOT(OR(N14="",COUNTIF($F$2:$F$46,N14)=0,COUNTIFS($F$2:$F$46,N14,$Q$2:$Q$46,"Aprobada")>0,AND(Resumen!$B$15="La cursada aprobada",COUNTIFS($F$2:$F$46,N14,$Q$2:$Q$46,"Cursada aprobada")>0))),N14&" ","")&IF(NOT(OR(O14="",COUNTIF($F$2:$F$46,O14)=0,COUNTIFS($F$2:$F$46,O14,$Q$2:$Q$46,"Aprobada")>0,AND(Resumen!$B$15="La cursada aprobada",COUNTIFS($F$2:$F$46,O14,$Q$2:$Q$46,"Cursada aprobada")>0))),O14&" ","")&IF(NOT(OR(P14="",COUNTIF($F$2:$F$46,P14)=0,COUNTIFS($F$2:$F$46,P14,$Q$2:$Q$46,"Aprobada")>0,AND(Resumen!$B$15="La cursada aprobada",COUNTIFS($F$2:$F$46,P14,$Q$2:$Q$46,"Cursada aprobada")>0))),P14&" ","")) -> 103 | T14: =IF(Q14="Cursada aprobada",IF(AND(OR(L14="",COUNTIF($F$2:$F$46,L14)=0,COUNTIFS($F$2:$F$46,L14,$Q$2:$Q$46,"Aprobada")>0),OR(M14="",COUNTIF($F$2:$F$46,M14)=0,COUNTIFS($F$2:$F$46,M14,$Q$2:$Q$46,"Aprobada")>0),OR(N14="",COUNTIF($F$2:$F$46,N14)=0,COUNTIFS($F$2:$F$46,N14,$Q$2:$Q$46,"Aprobada")>0),OR(O14="",COUNTIF($F$2:$F$46,O14)=0,COUNTIFS($F$2:$F$46,O14,$Q$2:$Q$46,"Aprobada")>0),OR(P14="",COUNTIF($F$2:$F$46,P14)=0,COUNTIFS($F$2:$F$46,P14,$Q$2:$Q$46,"Aprobada")>0)),"Sí","No"),"") | U14: =IF(Q14="Aprobada",TRIM(IF(NOT(OR(L14="",COUNTIF($F$2:$F$46,L14)=0,COUNTIFS($F$2:$F$46,L14,$Q$2:$Q$46,"Aprobada")>0)),L14&" ","")&IF(NOT(OR(M14="",COUNTIF($F$2:$F$46,M14)=0,COUNTIFS($F$2:$F$46,M14,$Q$2:$Q$46,"Aprobada")>0)),M14&" ","")&IF(NOT(OR(N14="",COUNTIF($F$2:$F$46,N14)=0,COUNTIFS($F$2:$F$46,N14,$Q$2:$Q$46,"Aprobada")>0)),N14&" ","")&IF(NOT(OR(O14="",COUNTIF($F$2:$F$46,O14)=0,COUNTIFS($F$2:$F$46,O14,$Q$2:$Q$46,"Aprobada")>0)),O14&" ","")&IF(NOT(OR(P14="",COUNTIF($F$2:$F$46,P14)=0,COUNTIFS($F$2:$F$46,P14,$Q$2:$Q$46,"Aprobada")>0)),P14&" ","")),IF(Q14="Cursada aprobada",TRIM(IF(NOT(OR(L14="",COUNTIF($F$2:$F$46,L14)=0,COUNTIFS($F$2:$F$46,L14,$Q$2:$Q$46,"Aprobada")>0,AND(Resumen!$B$15="La cursada aprobada",COUNTIFS($F$2:$F$46,L14,$Q$2:$Q$46,"Cursada aprobada")>0))),L14&" ","")&IF(NOT(OR(M14="",COUNTIF($F$2:$F$46,M14)=0,COUNTIFS($F$2:$F$46,M14,$Q$2:$Q$46,"Aprobada")>0,AND(Resumen!$B$15="La cursada aprobada",COUNTIFS($F$2:$F$46,M14,$Q$2:$Q$46,"Cursada aprobada")>0))),M14&" ","")&IF(NOT(OR(N14="",COUNTIF($F$2:$F$46,N14)=0,COUNTIFS($F$2:$F$46,N14,$Q$2:$Q$46,"Aprobada")>0,AND(Resumen!$B$15="La cursada aprobada",COUNTIFS($F$2:$F$46,N14,$Q$2:$Q$46,"Cursada aprobada")>0))),N14&" ","")&IF(NOT(OR(O14="",COUNTIF($F$2:$F$46,O14)=0,COUNTIFS($F$2:$F$46,O14,$Q$2:$Q$46,"Aprobada")>0,AND(Resumen!$B$15="La cursada aprobada",COUNTIFS($F$2:$F$46,O14,$Q$2:$Q$46,"Cursada aprobada")>0))),O14&" ","")&IF(NOT(OR(P14="",COUNTIF($F$2:$F$46,P14)=0,COUNTIFS($F$2:$F$46,P14,$Q$2:$Q$46,"Aprobada")>0,AND(Resumen!$B$15="La cursada aprobada",COUNTIFS($F$2:$F$46,P14,$Q$2:$Q$46,"Cursada aprobada")>0))),P14&" ","")),""))
A15: Ciclo básico | C15: 2 | D15: 2 | E15: EC | F15: 208 | G15: Microeconomía I | H15: I | I15: 6 | K15: 96 | L15: 101 | M15: 209 | Q15: No cursada | R15: =IF(Q15="Aprobada","Ya aprobada",IF(Q15="Cursada aprobada","Ya cursada",IF(AND(OR(L15="",COUNTIF($F$2:$F$46,L15)=0,COUNTIFS($F$2:$F$46,L15,$Q$2:$Q$46,"Aprobada")>0,AND(Resumen!$B$15="La cursada aprobada",COUNTIFS($F$2:$F$46,L15,$Q$2:$Q$46,"Cursada aprobada")>0)),OR(M15="",COUNTIF($F$2:$F$46,M15)=0,COUNTIFS($F$2:$F$46,M15,$Q$2:$Q$46,"Aprobada")>0,AND(Resumen!$B$15="La cursada aprobada",COUNTIFS($F$2:$F$46,M15,$Q$2:$Q$46,"Cursada aprobada")>0)),OR(N15="",COUNTIF($F$2:$F$46,N15)=0,COUNTIFS($F$2:$F$46,N15,$Q$2:$Q$46,"Aprobada")>0,AND(Resumen!$B$15="La cursada aprobada",COUNTIFS($F$2:$F$46,N15,$Q$2:$Q$46,"Cursada aprobada")>0)),OR(O15="",COUNTIF($F$2:$F$46,O15)=0,COUNTIFS($F$2:$F$46,O15,$Q$2:$Q$46,"Aprobada")>0,AND(Resumen!$B$15="La cursada aprobada",COUNTIFS($F$2:$F$46,O15,$Q$2:$Q$46,"Cursada aprobada")>0)),OR(P15="",COUNTIF($F$2:$F$46,P15)=0,COUNTIFS($F$2:$F$46,P15,$Q$2:$Q$46,"Aprobada")>0,AND(Resumen!$B$15="La cursada aprobada",COUNTIFS($F$2:$F$46,P15,$Q$2:$Q$46,"Cursada aprobada")>0))),"Sí","No"))) -> No | S15: =TRIM(IF(NOT(OR(L15="",COUNTIF($F$2:$F$46,L15)=0,COUNTIFS($F$2:$F$46,L15,$Q$2:$Q$46,"Aprobada")>0,AND(Resumen!$B$15="La cursada aprobada",COUNTIFS($F$2:$F$46,L15,$Q$2:$Q$46,"Cursada aprobada")>0))),L15&" ","")&IF(NOT(OR(M15="",COUNTIF($F$2:$F$46,M15)=0,COUNTIFS($F$2:$F$46,M15,$Q$2:$Q$46,"Aprobada")>0,AND(Resumen!$B$15="La cursada aprobada",COUNTIFS($F$2:$F$46,M15,$Q$2:$Q$46,"Cursada aprobada")>0))),M15&" ","")&IF(NOT(OR(N15="",COUNTIF($F$2:$F$46,N15)=0,COUNTIFS($F$2:$F$46,N15,$Q$2:$Q$46,"Aprobada")>0,AND(Resumen!$B$15="La cursada aprobada",COUNTIFS($F$2:$F$46,N15,$Q$2:$Q$46,"Cursada aprobada")>0))),N15&" ","")&IF(NOT(OR(O15="",COUNTIF($F$2:$F$46,O15)=0,COUNTIFS($F$2:$F$46,O15,$Q$2:$Q$46,"Aprobada")>0,AND(Resumen!$B$15="La cursada aprobada",COUNTIFS($F$2:$F$46,O15,$Q$2:$Q$46,"Cursada aprobada")>0))),O15&" ","")&IF(NOT(OR(P15="",COUNTIF($F$2:$F$46,P15)=0,COUNTIFS($F$2:$F$46,P15,$Q$2:$Q$46,"Aprobada")>0,AND(Resumen!$B$15="La cursada aprobada",COUNTIFS($F$2:$F$46,P15,$Q$2:$Q$46,"Cursada aprobada")>0))),P15&" ","")) -> 101 209 | T15: =IF(Q15="Cursada aprobada",IF(AND(OR(L15="",COUNTIF($F$2:$F$46,L15)=0,COUNTIFS($F$2:$F$46,L15,$Q$2:$Q$46,"Aprobada")>0),OR(M15="",COUNTIF($F$2:$F$46,M15)=0,COUNTIFS($F$2:$F$46,M15,$Q$2:$Q$46,"Aprobada")>0),OR(N15="",COUNTIF($F$2:$F$46,N15)=0,COUNTIFS($F$2:$F$46,N15,$Q$2:$Q$46,"Aprobada")>0),OR(O15="",COUNTIF($F$2:$F$46,O15)=0,COUNTIFS($F$2:$F$46,O15,$Q$2:$Q$46,"Aprobada")>0),OR(P15="",COUNTIF($F$2:$F$46,P15)=0,COUNTIFS($F$2:$F$46,P15,$Q$2:$Q$46,"Aprobada")>0)),"Sí","No"),"") | U15: =IF(Q15="Aprobada",TRIM(IF(NOT(OR(L15="",COUNTIF($F$2:$F$46,L15)=0,COUNTIFS($F$2:$F$46,L15,$Q$2:$Q$46,"Aprobada")>0)),L15&" ","")&IF(NOT(OR(M15="",COUNTIF($F$2:$F$46,M15)=0,COUNTIFS($F$2:$F$46,M15,$Q$2:$Q$46,"Aprobada")>0)),M15&" ","")&IF(NOT(OR(N15="",COUNTIF($F$2:$F$46,N15)=0,COUNTIFS($F$2:$F$46,N15,$Q$2:$Q$46,"Aprobada")>0)),N15&" ","")&IF(NOT(OR(O15="",COUNTIF($F$2:$F$46,O15)=0,COUNTIFS($F$2:$F$46,O15,$Q$2:$Q$46,"Aprobada")>0)),O15&" ","")&IF(NOT(OR(P15="",COUNTIF($F$2:$F$46,P15)=0,COUNTIFS($F$2:$F$46,P15,$Q$2:$Q$46,"Aprobada")>0)),P15&" ","")),IF(Q15="Cursada aprobada",TRIM(IF(NOT(OR(L15="",COUNTIF($F$2:$F$46,L15)=0,COUNTIFS($F$2:$F$46,L15,$Q$2:$Q$46,"Aprobada")>0,AND(Resumen!$B$15="La cursada aprobada",COUNTIFS($F$2:$F$46,L15,$Q$2:$Q$46,"Cursada aprobada")>0))),L15&" ","")&IF(NOT(OR(M15="",COUNTIF($F$2:$F$46,M15)=0,COUNTIFS($F$2:$F$46,M15,$Q$2:$Q$46,"Aprobada")>0,AND(Resumen!$B$15="La cursada aprobada",COUNTIFS($F$2:$F$46,M15,$Q$2:$Q$46,"Cursada aprobada")>0))),M15&" ","")&IF(NOT(OR(N15="",COUNTIF($F$2:$F$46,N15)=0,COUNTIFS($F$2:$F$46,N15,$Q$2:$Q$46,"Aprobada")>0,AND(Resumen!$B$15="La cursada aprobada",COUNTIFS($F$2:$F$46,N15,$Q$2:$Q$46,"Cursada aprobada")>0))),N15&" ","")&IF(NOT(OR(O15="",COUNTIF($F$2:$F$46,O15)=0,COUNTIFS($F$2:$F$46,O15,$Q$2:$Q$46,"Aprobada")>0,AND(Resumen!$B$15="La cursada aprobada",COUNTIFS($F$2:$F$46,O15,$Q$2:$Q$46,"Cursada aprobada")>0))),O15&" ","")&IF(NOT(OR(P15="",COUNTIF($F$2:$F$46,P15)=0,COUNTIFS($F$2:$F$46,P15,$Q$2:$Q$46,"Aprobada")>0,AND(Resumen!$B$15="La cursada aprobada",COUNTIFS($F$2:$F$46,P15,$Q$2:$Q$46,"Cursada aprobada")>0))),P15&" ","")),""))
A16: Ciclo básico | C16: 2 | D16: 2 | E16: MA | F16: 250 | G16: Estadística | H16: I | I16: 6 | K16: 96 | L16: 209 | Q16: No cursada | R16: =IF(Q16="Aprobada","Ya aprobada",IF(Q16="Cursada aprobada","Ya cursada",IF(AND(OR(L16="",COUNTIF($F$2:$F$46,L16)=0,COUNTIFS($F$2:$F$46,L16,$Q$2:$Q$46,"Aprobada")>0,AND(Resumen!$B$15="La cursada aprobada",COUNTIFS($F$2:$F$46,L16,$Q$2:$Q$46,"Cursada aprobada")>0)),OR(M16="",COUNTIF($F$2:$F$46,M16)=0,COUNTIFS($F$2:$F$46,M16,$Q$2:$Q$46,"Aprobada")>0,AND(Resumen!$B$15="La cursada aprobada",COUNTIFS($F$2:$F$46,M16,$Q$2:$Q$46,"Cursada aprobada")>0)),OR(N16="",COUNTIF($F$2:$F$46,N16)=0,COUNTIFS($F$2:$F$46,N16,$Q$2:$Q$46,"Aprobada")>0,AND(Resumen!$B$15="La cursada aprobada",COUNTIFS($F$2:$F$46,N16,$Q$2:$Q$46,"Cursada aprobada")>0)),OR(O16="",COUNTIF($F$2:$F$46,O16)=0,COUNTIFS($F$2:$F$46,O16,$Q$2:$Q$46,"Aprobada")>0,AND(Resumen!$B$15="La cursada aprobada",COUNTIFS($F$2:$F$46,O16,$Q$2:$Q$46,"Cursada aprobada")>0)),OR(P16="",COUNTIF($F$2:$F$46,P16)=0,COUNTIFS($F$2:$F$46,P16,$Q$2:$Q$46,"Aprobada")>0,AND(Resumen!$B$15="La cursada aprobada",COUNTIFS($F$2:$F$46,P16,$Q$2:$Q$46,"Cursada aprobada")>0))),"Sí","No"))) -> No | S16: =TRIM(IF(NOT(OR(L16="",COUNTIF($F$2:$F$46,L16)=0,COUNTIFS($F$2:$F$46,L16,$Q$2:$Q$46,"Aprobada")>0,AND(Resumen!$B$15="La cursada aprobada",COUNTIFS($F$2:$F$46,L16,$Q$2:$Q$46,"Cursada aprobada")>0))),L16&" ","")&IF(NOT(OR(M16="",COUNTIF($F$2:$F$46,M16)=0,COUNTIFS($F$2:$F$46,M16,$Q$2:$Q$46,"Aprobada")>0,AND(Resumen!$B$15="La cursada aprobada",COUNTIFS($F$2:$F$46,M16,$Q$2:$Q$46,"Cursada aprobada")>0))),M16&" ","")&IF(NOT(OR(N16="",COUNTIF($F$2:$F$46,N16)=0,COUNTIFS($F$2:$F$46,N16,$Q$2:$Q$46,"Aprobada")>0,AND(Resumen!$B$15="La cursada aprobada",COUNTIFS($F$2:$F$46,N16,$Q$2:$Q$46,"Cursada aprobada")>0))),N16&" ","")&IF(NOT(OR(O16="",COUNTIF($F$2:$F$46,O16)=0,COUNTIFS($F$2:$F$46,O16,$Q$2:$Q$46,"Aprobada")>0,AND(Resumen!$B$15="La cursada aprobada",COUNTIFS($F$2:$F$46,O16,$Q$2:$Q$46,"Cursada aprobada")>0))),O16&" ","")&IF(NOT(OR(P16="",COUNTIF($F$2:$F$46,P16)=0,COUNTIFS($F$2:$F$46,P16,$Q$2:$Q$46,"Aprobada")>0,AND(Resumen!$B$15="La cursada aprobada",COUNTIFS($F$2:$F$46,P16,$Q$2:$Q$46,"Cursada aprobada")>0))),P16&" ","")) -> 209 | T16: =IF(Q16="Cursada aprobada",IF(AND(OR(L16="",COUNTIF($F$2:$F$46,L16)=0,COUNTIFS($F$2:$F$46,L16,$Q$2:$Q$46,"Aprobada")>0),OR(M16="",COUNTIF($F$2:$F$46,M16)=0,COUNTIFS($F$2:$F$46,M16,$Q$2:$Q$46,"Aprobada")>0),OR(N16="",COUNTIF($F$2:$F$46,N16)=0,COUNTIFS($F$2:$F$46,N16,$Q$2:$Q$46,"Aprobada")>0),OR(O16="",COUNTIF($F$2:$F$46,O16)=0,COUNTIFS($F$2:$F$46,O16,$Q$2:$Q$46,"Aprobada")>0),OR(P16="",COUNTIF($F$2:$F$46,P16)=0,COUNTIFS($F$2:$F$46,P16,$Q$2:$Q$46,"Aprobada")>0)),"Sí","No"),"") | U16: =IF(Q16="Aprobada",TRIM(IF(NOT(OR(L16="",COUNTIF($F$2:$F$46,L16)=0,COUNTIFS($F$2:$F$46,L16,$Q$2:$Q$46,"Aprobada")>0)),L16&" ","")&IF(NOT(OR(M16="",COUNTIF($F$2:$F$46,M16)=0,COUNTIFS($F$2:$F$46,M16,$Q$2:$Q$46,"Aprobada")>0)),M16&" ","")&IF(NOT(OR(N16="",COUNTIF($F$2:$F$46,N16)=0,COUNTIFS($F$2:$F$46,N16,$Q$2:$Q$46,"Aprobada")>0)),N16&" ","")&IF(NOT(OR(O16="",COUNTIF($F$2:$F$46,O16)=0,COUNTIFS($F$2:$F$46,O16,$Q$2:$Q$46,"Aprobada")>0)),O16&" ","")&IF(NOT(OR(P16="",COUNTIF($F$2:$F$46,P16)=0,COUNTIFS($F$2:$F$46,P16,$Q$2:$Q$46,"Aprobada")>0)),P16&" ","")),IF(Q16="Cursada aprobada",TRIM(IF(NOT(OR(L16="",COUNTIF($F$2:$F$46,L16)=0,COUNTIFS($F$2:$F$46,L16,$Q$2:$Q$46,"Aprobada")>0,AND(Resumen!$B$15="La cursada aprobada",COUNTIFS($F$2:$F$46,L16,$Q$2:$Q$46,"Cursada aprobada")>0))),L16&" ","")&IF(NOT(OR(M16="",COUNTIF($F$2:$F$46,M16)=0,COUNTIFS($F$2:$F$46,M16,$Q$2:$Q$46,"Aprobada")>0,AND(Resumen!$B$15="La cursada aprobada",COUNTIFS($F$2:$F$46,M16,$Q$2:$Q$46,"Cursada aprobada")>0))),M16&" ","")&IF(NOT(OR(N16="",COUNTIF($F$2:$F$46,N16)=0,COUNTIFS($F$2:$F$46,N16,$Q$2:$Q$46,"Aprobada")>0,AND(Resumen!$B$15="La cursada aprobada",COUNTIFS($F$2:$F$46,N16,$Q$2:$Q$46,"Cursada aprobada")>0))),N16&" ","")&IF(NOT(OR(O16="",COUNTIF($F$2:$F$46,O16)=0,COUNTIFS($F$2:$F$46,O16,$Q$2:$Q$46,"Aprobada")>0,AND(Resumen!$B$15="La cursada aprobada",COUNTIFS($F$2:$F$46,O16,$Q$2:$Q$46,"Cursada aprobada")>0))),O16&" ","")&IF(NOT(OR(P16="",COUNTIF($F$2:$F$46,P16)=0,COUNTIFS($F$2:$F$46,P16,$Q$2:$Q$46,"Aprobada")>0,AND(Resumen!$B$15="La cursada aprobada",COUNTIFS($F$2:$F$46,P16,$Q$2:$Q$46,"Cursada aprobada")>0))),P16&" ","")),""))
A17: Ciclo profesional | C17: 3 | D17: 1 | E17: CO | F17: 402 | G17: Contabilidad III | H17: I | I17: 5 | K17: 80 | L17: 210 | Q17: No cursada | R17: =IF(Q17="Aprobada","Ya aprobada",IF(Q17="Cursada aprobada","Ya cursada",IF(AND(OR(L17="",COUNTIF($F$2:$F$46,L17)=0,COUNTIFS($F$2:$F$46,L17,$Q$2:$Q$46,"Aprobada")>0,AND(Resumen!$B$15="La cursada aprobada",COUNTIFS($F$2:$F$46,L17,$Q$2:$Q$46,"Cursada aprobada")>0)),OR(M17="",COUNTIF($F$2:$F$46,M17)=0,COUNTIFS($F$2:$F$46,M17,$Q$2:$Q$46,"Aprobada")>0,AND(Resumen!$B$15="La cursada aprobada",COUNTIFS($F$2:$F$46,M17,$Q$2:$Q$46,"Cursada aprobada")>0)),OR(N17="",COUNTIF($F$2:$F$46,N17)=0,COUNTIFS($F$2:$F$46,N17,$Q$2:$Q$46,"Aprobada")>0,AND(Resumen!$B$15="La cursada aprobada",COUNTIFS($F$2:$F$46,N17,$Q$2:$Q$46,"Cursada aprobada")>0)),OR(O17="",COUNTIF($F$2:$F$46,O17)=0,COUNTIFS($F$2:$F$46,O17,$Q$2:$Q$46,"Aprobada")>0,AND(Resumen!$B$15="La cursada aprobada",COUNTIFS($F$2:$F$46,O17,$Q$2:$Q$46,"Cursada aprobada")>0)),OR(P17="",COUNTIF($F$2:$F$46,P17)=0,COUNTIFS($F$2:$F$46,P17,$Q$2:$Q$46,"Aprobada")>0,AND(Resumen!$B$15="La cursada aprobada",COUNTIFS($F$2:$F$46,P17,$Q$2:$Q$46,"Cursada aprobada")>0))),"Sí","No"))) -> No | S17: =TRIM(IF(NOT(OR(L17="",COUNTIF($F$2:$F$46,L17)=0,COUNTIFS($F$2:$F$46,L17,$Q$2:$Q$46,"Aprobada")>0,AND(Resumen!$B$15="La cursada aprobada",COUNTIFS($F$2:$F$46,L17,$Q$2:$Q$46,"Cursada aprobada")>0))),L17&" ","")&IF(NOT(OR(M17="",COUNTIF($F$2:$F$46,M17)=0,COUNTIFS($F$2:$F$46,M17,$Q$2:$Q$46,"Aprobada")>0,AND(Resumen!$B$15="La cursada aprobada",COUNTIFS($F$2:$F$46,M17,$Q$2:$Q$46,"Cursada aprobada")>0))),M17&" ","")&IF(NOT(OR(N17="",COUNTIF($F$2:$F$46,N17)=0,COUNTIFS($F$2:$F$46,N17,$Q$2:$Q$46,"Aprobada")>0,AND(Resumen!$B$15="La cursada aprobada",COUNTIFS($F$2:$F$46,N17,$Q$2:$Q$46,"Cursada aprobada")>0))),N17&" ","")&IF(NOT(OR(O17="",COUNTIF($F$2:$F$46,O17)=0,COUNTIFS($F$2:$F$46,O17,$Q$2:$Q$46,"Aprobada")>0,AND(Resumen!$B$15="La cursada aprobada",COUNTIFS($F$2:$F$46,O17,$Q$2:$Q$46,"Cursada aprobada")>0))),O17&" ","")&IF(NOT(OR(P17="",COUNTIF($F$2:$F$46,P17)=0,COUNTIFS($F$2:$F$46,P17,$Q$2:$Q$46,"Aprobada")>0,AND(Resumen!$B$15="La cursada aprobada",COUNTIFS($F$2:$F$46,P17,$Q$2:$Q$46,"Cursada aprobada")>0))),P17&" ","")) -> 210 | T17: =IF(Q17="Cursada aprobada",IF(AND(OR(L17="",COUNTIF($F$2:$F$46,L17)=0,COUNTIFS($F$2:$F$46,L17,$Q$2:$Q$46,"Aprobada")>0),OR(M17="",COUNTIF($F$2:$F$46,M17)=0,COUNTIFS($F$2:$F$46,M17,$Q$2:$Q$46,"Aprobada")>0),OR(N17="",COUNTIF($F$2:$F$46,N17)=0,COUNTIFS($F$2:$F$46,N17,$Q$2:$Q$46,"Aprobada")>0),OR(O17="",COUNTIF($F$2:$F$46,O17)=0,COUNTIFS($F$2:$F$46,O17,$Q$2:$Q$46,"Aprobada")>0),OR(P17="",COUNTIF($F$2:$F$46,P17)=0,COUNTIFS($F$2:$F$46,P17,$Q$2:$Q$46,"Aprobada")>0)),"Sí","No"),"") | U17: =IF(Q17="Aprobada",TRIM(IF(NOT(OR(L17="",COUNTIF($F$2:$F$46,L17)=0,COUNTIFS($F$2:$F$46,L17,$Q$2:$Q$46,"Aprobada")>0)),L17&" ","")&IF(NOT(OR(M17="",COUNTIF($F$2:$F$46,M17)=0,COUNTIFS($F$2:$F$46,M17,$Q$2:$Q$46,"Aprobada")>0)),M17&" ","")&IF(NOT(OR(N17="",COUNTIF($F$2:$F$46,N17)=0,COUNTIFS($F$2:$F$46,N17,$Q$2:$Q$46,"Aprobada")>0)),N17&" ","")&IF(NOT(OR(O17="",COUNTIF($F$2:$F$46,O17)=0,COUNTIFS($F$2:$F$46,O17,$Q$2:$Q$46,"Aprobada")>0)),O17&" ","")&IF(NOT(OR(P17="",COUNTIF($F$2:$F$46,P17)=0,COUNTIFS($F$2:$F$46,P17,$Q$2:$Q$46,"Aprobada")>0)),P17&" ","")),IF(Q17="Cursada aprobada",TRIM(IF(NOT(OR(L17="",COUNTIF($F$2:$F$46,L17)=0,COUNTIFS($F$2:$F$46,L17,$Q$2:$Q$46,"Aprobada")>0,AND(Resumen!$B$15="La cursada aprobada",COUNTIFS($F$2:$F$46,L17,$Q$2:$Q$46,"Cursada aprobada")>0))),L17&" ","")&IF(NOT(OR(M17="",COUNTIF($F$2:$F$46,M17)=0,COUNTIFS($F$2:$F$46,M17,$Q$2:$Q$46,"Aprobada")>0,AND(Resumen!$B$15="La cursada aprobada",COUNTIFS($F$2:$F$46,M17,$Q$2:$Q$46,"Cursada aprobada")>0))),M17&" ","")&IF(NOT(OR(N17="",COUNTIF($F$2:$F$46,N17)=0,COUNTIFS($F$2:$F$46,N17,$Q$2:$Q$46,"Aprobada")>0,AND(Resumen!$B$15="La cursada aprobada",COUNTIFS($F$2:$F$46,N17,$Q$2:$Q$46,"Cursada aprobada")>0))),N17&" ","")&IF(NOT(OR(O17="",COUNTIF($F$2:$F$46,O17)=0,COUNTIFS($F$2:$F$46,O17,$Q$2:$Q$46,"Aprobada")>0,AND(Resumen!$B$15="La cursada aprobada",COUNTIFS($F$2:$F$46,O17,$Q$2:$Q$46,"Cursada aprobada")>0))),O17&" ","")&IF(NOT(OR(P17="",COUNTIF($F$2:$F$46,P17)=0,COUNTIFS($F$2:$F$46,P17,$Q$2:$Q$46,"Aprobada")>0,AND(Resumen!$B$15="La cursada aprobada",COUNTIFS($F$2:$F$46,P17,$Q$2:$Q$46,"Cursada aprobada")>0))),P17&" ","")),""))
A18: Ciclo profesional | C18: 3 | D18: 1 | E18: AD | F18: 330 | G18: Sistemas de Información | H18: I | I18: 6 | K18: 96 | L18: 103 | M18: 308 | Q18: No cursada | R18: =IF(Q18="Aprobada","Ya aprobada",IF(Q18="Cursada aprobada","Ya cursada",IF(AND(OR(L18="",COUNTIF($F$2:$F$46,L18)=0,COUNTIFS($F$2:$F$46,L18,$Q$2:$Q$46,"Aprobada")>0,AND(Resumen!$B$15="La cursada aprobada",COUNTIFS($F$2:$F$46,L18,$Q$2:$Q$46,"Cursada aprobada")>0)),OR(M18="",COUNTIF($F$2:$F$46,M18)=0,COUNTIFS($F$2:$F$46,M18,$Q$2:$Q$46,"Aprobada")>0,AND(Resumen!$B$15="La cursada aprobada",COUNTIFS($F$2:$F$46,M18,$Q$2:$Q$46,"Cursada aprobada")>0)),OR(N18="",COUNTIF($F$2:$F$46,N18)=0,COUNTIFS($F$2:$F$46,N18,$Q$2:$Q$46,"Aprobada")>0,AND(Resumen!$B$15="La cursada aprobada",COUNTIFS($F$2:$F$46,N18,$Q$2:$Q$46,"Cursada aprobada")>0)),OR(O18="",COUNTIF($F$2:$F$46,O18)=0,COUNTIFS($F$2:$F$46,O18,$Q$2:$Q$46,"Aprobada")>0,AND(Resumen!$B$15="La cursada aprobada",COUNTIFS($F$2:$F$46,O18,$Q$2:$Q$46,"Cursada aprobada")>0)),OR(P18="",COUNTIF($F$2:$F$46,P18)=0,COUNTIFS($F$2:$F$46,P18,$Q$2:$Q$46,"Aprobada")>0,AND(Resumen!$B$15="La cursada aprobada",COUNTIFS($F$2:$F$46,P18,$Q$2:$Q$46,"Cursada aprobada")>0))),"Sí","No"))) -> No | S18: =TRIM(IF(NOT(OR(L18="",COUNTIF($F$2:$F$46,L18)=0,COUNTIFS($F$2:$F$46,L18,$Q$2:$Q$46,"Aprobada")>0,AND(Resumen!$B$15="La cursada aprobada",COUNTIFS($F$2:$F$46,L18,$Q$2:$Q$46,"Cursada aprobada")>0))),L18&" ","")&IF(NOT(OR(M18="",COUNTIF($F$2:$F$46,M18)=0,COUNTIFS($F$2:$F$46,M18,$Q$2:$Q$46,"Aprobada")>0,AND(Resumen!$B$15="La cursada aprobada",COUNTIFS($F$2:$F$46,M18,$Q$2:$Q$46,"Cursada aprobada")>0))),M18&" ","")&IF(NOT(OR(N18="",COUNTIF($F$2:$F$46,N18)=0,COUNTIFS($F$2:$F$46,N18,$Q$2:$Q$46,"Aprobada")>0,AND(Resumen!$B$15="La cursada aprobada",COUNTIFS($F$2:$F$46,N18,$Q$2:$Q$46,"Cursada aprobada")>0))),N18&" ","")&IF(NOT(OR(O18="",COUNTIF($F$2:$F$46,O18)=0,COUNTIFS($F$2:$F$46,O18,$Q$2:$Q$46,"Aprobada")>0,AND(Resumen!$B$15="La cursada aprobada",COUNTIFS($F$2:$F$46,O18,$Q$2:$Q$46,"Cursada aprobada")>0))),O18&" ","")&IF(NOT(OR(P18="",COUNTIF($F$2:$F$46,P18)=0,COUNTIFS($F$2:$F$46,P18,$Q$2:$Q$46,"Aprobada")>0,AND(Resumen!$B$15="La cursada aprobada",COUNTIFS($F$2:$F$46,P18,$Q$2:$Q$46,"Cursada aprobada")>0))),P18&" ","")) -> 103 308 | T18: =IF(Q18="Cursada aprobada",IF(AND(OR(L18="",COUNTIF($F$2:$F$46,L18)=0,COUNTIFS($F$2:$F$46,L18,$Q$2:$Q$46,"Aprobada")>0),OR(M18="",COUNTIF($F$2:$F$46,M18)=0,COUNTIFS($F$2:$F$46,M18,$Q$2:$Q$46,"Aprobada")>0),OR(N18="",COUNTIF($F$2:$F$46,N18)=0,COUNTIFS($F$2:$F$46,N18,$Q$2:$Q$46,"Aprobada")>0),OR(O18="",COUNTIF($F$2:$F$46,O18)=0,COUNTIFS($F$2:$F$46,O18,$Q$2:$Q$46,"Aprobada")>0),OR(P18="",COUNTIF($F$2:$F$46,P18)=0,COUNTIFS($F$2:$F$46,P18,$Q$2:$Q$46,"Aprobada")>0)),"Sí","No"),"") | U18: =IF(Q18="Aprobada",TRIM(IF(NOT(OR(L18="",COUNTIF($F$2:$F$46,L18)=0,COUNTIFS($F$2:$F$46,L18,$Q$2:$Q$46,"Aprobada")>0)),L18&" ","")&IF(NOT(OR(M18="",COUNTIF($F$2:$F$46,M18)=0,COUNTIFS($F$2:$F$46,M18,$Q$2:$Q$46,"Aprobada")>0)),M18&" ","")&IF(NOT(OR(N18="",COUNTIF($F$2:$F$46,N18)=0,COUNTIFS($F$2:$F$46,N18,$Q$2:$Q$46,"Aprobada")>0)),N18&" ","")&IF(NOT(OR(O18="",COUNTIF($F$2:$F$46,O18)=0,COUNTIFS($F$2:$F$46,O18,$Q$2:$Q$46,"Aprobada")>0)),O18&" ","")&IF(NOT(OR(P18="",COUNTIF($F$2:$F$46,P18)=0,COUNTIFS($F$2:$F$46,P18,$Q$2:$Q$46,"Aprobada")>0)),P18&" ","")),IF(Q18="Cursada aprobada",TRIM(IF(NOT(OR(L18="",COUNTIF($F$2:$F$46,L18)=0,COUNTIFS($F$2:$F$46,L18,$Q$2:$Q$46,"Aprobada")>0,AND(Resumen!$B$15="La cursada aprobada",COUNTIFS($F$2:$F$46,L18,$Q$2:$Q$46,"Cursada aprobada")>0))),L18&" ","")&IF(NOT(OR(M18="",COUNTIF($F$2:$F$46,M18)=0,COUNTIFS($F$2:$F$46,M18,$Q$2:$Q$46,"Aprobada")>0,AND(Resumen!$B$15="La cursada aprobada",COUNTIFS($F$2:$F$46,M18,$Q$2:$Q$46,"Cursada aprobada")>0))),M18&" ","")&IF(NOT(OR(N18="",COUNTIF($F$2:$F$46,N18)=0,COUNTIFS($F$2:$F$46,N18,$Q$2:$Q$46,"Aprobada")>0,AND(Resumen!$B$15="La cursada aprobada",COUNTIFS($F$2:$F$46,N18,$Q$2:$Q$46,"Cursada aprobada")>0))),N18&" ","")&IF(NOT(OR(O18="",COUNTIF($F$2:$F$46,O18)=0,COUNTIFS($F$2:$F$46,O18,$Q$2:$Q$46,"Aprobada")>0,AND(Resumen!$B$15="La cursada aprobada",COUNTIFS($F$2:$F$46,O18,$Q$2:$Q$46,"Cursada aprobada")>0))),O18&" ","")&IF(NOT(OR(P18="",COUNTIF($F$2:$F$46,P18)=0,COUNTIFS($F$2:$F$46,P18,$Q$2:$Q$46,"Aprobada")>0,AND(Resumen!$B$15="La cursada aprobada",COUNTIFS($F$2:$F$46,P18,$Q$2:$Q$46,"Cursada aprobada")>0))),P18&" ","")),""))
A19: Ciclo profesional | C19: 3 | D19: 1 | E19: MA | F19: 424 | G19: Matemática Financiera | H19: I | I19: 5 | K19: 80 | L19: 250 | Q19: No cursada | R19: =IF(Q19="Aprobada","Ya aprobada",IF(Q19="Cursada aprobada","Ya cursada",IF(AND(OR(L19="",COUNTIF($F$2:$F$46,L19)=0,COUNTIFS($F$2:$F$46,L19,$Q$2:$Q$46,"Aprobada")>0,AND(Resumen!$B$15="La cursada aprobada",COUNTIFS($F$2:$F$46,L19,$Q$2:$Q$46,"Cursada aprobada")>0)),OR(M19="",COUNTIF($F$2:$F$46,M19)=0,COUNTIFS($F$2:$F$46,M19,$Q$2:$Q$46,"Aprobada")>0,AND(Resumen!$B$15="La cursada aprobada",COUNTIFS($F$2:$F$46,M19,$Q$2:$Q$46,"Cursada aprobada")>0)),OR(N19="",COUNTIF($F$2:$F$46,N19)=0,COUNTIFS($F$2:$F$46,N19,$Q$2:$Q$46,"Aprobada")>0,AND(Resumen!$B$15="La cursada aprobada",COUNTIFS($F$2:$F$46,N19,$Q$2:$Q$46,"Cursada aprobada")>0)),OR(O19="",COUNTIF($F$2:$F$46,O19)=0,COUNTIFS($F$2:$F$46,O19,$Q$2:$Q$46,"Aprobada")>0,AND(Resumen!$B$15="La cursada aprobada",COUNTIFS($F$2:$F$46,O19,$Q$2:$Q$46,"Cursada aprobada")>0)),OR(P19="",COUNTIF($F$2:$F$46,P19)=0,COUNTIFS($F$2:$F$46,P19,$Q$2:$Q$46,"Aprobada")>0,AND(Resumen!$B$15="La cursada aprobada",COUNTIFS($F$2:$F$46,P19,$Q$2:$Q$46,"Cursada aprobada")>0))),"Sí","No"))) -> No | S19: =TRIM(IF(NOT(OR(L19="",COUNTIF($F$2:$F$46,L19)=0,COUNTIFS($F$2:$F$46,L19,$Q$2:$Q$46,"Aprobada")>0,AND(Resumen!$B$15="La cursada aprobada",COUNTIFS($F$2:$F$46,L19,$Q$2:$Q$46,"Cursada aprobada")>0))),L19&" ","")&IF(NOT(OR(M19="",COUNTIF($F$2:$F$46,M19)=0,COUNTIFS($F$2:$F$46,M19,$Q$2:$Q$46,"Aprobada")>0,AND(Resumen!$B$15="La cursada aprobada",COUNTIFS($F$2:$F$46,M19,$Q$2:$Q$46,"Cursada aprobada")>0))),M19&" ","")&IF(NOT(OR(N19="",COUNTIF($F$2:$F$46,N19)=0,COUNTIFS($F$2:$F$46,N19,$Q$2:$Q$46,"Aprobada")>0,AND(Resumen!$B$15="La cursada aprobada",COUNTIFS($F$2:$F$46,N19,$Q$2:$Q$46,"Cursada aprobada")>0))),N19&" ","")&IF(NOT(OR(O19="",COUNTIF($F$2:$F$46,O19)=0,COUNTIFS($F$2:$F$46,O19,$Q$2:$Q$46,"Aprobada")>0,AND(Resumen!$B$15="La cursada aprobada",COUNTIFS($F$2:$F$46,O19,$Q$2:$Q$46,"Cursada aprobada")>0))),O19&" ","")&IF(NOT(OR(P19="",COUNTIF($F$2:$F$46,P19)=0,COUNTIFS($F$2:$F$46,P19,$Q$2:$Q$46,"Aprobada")>0,AND(Resumen!$B$15="La cursada aprobada",COUNTIFS($F$2:$F$46,P19,$Q$2:$Q$46,"Cursada aprobada")>0))),P19&" ","")) -> 250 | T19: =IF(Q19="Cursada aprobada",IF(AND(OR(L19="",COUNTIF($F$2:$F$46,L19)=0,COUNTIFS($F$2:$F$46,L19,$Q$2:$Q$46,"Aprobada")>0),OR(M19="",COUNTIF($F$2:$F$46,M19)=0,COUNTIFS($F$2:$F$46,M19,$Q$2:$Q$46,"Aprobada")>0),OR(N19="",COUNTIF($F$2:$F$46,N19)=0,COUNTIFS($F$2:$F$46,N19,$Q$2:$Q$46,"Aprobada")>0),OR(O19="",COUNTIF($F$2:$F$46,O19)=0,COUNTIFS($F$2:$F$46,O19,$Q$2:$Q$46,"Aprobada")>0),OR(P19="",COUNTIF($F$2:$F$46,P19)=0,COUNTIFS($F$2:$F$46,P19,$Q$2:$Q$46,"Aprobada")>0)),"Sí","No"),"") | U19: =IF(Q19="Aprobada",TRIM(IF(NOT(OR(L19="",COUNTIF($F$2:$F$46,L19)=0,COUNTIFS($F$2:$F$46,L19,$Q$2:$Q$46,"Aprobada")>0)),L19&" ","")&IF(NOT(OR(M19="",COUNTIF($F$2:$F$46,M19)=0,COUNTIFS($F$2:$F$46,M19,$Q$2:$Q$46,"Aprobada")>0)),M19&" ","")&IF(NOT(OR(N19="",COUNTIF($F$2:$F$46,N19)=0,COUNTIFS($F$2:$F$46,N19,$Q$2:$Q$46,"Aprobada")>0)),N19&" ","")&IF(NOT(OR(O19="",COUNTIF($F$2:$F$46,O19)=0,COUNTIFS($F$2:$F$46,O19,$Q$2:$Q$46,"Aprobada")>0)),O19&" ","")&IF(NOT(OR(P19="",COUNTIF($F$2:$F$46,P19)=0,COUNTIFS($F$2:$F$46,P19,$Q$2:$Q$46,"Aprobada")>0)),P19&" ","")),IF(Q19="Cursada aprobada",TRIM(IF(NOT(OR(L19="",COUNTIF($F$2:$F$46,L19)=0,COUNTIFS($F$2:$F$46,L19,$Q$2:$Q$46,"Aprobada")>0,AND(Resumen!$B$15="La cursada aprobada",COUNTIFS($F$2:$F$46,L19,$Q$2:$Q$46,"Cursada aprobada")>0))),L19&" ","")&IF(NOT(OR(M19="",COUNTIF($F$2:$F$46,M19)=0,COUNTIFS($F$2:$F$46,M19,$Q$2:$Q$46,"Aprobada")>0,AND(Resumen!$B$15="La cursada aprobada",COUNTIFS($F$2:$F$46,M19,$Q$2:$Q$46,"Cursada aprobada")>0))),M19&" ","")&IF(NOT(OR(N19="",COUNTIF($F$2:$F$46,N19)=0,COUNTIFS($F$2:$F$46,N19,$Q$2:$Q$46,"Aprobada")>0,AND(Resumen!$B$15="La cursada aprobada",COUNTIFS($F$2:$F$46,N19,$Q$2:$Q$46,"Cursada aprobada")>0))),N19&" ","")&IF(NOT(OR(O19="",COUNTIF($F$2:$F$46,O19)=0,COUNTIFS($F$2:$F$46,O19,$Q$2:$Q$46,"Aprobada")>0,AND(Resumen!$B$15="La cursada aprobada",COUNTIFS($F$2:$F$46,O19,$Q$2:$Q$46,"Cursada aprobada")>0))),O19&" ","")&IF(NOT(OR(P19="",COUNTIF($F$2:$F$46,P19)=0,COUNTIFS($F$2:$F$46,P19,$Q$2:$Q$46,"Aprobada")>0,AND(Resumen!$B$15="La cursada aprobada",COUNTIFS($F$2:$F$46,P19,$Q$2:$Q$46,"Cursada aprobada")>0))),P19&" ","")),""))
A20: Ciclo profesional | C20: 3 | D20: 1 | E20: JU | F20: 340 | G20: Derecho Privado | H20: II | I20: 4 | K20: 64 | L20: 202 | M20: 307 | Q20: No cursada | R20: =IF(Q20="Aprobada","Ya aprobada",IF(Q20="Cursada aprobada","Ya cursada",IF(AND(OR(L20="",COUNTIF($F$2:$F$46,L20)=0,COUNTIFS($F$2:$F$46,L20,$Q$2:$Q$46,"Aprobada")>0,AND(Resumen!$B$15="La cursada aprobada",COUNTIFS($F$2:$F$46,L20,$Q$2:$Q$46,"Cursada aprobada")>0)),OR(M20="",COUNTIF($F$2:$F$46,M20)=0,COUNTIFS($F$2:$F$46,M20,$Q$2:$Q$46,"Aprobada")>0,AND(Resumen!$B$15="La cursada aprobada",COUNTIFS($F$2:$F$46,M20,$Q$2:$Q$46,"Cursada aprobada")>0)),OR(N20="",COUNTIF($F$2:$F$46,N20)=0,COUNTIFS($F$2:$F$46,N20,$Q$2:$Q$46,"Aprobada")>0,AND(Resumen!$B$15="La cursada aprobada",COUNTIFS($F$2:$F$46,N20,$Q$2:$Q$46,"Cursada aprobada")>0)),OR(O20="",COUNTIF($F$2:$F$46,O20)=0,COUNTIFS($F$2:$F$46,O20,$Q$2:$Q$46,"Aprobada")>0,AND(Resumen!$B$15="La cursada aprobada",COUNTIFS($F$2:$F$46,O20,$Q$2:$Q$46,"Cursada aprobada")>0)),OR(P20="",COUNTIF($F$2:$F$46,P20)=0,COUNTIFS($F$2:$F$46,P20,$Q$2:$Q$46,"Aprobada")>0,AND(Resumen!$B$15="La cursada aprobada",COUNTIFS($F$2:$F$46,P20,$Q$2:$Q$46,"Cursada aprobada")>0))),"Sí","No"))) -> No | S20: =TRIM(IF(NOT(OR(L20="",COUNTIF($F$2:$F$46,L20)=0,COUNTIFS($F$2:$F$46,L20,$Q$2:$Q$46,"Aprobada")>0,AND(Resumen!$B$15="La cursada aprobada",COUNTIFS($F$2:$F$46,L20,$Q$2:$Q$46,"Cursada aprobada")>0))),L20&" ","")&IF(NOT(OR(M20="",COUNTIF($F$2:$F$46,M20)=0,COUNTIFS($F$2:$F$46,M20,$Q$2:$Q$46,"Aprobada")>0,AND(Resumen!$B$15="La cursada aprobada",COUNTIFS($F$2:$F$46,M20,$Q$2:$Q$46,"Cursada aprobada")>0))),M20&" ","")&IF(NOT(OR(N20="",COUNTIF($F$2:$F$46,N20)=0,COUNTIFS($F$2:$F$46,N20,$Q$2:$Q$46,"Aprobada")>0,AND(Resumen!$B$15="La cursada aprobada",COUNTIFS($F$2:$F$46,N20,$Q$2:$Q$46,"Cursada aprobada")>0))),N20&" ","")&IF(NOT(OR(O20="",COUNTIF($F$2:$F$46,O20)=0,COUNTIFS($F$2:$F$46,O20,$Q$2:$Q$46,"Aprobada")>0,AND(Resumen!$B$15="La cursada aprobada",COUNTIFS($F$2:$F$46,O20,$Q$2:$Q$46,"Cursada aprobada")>0))),O20&" ","")&IF(NOT(OR(P20="",COUNTIF($F$2:$F$46,P20)=0,COUNTIFS($F$2:$F$46,P20,$Q$2:$Q$46,"Aprobada")>0,AND(Resumen!$B$15="La cursada aprobada",COUNTIFS($F$2:$F$46,P20,$Q$2:$Q$46,"Cursada aprobada")>0))),P20&" ","")) -> 202 307 | T20: =IF(Q20="Cursada aprobada",IF(AND(OR(L20="",COUNTIF($F$2:$F$46,L20)=0,COUNTIFS($F$2:$F$46,L20,$Q$2:$Q$46,"Aprobada")>0),OR(M20="",COUNTIF($F$2:$F$46,M20)=0,COUNTIFS($F$2:$F$46,M20,$Q$2:$Q$46,"Aprobada")>0),OR(N20="",COUNTIF($F$2:$F$46,N20)=0,COUNTIFS($F$2:$F$46,N20,$Q$2:$Q$46,"Aprobada")>0),OR(O20="",COUNTIF($F$2:$F$46,O20)=0,COUNTIFS($F$2:$F$46,O20,$Q$2:$Q$46,"Aprobada")>0),OR(P20="",COUNTIF($F$2:$F$46,P20)=0,COUNTIFS($F$2:$F$46,P20,$Q$2:$Q$46,"Aprobada")>0)),"Sí","No"),"") | U20: =IF(Q20="Aprobada",TRIM(IF(NOT(OR(L20="",COUNTIF($F$2:$F$46,L20)=0,COUNTIFS($F$2:$F$46,L20,$Q$2:$Q$46,"Aprobada")>0)),L20&" ","")&IF(NOT(OR(M20="",COUNTIF($F$2:$F$46,M20)=0,COUNTIFS($F$2:$F$46,M20,$Q$2:$Q$46,"Aprobada")>0)),M20&" ","")&IF(NOT(OR(N20="",COUNTIF($F$2:$F$46,N20)=0,COUNTIFS($F$2:$F$46,N20,$Q$2:$Q$46,"Aprobada")>0)),N20&" ","")&IF(NOT(OR(O20="",COUNTIF($F$2:$F$46,O20)=0,COUNTIFS($F$2:$F$46,O20,$Q$2:$Q$46,"Aprobada")>0)),O20&" ","")&IF(NOT(OR(P20="",COUNTIF($F$2:$F$46,P20)=0,COUNTIFS($F$2:$F$46,P20,$Q$2:$Q$46,"Aprobada")>0)),P20&" ","")),IF(Q20="Cursada aprobada",TRIM(IF(NOT(OR(L20="",COUNTIF($F$2:$F$46,L20)=0,COUNTIFS($F$2:$F$46,L20,$Q$2:$Q$46,"Aprobada")>0,AND(Resumen!$B$15="La cursada aprobada",COUNTIFS($F$2:$F$46,L20,$Q$2:$Q$46,"Cursada aprobada")>0))),L20&" ","")&IF(NOT(OR(M20="",COUNTIF($F$2:$F$46,M20)=0,COUNTIFS($F$2:$F$46,M20,$Q$2:$Q$46,"Aprobada")>0,AND(Resumen!$B$15="La cursada aprobada",COUNTIFS($F$2:$F$46,M20,$Q$2:$Q$46,"Cursada aprobada")>0))),M20&" ","")&IF(NOT(OR(N20="",COUNTIF($F$2:$F$46,N20)=0,COUNTIFS($F$2:$F$46,N20,$Q$2:$Q$46,"Aprobada")>0,AND(Resumen!$B$15="La cursada aprobada",COUNTIFS($F$2:$F$46,N20,$Q$2:$Q$46,"Cursada aprobada")>0))),N20&" ","")&IF(NOT(OR(O20="",COUNTIF($F$2:$F$46,O20)=0,COUNTIFS($F$2:$F$46,O20,$Q$2:$Q$46,"Aprobada")>0,AND(Resumen!$B$15="La cursada aprobada",COUNTIFS($F$2:$F$46,O20,$Q$2:$Q$46,"Cursada aprobada")>0))),O20&" ","")&IF(NOT(OR(P20="",COUNTIF($F$2:$F$46,P20)=0,COUNTIFS($F$2:$F$46,P20,$Q$2:$Q$46,"Aprobada")>0,AND(Resumen!$B$15="La cursada aprobada",COUNTIFS($F$2:$F$46,P20,$Q$2:$Q$46,"Cursada aprobada")>0))),P20&" ","")),""))
A21: Ciclo profesional | C21: 3 | D21: 2 | E21: CO | F21: 401 | G21: Costos | H21: I | I21: 6 | K21: 96 | L21: 210 | Q21: No cursada | R21: =IF(Q21="Aprobada","Ya aprobada",IF(Q21="Cursada aprobada","Ya cursada",IF(AND(OR(L21="",COUNTIF($F$2:$F$46,L21)=0,COUNTIFS($F$2:$F$46,L21,$Q$2:$Q$46,"Aprobada")>0,AND(Resumen!$B$15="La cursada aprobada",COUNTIFS($F$2:$F$46,L21,$Q$2:$Q$46,"Cursada aprobada")>0)),OR(M21="",COUNTIF($F$2:$F$46,M21)=0,COUNTIFS($F$2:$F$46,M21,$Q$2:$Q$46,"Aprobada")>0,AND(Resumen!$B$15="La cursada aprobada",COUNTIFS($F$2:$F$46,M21,$Q$2:$Q$46,"Cursada aprobada")>0)),OR(N21="",COUNTIF($F$2:$F$46,N21)=0,COUNTIFS($F$2:$F$46,N21,$Q$2:$Q$46,"Aprobada")>0,AND(Resumen!$B$15="La cursada aprobada",COUNTIFS($F$2:$F$46,N21,$Q$2:$Q$46,"Cursada aprobada")>0)),OR(O21="",COUNTIF($F$2:$F$46,O21)=0,COUNTIFS($F$2:$F$46,O21,$Q$2:$Q$46,"Aprobada")>0,AND(Resumen!$B$15="La cursada aprobada",COUNTIFS($F$2:$F$46,O21,$Q$2:$Q$46,"Cursada aprobada")>0)),OR(P21="",COUNTIF($F$2:$F$46,P21)=0,COUNTIFS($F$2:$F$46,P21,$Q$2:$Q$46,"Aprobada")>0,AND(Resumen!$B$15="La cursada aprobada",COUNTIFS($F$2:$F$46,P21,$Q$2:$Q$46,"Cursada aprobada")>0))),"Sí","No"))) -> No | S21: =TRIM(IF(NOT(OR(L21="",COUNTIF($F$2:$F$46,L21)=0,COUNTIFS($F$2:$F$46,L21,$Q$2:$Q$46,"Aprobada")>0,AND(Resumen!$B$15="La cursada aprobada",COUNTIFS($F$2:$F$46,L21,$Q$2:$Q$46,"Cursada aprobada")>0))),L21&" ","")&IF(NOT(OR(M21="",COUNTIF($F$2:$F$46,M21)=0,COUNTIFS($F$2:$F$46,M21,$Q$2:$Q$46,"Aprobada")>0,AND(Resumen!$B$15="La cursada aprobada",COUNTIFS($F$2:$F$46,M21,$Q$2:$Q$46,"Cursada aprobada")>0))),M21&" ","")&IF(NOT(OR(N21="",COUNTIF($F$2:$F$46,N21)=0,COUNTIFS($F$2:$F$46,N21,$Q$2:$Q$46,"Aprobada")>0,AND(Resumen!$B$15="La cursada aprobada",COUNTIFS($F$2:$F$46,N21,$Q$2:$Q$46,"Cursada aprobada")>0))),N21&" ","")&IF(NOT(OR(O21="",COUNTIF($F$2:$F$46,O21)=0,COUNTIFS($F$2:$F$46,O21,$Q$2:$Q$46,"Aprobada")>0,AND(Resumen!$B$15="La cursada aprobada",COUNTIFS($F$2:$F$46,O21,$Q$2:$Q$46,"Cursada aprobada")>0))),O21&" ","")&IF(NOT(OR(P21="",COUNTIF($F$2:$F$46,P21)=0,COUNTIFS($F$2:$F$46,P21,$Q$2:$Q$46,"Aprobada")>0,AND(Resumen!$B$15="La cursada aprobada",COUNTIFS($F$2:$F$46,P21,$Q$2:$Q$46,"Cursada aprobada")>0))),P21&" ","")) -> 210 | T21: =IF(Q21="Cursada aprobada",IF(AND(OR(L21="",COUNTIF($F$2:$F$46,L21)=0,COUNTIFS($F$2:$F$46,L21,$Q$2:$Q$46,"Aprobada")>0),OR(M21="",COUNTIF($F$2:$F$46,M21)=0,COUNTIFS($F$2:$F$46,M21,$Q$2:$Q$46,"Aprobada")>0),OR(N21="",COUNTIF($F$2:$F$46,N21)=0,COUNTIFS($F$2:$F$46,N21,$Q$2:$Q$46,"Aprobada")>0),OR(O21="",COUNTIF($F$2:$F$46,O21)=0,COUNTIFS($F$2:$F$46,O21,$Q$2:$Q$46,"Aprobada")>0),OR(P21="",COUNTIF($F$2:$F$46,P21)=0,COUNTIFS($F$2:$F$46,P21,$Q$2:$Q$46,"Aprobada")>0)),"Sí","No"),"") | U21: =IF(Q21="Aprobada",TRIM(IF(NOT(OR(L21="",COUNTIF($F$2:$F$46,L21)=0,COUNTIFS($F$2:$F$46,L21,$Q$2:$Q$46,"Aprobada")>0)),L21&" ","")&IF(NOT(OR(M21="",COUNTIF($F$2:$F$46,M21)=0,COUNTIFS($F$2:$F$46,M21,$Q$2:$Q$46,"Aprobada")>0)),M21&" ","")&IF(NOT(OR(N21="",COUNTIF($F$2:$F$46,N21)=0,COUNTIFS($F$2:$F$46,N21,$Q$2:$Q$46,"Aprobada")>0)),N21&" ","")&IF(NOT(OR(O21="",COUNTIF($F$2:$F$46,O21)=0,COUNTIFS($F$2:$F$46,O21,$Q$2:$Q$46,"Aprobada")>0)),O21&" ","")&IF(NOT(OR(P21="",COUNTIF($F$2:$F$46,P21)=0,COUNTIFS($F$2:$F$46,P21,$Q$2:$Q$46,"Aprobada")>0)),P21&" ","")),IF(Q21="Cursada aprobada",TRIM(IF(NOT(OR(L21="",COUNTIF($F$2:$F$46,L21)=0,COUNTIFS($F$2:$F$46,L21,$Q$2:$Q$46,"Aprobada")>0,AND(Resumen!$B$15="La cursada aprobada",COUNTIFS($F$2:$F$46,L21,$Q$2:$Q$46,"Cursada aprobada")>0))),L21&" ","")&IF(NOT(OR(M21="",COUNTIF($F$2:$F$46,M21)=0,COUNTIFS($F$2:$F$46,M21,$Q$2:$Q$46,"Aprobada")>0,AND(Resumen!$B$15="La cursada aprobada",COUNTIFS($F$2:$F$46,M21,$Q$2:$Q$46,"Cursada aprobada")>0))),M21&" ","")&IF(NOT(OR(N21="",COUNTIF($F$2:$F$46,N21)=0,COUNTIFS($F$2:$F$46,N21,$Q$2:$Q$46,"Aprobada")>0,AND(Resumen!$B$15="La cursada aprobada",COUNTIFS($F$2:$F$46,N21,$Q$2:$Q$46,"Cursada aprobada")>0))),N21&" ","")&IF(NOT(OR(O21="",COUNTIF($F$2:$F$46,O21)=0,COUNTIFS($F$2:$F$46,O21,$Q$2:$Q$46,"Aprobada")>0,AND(Resumen!$B$15="La cursada aprobada",COUNTIFS($F$2:$F$46,O21,$Q$2:$Q$46,"Cursada aprobada")>0))),O21&" ","")&IF(NOT(OR(P21="",COUNTIF($F$2:$F$46,P21)=0,COUNTIFS($F$2:$F$46,P21,$Q$2:$Q$46,"Aprobada")>0,AND(Resumen!$B$15="La cursada aprobada",COUNTIFS($F$2:$F$46,P21,$Q$2:$Q$46,"Cursada aprobada")>0))),P21&" ","")),""))
A22: Ciclo profesional | C22: 3 | D22: 2 | E22: CO | F22: 349 | G22: Economía y Org. del Sector Público | H22: I | I22: 6 | K22: 96 | L22: 202 | M22: 314 | Q22: No cursada | R22: =IF(Q22="Aprobada","Ya aprobada",IF(Q22="Cursada aprobada","Ya cursada",IF(AND(OR(L22="",COUNTIF($F$2:$F$46,L22)=0,COUNTIFS($F$2:$F$46,L22,$Q$2:$Q$46,"Aprobada")>0,AND(Resumen!$B$15="La cursada aprobada",COUNTIFS($F$2:$F$46,L22,$Q$2:$Q$46,"Cursada aprobada")>0)),OR(M22="",COUNTIF($F$2:$F$46,M22)=0,COUNTIFS($F$2:$F$46,M22,$Q$2:$Q$46,"Aprobada")>0,AND(Resumen!$B$15="La cursada aprobada",COUNTIFS($F$2:$F$46,M22,$Q$2:$Q$46,"Cursada aprobada")>0)),OR(N22="",COUNTIF($F$2:$F$46,N22)=0,COUNTIFS($F$2:$F$46,N22,$Q$2:$Q$46,"Aprobada")>0,AND(Resumen!$B$15="La cursada aprobada",COUNTIFS($F$2:$F$46,N22,$Q$2:$Q$46,"Cursada aprobada")>0)),OR(O22="",COUNTIF($F$2:$F$46,O22)=0,COUNTIFS($F$2:$F$46,O22,$Q$2:$Q$46,"Aprobada")>0,AND(Resumen!$B$15="La cursada aprobada",COUNTIFS($F$2:$F$46,O22,$Q$2:$Q$46,"Cursada aprobada")>0)),OR(P22="",COUNTIF($F$2:$F$46,P22)=0,COUNTIFS($F$2:$F$46,P22,$Q$2:$Q$46,"Aprobada")>0,AND(Resumen!$B$15="La cursada aprobada",COUNTIFS($F$2:$F$46,P22,$Q$2:$Q$46,"Cursada aprobada")>0))),"Sí","No"))) -> No | S22: =TRIM(IF(NOT(OR(L22="",COUNTIF($F$2:$F$46,L22)=0,COUNTIFS($F$2:$F$46,L22,$Q$2:$Q$46,"Aprobada")>0,AND(Resumen!$B$15="La cursada aprobada",COUNTIFS($F$2:$F$46,L22,$Q$2:$Q$46,"Cursada aprobada")>0))),L22&" ","")&IF(NOT(OR(M22="",COUNTIF($F$2:$F$46,M22)=0,COUNTIFS($F$2:$F$46,M22,$Q$2:$Q$46,"Aprobada")>0,AND(Resumen!$B$15="La cursada aprobada",COUNTIFS($F$2:$F$46,M22,$Q$2:$Q$46,"Cursada aprobada")>0))),M22&" ","")&IF(NOT(OR(N22="",COUNTIF($F$2:$F$46,N22)=0,COUNTIFS($F$2:$F$46,N22,$Q$2:$Q$46,"Aprobada")>0,AND(Resumen!$B$15="La cursada aprobada",COUNTIFS($F$2:$F$46,N22,$Q$2:$Q$46,"Cursada aprobada")>0))),N22&" ","")&IF(NOT(OR(O22="",COUNTIF($F$2:$F$46,O22)=0,COUNTIFS($F$2:$F$46,O22,$Q$2:$Q$46,"Aprobada")>0,AND(Resumen!$B$15="La cursada aprobada",COUNTIFS($F$2:$F$46,O22,$Q$2:$Q$46,"Cursada aprobada")>0))),O22&" ","")&IF(NOT(OR(P22="",COUNTIF($F$2:$F$46,P22)=0,COUNTIFS($F$2:$F$46,P22,$Q$2:$Q$46,"Aprobada")>0,AND(Resumen!$B$15="La cursada aprobada",COUNTIFS($F$2:$F$46,P22,$Q$2:$Q$46,"Cursada aprobada")>0))),P22&" ","")) -> 202 314 | T22: =IF(Q22="Cursada aprobada",IF(AND(OR(L22="",COUNTIF($F$2:$F$46,L22)=0,COUNTIFS($F$2:$F$46,L22,$Q$2:$Q$46,"Aprobada")>0),OR(M22="",COUNTIF($F$2:$F$46,M22)=0,COUNTIFS($F$2:$F$46,M22,$Q$2:$Q$46,"Aprobada")>0),OR(N22="",COUNTIF($F$2:$F$46,N22)=0,COUNTIFS($F$2:$F$46,N22,$Q$2:$Q$46,"Aprobada")>0),OR(O22="",COUNTIF($F$2:$F$46,O22)=0,COUNTIFS($F$2:$F$46,O22,$Q$2:$Q$46,"Aprobada")>0),OR(P22="",COUNTIF($F$2:$F$46,P22)=0,COUNTIFS($F$2:$F$46,P22,$Q$2:$Q$46,"Aprobada")>0)),"Sí","No"),"") | U22: =IF(Q22="Aprobada",TRIM(IF(NOT(OR(L22="",COUNTIF($F$2:$F$46,L22)=0,COUNTIFS($F$2:$F$46,L22,$Q$2:$Q$46,"Aprobada")>0)),L22&" ","")&IF(NOT(OR(M22="",COUNTIF($F$2:$F$46,M22)=0,COUNTIFS($F$2:$F$46,M22,$Q$2:$Q$46,"Aprobada")>0)),M22&" ","")&IF(NOT(OR(N22="",COUNTIF($F$2:$F$46,N22)=0,COUNTIFS($F$2:$F$46,N22,$Q$2:$Q$46,"Aprobada")>0)),N22&" ","")&IF(NOT(OR(O22="",COUNTIF($F$2:$F$46,O22)=0,COUNTIFS($F$2:$F$46,O22,$Q$2:$Q$46,"Aprobada")>0)),O22&" ","")&IF(NOT(OR(P22="",COUNTIF($F$2:$F$46,P22)=0,COUNTIFS($F$2:$F$46,P22,$Q$2:$Q$46,"Aprobada")>0)),P22&" ","")),IF(Q22="Cursada aprobada",TRIM(IF(NOT(OR(L22="",COUNTIF($F$2:$F$46,L22)=0,COUNTIFS($F$2:$F$46,L22,$Q$2:$Q$46,"Aprobada")>0,AND(Resumen!$B$15="La cursada aprobada",COUNTIFS($F$2:$F$46,L22,$Q$2:$Q$46,"Cursada aprobada")>0))),L22&" ","")&IF(NOT(OR(M22="",COUNTIF($F$2:$F$46,M22)=0,COUNTIFS($F$2:$F$46,M22,$Q$2:$Q$46,"Aprobada")>0,AND(Resumen!$B$15="La cursada aprobada",COUNTIFS($F$2:$F$46,M22,$Q$2:$Q$46,"Cursada aprobada")>0))),M22&" ","")&IF(NOT(OR(N22="",COUNTIF($F$2:$F$46,N22)=0,COUNTIFS($F$2:$F$46,N22,$Q$2:$Q$46,"Aprobada")>0,AND(Resumen!$B$15="La cursada aprobada",COUNTIFS($F$2:$F$46,N22,$Q$2:$Q$46,"Cursada aprobada")>0))),N22&" ","")&IF(NOT(OR(O22="",COUNTIF($F$2:$F$46,O22)=0,COUNTIFS($F$2:$F$46,O22,$Q$2:$Q$46,"Aprobada")>0,AND(Resumen!$B$15="La cursada aprobada",COUNTIFS($F$2:$F$46,O22,$Q$2:$Q$46,"Cursada aprobada")>0))),O22&" ","")&IF(NOT(OR(P22="",COUNTIF($F$2:$F$46,P22)=0,COUNTIFS($F$2:$F$46,P22,$Q$2:$Q$46,"Aprobada")>0,AND(Resumen!$B$15="La cursada aprobada",COUNTIFS($F$2:$F$46,P22,$Q$2:$Q$46,"Cursada aprobada")>0))),P22&" ","")),""))
A23: Ciclo profesional | C23: 3 | D23: 2 | E23: JU | F23: 503 | G23: Sociedades | H23: II | I23: 4 | K23: 64 | L23: 340 | Q23: No cursada | R23: =IF(Q23="Aprobada","Ya aprobada",IF(Q23="Cursada aprobada","Ya cursada",IF(AND(OR(L23="",COUNTIF($F$2:$F$46,L23)=0,COUNTIFS($F$2:$F$46,L23,$Q$2:$Q$46,"Aprobada")>0,AND(Resumen!$B$15="La cursada aprobada",COUNTIFS($F$2:$F$46,L23,$Q$2:$Q$46,"Cursada aprobada")>0)),OR(M23="",COUNTIF($F$2:$F$46,M23)=0,COUNTIFS($F$2:$F$46,M23,$Q$2:$Q$46,"Aprobada")>0,AND(Resumen!$B$15="La cursada aprobada",COUNTIFS($F$2:$F$46,M23,$Q$2:$Q$46,"Cursada aprobada")>0)),OR(N23="",COUNTIF($F$2:$F$46,N23)=0,COUNTIFS($F$2:$F$46,N23,$Q$2:$Q$46,"Aprobada")>0,AND(Resumen!$B$15="La cursada aprobada",COUNTIFS($F$2:$F$46,N23,$Q$2:$Q$46,"Cursada aprobada")>0)),OR(O23="",COUNTIF($F$2:$F$46,O23)=0,COUNTIFS($F$2:$F$46,O23,$Q$2:$Q$46,"Aprobada")>0,AND(Resumen!$B$15="La cursada aprobada",COUNTIFS($F$2:$F$46,O23,$Q$2:$Q$46,"Cursada aprobada")>0)),OR(P23="",COUNTIF($F$2:$F$46,P23)=0,COUNTIFS($F$2:$F$46,P23,$Q$2:$Q$46,"Aprobada")>0,AND(Resumen!$B$15="La cursada aprobada",COUNTIFS($F$2:$F$46,P23,$Q$2:$Q$46,"Cursada aprobada")>0))),"Sí","No"))) -> No | S23: =TRIM(IF(NOT(OR(L23="",COUNTIF($F$2:$F$46,L23)=0,COUNTIFS($F$2:$F$46,L23,$Q$2:$Q$46,"Aprobada")>0,AND(Resumen!$B$15="La cursada aprobada",COUNTIFS($F$2:$F$46,L23,$Q$2:$Q$46,"Cursada aprobada")>0))),L23&" ","")&IF(NOT(OR(M23="",COUNTIF($F$2:$F$46,M23)=0,COUNTIFS($F$2:$F$46,M23,$Q$2:$Q$46,"Aprobada")>0,AND(Resumen!$B$15="La cursada aprobada",COUNTIFS($F$2:$F$46,M23,$Q$2:$Q$46,"Cursada aprobada")>0))),M23&" ","")&IF(NOT(OR(N23="",COUNTIF($F$2:$F$46,N23)=0,COUNTIFS($F$2:$F$46,N23,$Q$2:$Q$46,"Aprobada")>0,AND(Resumen!$B$15="La cursada aprobada",COUNTIFS($F$2:$F$46,N23,$Q$2:$Q$46,"Cursada aprobada")>0))),N23&" ","")&IF(NOT(OR(O23="",COUNTIF($F$2:$F$46,O23)=0,COUNTIFS($F$2:$F$46,O23,$Q$2:$Q$46,"Aprobada")>0,AND(Resumen!$B$15="La cursada aprobada",COUNTIFS($F$2:$F$46,O23,$Q$2:$Q$46,"Cursada aprobada")>0))),O23&" ","")&IF(NOT(OR(P23="",COUNTIF($F$2:$F$46,P23)=0,COUNTIFS($F$2:$F$46,P23,$Q$2:$Q$46,"Aprobada")>0,AND(Resumen!$B$15="La cursada aprobada",COUNTIFS($F$2:$F$46,P23,$Q$2:$Q$46,"Cursada aprobada")>0))),P23&" ","")) -> 340 | T23: =IF(Q23="Cursada aprobada",IF(AND(OR(L23="",COUNTIF($F$2:$F$46,L23)=0,COUNTIFS($F$2:$F$46,L23,$Q$2:$Q$46,"Aprobada")>0),OR(M23="",COUNTIF($F$2:$F$46,M23)=0,COUNTIFS($F$2:$F$46,M23,$Q$2:$Q$46,"Aprobada")>0),OR(N23="",COUNTIF($F$2:$F$46,N23)=0,COUNTIFS($F$2:$F$46,N23,$Q$2:$Q$46,"Aprobada")>0),OR(O23="",COUNTIF($F$2:$F$46,O23)=0,COUNTIFS($F$2:$F$46,O23,$Q$2:$Q$46,"Aprobada")>0),OR(P23="",COUNTIF($F$2:$F$46,P23)=0,COUNTIFS($F$2:$F$46,P23,$Q$2:$Q$46,"Aprobada")>0)),"Sí","No"),"") | U23: =IF(Q23="Aprobada",TRIM(IF(NOT(OR(L23="",COUNTIF($F$2:$F$46,L23)=0,COUNTIFS($F$2:$F$46,L23,$Q$2:$Q$46,"Aprobada")>0)),L23&" ","")&IF(NOT(OR(M23="",COUNTIF($F$2:$F$46,M23)=0,COUNTIFS($F$2:$F$46,M23,$Q$2:$Q$46,"Aprobada")>0)),M23&" ","")&IF(NOT(OR(N23="",COUNTIF($F$2:$F$46,N23)=0,COUNTIFS($F$2:$F$46,N23,$Q$2:$Q$46,"Aprobada")>0)),N23&" ","")&IF(NOT(OR(O23="",COUNTIF($F$2:$F$46,O23)=0,COUNTIFS($F$2:$F$46,O23,$Q$2:$Q$46,"Aprobada")>0)),O23&" ","")&IF(NOT(OR(P23="",COUNTIF($F$2:$F$46,P23)=0,COUNTIFS($F$2:$F$46,P23,$Q$2:$Q$46,"Aprobada")>0)),P23&" ","")),IF(Q23="Cursada aprobada",TRIM(IF(NOT(OR(L23="",COUNTIF($F$2:$F$46,L23)=0,COUNTIFS($F$2:$F$46,L23,$Q$2:$Q$46,"Aprobada")>0,AND(Resumen!$B$15="La cursada aprobada",COUNTIFS($F$2:$F$46,L23,$Q$2:$Q$46,"Cursada aprobada")>0))),L23&" ","")&IF(NOT(OR(M23="",COUNTIF($F$2:$F$46,M23)=0,COUNTIFS($F$2:$F$46,M23,$Q$2:$Q$46,"Aprobada")>0,AND(Resumen!$B$15="La cursada aprobada",COUNTIFS($F$2:$F$46,M23,$Q$2:$Q$46,"Cursada aprobada")>0))),M23&" ","")&IF(NOT(OR(N23="",COUNTIF($F$2:$F$46,N23)=0,COUNTIFS($F$2:$F$46,N23,$Q$2:$Q$46,"Aprobada")>0,AND(Resumen!$B$15="La cursada aprobada",COUNTIFS($F$2:$F$46,N23,$Q$2:$Q$46,"Cursada aprobada")>0))),N23&" ","")&IF(NOT(OR(O23="",COUNTIF($F$2:$F$46,O23)=0,COUNTIFS($F$2:$F$46,O23,$Q$2:$Q$46,"Aprobada")>0,AND(Resumen!$B$15="La cursada aprobada",COUNTIFS($F$2:$F$46,O23,$Q$2:$Q$46,"Cursada aprobada")>0))),O23&" ","")&IF(NOT(OR(P23="",COUNTIF($F$2:$F$46,P23)=0,COUNTIFS($F$2:$F$46,P23,$Q$2:$Q$46,"Aprobada")>0,AND(Resumen!$B$15="La cursada aprobada",COUNTIFS($F$2:$F$46,P23,$Q$2:$Q$46,"Cursada aprobada")>0))),P23&" ","")),""))
A24: Ciclo profesional | C24: 3 | D24: 2 | E24: CS | F24: 201 | G24: Metodología de las Ciencias Sociales | H24: III | I24: 3 | K24: 48 | L24: 250 | Q24: No cursada | R24: =IF(Q24="Aprobada","Ya aprobada",IF(Q24="Cursada aprobada","Ya cursada",IF(AND(OR(L24="",COUNTIF($F$2:$F$46,L24)=0,COUNTIFS($F$2:$F$46,L24,$Q$2:$Q$46,"Aprobada")>0,AND(Resumen!$B$15="La cursada aprobada",COUNTIFS($F$2:$F$46,L24,$Q$2:$Q$46,"Cursada aprobada")>0)),OR(M24="",COUNTIF($F$2:$F$46,M24)=0,COUNTIFS($F$2:$F$46,M24,$Q$2:$Q$46,"Aprobada")>0,AND(Resumen!$B$15="La cursada aprobada",COUNTIFS($F$2:$F$46,M24,$Q$2:$Q$46,"Cursada aprobada")>0)),OR(N24="",COUNTIF($F$2:$F$46,N24)=0,COUNTIFS($F$2:$F$46,N24,$Q$2:$Q$46,"Aprobada")>0,AND(Resumen!$B$15="La cursada aprobada",COUNTIFS($F$2:$F$46,N24,$Q$2:$Q$46,"Cursada aprobada")>0)),OR(O24="",COUNTIF($F$2:$F$46,O24)=0,COUNTIFS($F$2:$F$46,O24,$Q$2:$Q$46,"Aprobada")>0,AND(Resumen!$B$15="La cursada aprobada",COUNTIFS($F$2:$F$46,O24,$Q$2:$Q$46,"Cursada aprobada")>0)),OR(P24="",COUNTIF($F$2:$F$46,P24)=0,COUNTIFS($F$2:$F$46,P24,$Q$2:$Q$46,"Aprobada")>0,AND(Resumen!$B$15="La cursada aprobada",COUNTIFS($F$2:$F$46,P24,$Q$2:$Q$46,"Cursada aprobada")>0))),"Sí","No"))) -> No | S24: =TRIM(IF(NOT(OR(L24="",COUNTIF($F$2:$F$46,L24)=0,COUNTIFS($F$2:$F$46,L24,$Q$2:$Q$46,"Aprobada")>0,AND(Resumen!$B$15="La cursada aprobada",COUNTIFS($F$2:$F$46,L24,$Q$2:$Q$46,"Cursada aprobada")>0))),L24&" ","")&IF(NOT(OR(M24="",COUNTIF($F$2:$F$46,M24)=0,COUNTIFS($F$2:$F$46,M24,$Q$2:$Q$46,"Aprobada")>0,AND(Resumen!$B$15="La cursada aprobada",COUNTIFS($F$2:$F$46,M24,$Q$2:$Q$46,"Cursada aprobada")>0))),M24&" ","")&IF(NOT(OR(N24="",COUNTIF($F$2:$F$46,N24)=0,COUNTIFS($F$2:$F$46,N24,$Q$2:$Q$46,"Aprobada")>0,AND(Resumen!$B$15="La cursada aprobada",COUNTIFS($F$2:$F$46,N24,$Q$2:$Q$46,"Cursada aprobada")>0))),N24&" ","")&IF(NOT(OR(O24="",COUNTIF($F$2:$F$46,O24)=0,COUNTIFS($F$2:$F$46,O24,$Q$2:$Q$46,"Aprobada")>0,AND(Resumen!$B$15="La cursada aprobada",COUNTIFS($F$2:$F$46,O24,$Q$2:$Q$46,"Cursada aprobada")>0))),O24&" ","")&IF(NOT(OR(P24="",COUNTIF($F$2:$F$46,P24)=0,COUNTIFS($F$2:$F$46,P24,$Q$2:$Q$46,"Aprobada")>0,AND(Resumen!$B$15="La cursada aprobada",COUNTIFS($F$2:$F$46,P24,$Q$2:$Q$46,"Cursada aprobada")>0))),P24&" ","")) -> 250 | T24: =IF(Q24="Cursada aprobada",IF(AND(OR(L24="",COUNTIF($F$2:$F$46,L24)=0,COUNTIFS($F$2:$F$46,L24,$Q$2:$Q$46,"Aprobada")>0),OR(M24="",COUNTIF($F$2:$F$46,M24)=0,COUNTIFS($F$2:$F$46,M24,$Q$2:$Q$46,"Aprobada")>0),OR(N24="",COUNTIF($F$2:$F$46,N24)=0,COUNTIFS($F$2:$F$46,N24,$Q$2:$Q$46,"Aprobada")>0),OR(O24="",COUNTIF($F$2:$F$46,O24)=0,COUNTIFS($F$2:$F$46,O24,$Q$2:$Q$46,"Aprobada")>0),OR(P24="",COUNTIF($F$2:$F$46,P24)=0,COUNTIFS($F$2:$F$46,P24,$Q$2:$Q$46,"Aprobada")>0)),"Sí","No"),"") | U24: =IF(Q24="Aprobada",TRIM(IF(NOT(OR(L24="",COUNTIF($F$2:$F$46,L24)=0,COUNTIFS($F$2:$F$46,L24,$Q$2:$Q$46,"Aprobada")>0)),L24&" ","")&IF(NOT(OR(M24="",COUNTIF($F$2:$F$46,M24)=0,COUNTIFS($F$2:$F$46,M24,$Q$2:$Q$46,"Aprobada")>0)),M24&" ","")&IF(NOT(OR(N24="",COUNTIF($F$2:$F$46,N24)=0,COUNTIFS($F$2:$F$46,N24,$Q$2:$Q$46,"Aprobada")>0)),N24&" ","")&IF(NOT(OR(O24="",COUNTIF($F$2:$F$46,O24)=0,COUNTIFS($F$2:$F$46,O24,$Q$2:$Q$46,"Aprobada")>0)),O24&" ","")&IF(NOT(OR(P24="",COUNTIF($F$2:$F$46,P24)=0,COUNTIFS($F$2:$F$46,P24,$Q$2:$Q$46,"Aprobada")>0)),P24&" ","")),IF(Q24="Cursada aprobada",TRIM(IF(NOT(OR(L24="",COUNTIF($F$2:$F$46,L24)=0,COUNTIFS($F$2:$F$46,L24,$Q$2:$Q$46,"Aprobada")>0,AND(Resumen!$B$15="La cursada aprobada",COUNTIFS($F$2:$F$46,L24,$Q$2:$Q$46,"Cursada aprobada")>0))),L24&" ","")&IF(NOT(OR(M24="",COUNTIF($F$2:$F$46,M24)=0,COUNTIFS($F$2:$F$46,M24,$Q$2:$Q$46,"Aprobada")>0,AND(Resumen!$B$15="La cursada aprobada",COUNTIFS($F$2:$F$46,M24,$Q$2:$Q$46,"Cursada aprobada")>0))),M24&" ","")&IF(NOT(OR(N24="",COUNTIF($F$2:$F$46,N24)=0,COUNTIFS($F$2:$F$46,N24,$Q$2:$Q$46,"Aprobada")>0,AND(Resumen!$B$15="La cursada aprobada",COUNTIFS($F$2:$F$46,N24,$Q$2:$Q$46,"Cursada aprobada")>0))),N24&" ","")&IF(NOT(OR(O24="",COUNTIF($F$2:$F$46,O24)=0,COUNTIFS($F$2:$F$46,O24,$Q$2:$Q$46,"Aprobada")>0,AND(Resumen!$B$15="La cursada aprobada",COUNTIFS($F$2:$F$46,O24,$Q$2:$Q$46,"Cursada aprobada")>0))),O24&" ","")&IF(NOT(OR(P24="",COUNTIF($F$2:$F$46,P24)=0,COUNTIFS($F$2:$F$46,P24,$Q$2:$Q$46,"Aprobada")>0,AND(Resumen!$B$15="La cursada aprobada",COUNTIFS($F$2:$F$46,P24,$Q$2:$Q$46,"Cursada aprobada")>0))),P24&" ","")),""))
A25: Ciclo profesional | C25: 4 | D25: 1 | E25: CO | F25: 430 | G25: Análisis Económico y Financiero | H25: I | I25: 6 | K25: 96 | L25: 308 | M25: 314 | N25: 402 | O25: 424 | P25: 401 | Q25: No cursada | R25: =IF(Q25="Aprobada","Ya aprobada",IF(Q25="Cursada aprobada","Ya cursada",IF(AND(OR(L25="",COUNTIF($F$2:$F$46,L25)=0,COUNTIFS($F$2:$F$46,L25,$Q$2:$Q$46,"Aprobada")>0,AND(Resumen!$B$15="La cursada aprobada",COUNTIFS($F$2:$F$46,L25,$Q$2:$Q$46,"Cursada aprobada")>0)),OR(M25="",COUNTIF($F$2:$F$46,M25)=0,COUNTIFS($F$2:$F$46,M25,$Q$2:$Q$46,"Aprobada")>0,AND(Resumen!$B$15="La cursada aprobada",COUNTIFS($F$2:$F$46,M25,$Q$2:$Q$46,"Cursada aprobada")>0)),OR(N25="",COUNTIF($F$2:$F$46,N25)=0,COUNTIFS($F$2:$F$46,N25,$Q$2:$Q$46,"Aprobada")>0,AND(Resumen!$B$15="La cursada aprobada",COUNTIFS($F$2:$F$46,N25,$Q$2:$Q$46,"Cursada aprobada")>0)),OR(O25="",COUNTIF($F$2:$F$46,O25)=0,COUNTIFS($F$2:$F$46,O25,$Q$2:$Q$46,"Aprobada")>0,AND(Resumen!$B$15="La cursada aprobada",COUNTIFS($F$2:$F$46,O25,$Q$2:$Q$46,"Cursada aprobada")>0)),OR(P25="",COUNTIF($F$2:$F$46,P25)=0,COUNTIFS($F$2:$F$46,P25,$Q$2:$Q$46,"Aprobada")>0,AND(Resumen!$B$15="La cursada aprobada",COUNTIFS($F$2:$F$46,P25,$Q$2:$Q$46,"Cursada aprobada")>0))),"Sí","No"))) -> No | S25: =TRIM(IF(NOT(OR(L25="",COUNTIF($F$2:$F$46,L25)=0,COUNTIFS($F$2:$F$46,L25,$Q$2:$Q$46,"Aprobada")>0,AND(Resumen!$B$15="La cursada aprobada",COUNTIFS($F$2:$F$46,L25,$Q$2:$Q$46,"Cursada aprobada")>0))),L25&" ","")&IF(NOT(OR(M25="",COUNTIF($F$2:$F$46,M25)=0,COUNTIFS($F$2:$F$46,M25,$Q$2:$Q$46,"Aprobada")>0,AND(Resumen!$B$15="La cursada aprobada",COUNTIFS($F$2:$F$46,M25,$Q$2:$Q$46,"Cursada aprobada")>0))),M25&" ","")&IF(NOT(OR(N25="",COUNTIF($F$2:$F$46,N25)=0,COUNTIFS($F$2:$F$46,N25,$Q$2:$Q$46,"Aprobada")>0,AND(Resumen!$B$15="La cursada aprobada",COUNTIFS($F$2:$F$46,N25,$Q$2:$Q$46,"Cursada aprobada")>0))),N25&" ","")&IF(NOT(OR(O25="",COUNTIF($F$2:$F$46,O25)=0,COUNTIFS($F$2:$F$46,O25,$Q$2:$Q$46,"Aprobada")>0,AND(Resumen!$B$15="La cursada aprobada",COUNTIFS($F$2:$F$46,O25,$Q$2:$Q$46,"Cursada aprobada")>0))),O25&" ","")&IF(NOT(OR(P25="",COUNTIF($F$2:$F$46,P25)=0,COUNTIFS($F$2:$F$46,P25,$Q$2:$Q$46,"Aprobada")>0,AND(Resumen!$B$15="La cursada aprobada",COUNTIFS($F$2:$F$46,P25,$Q$2:$Q$46,"Cursada aprobada")>0))),P25&" ","")) -> 308 314 402 424 401 | T25: =IF(Q25="Cursada aprobada",IF(AND(OR(L25="",COUNTIF($F$2:$F$46,L25)=0,COUNTIFS($F$2:$F$46,L25,$Q$2:$Q$46,"Aprobada")>0),OR(M25="",COUNTIF($F$2:$F$46,M25)=0,COUNTIFS($F$2:$F$46,M25,$Q$2:$Q$46,"Aprobada")>0),OR(N25="",COUNTIF($F$2:$F$46,N25)=0,COUNTIFS($F$2:$F$46,N25,$Q$2:$Q$46,"Aprobada")>0),OR(O25="",COUNTIF($F$2:$F$46,O25)=0,COUNTIFS($F$2:$F$46,O25,$Q$2:$Q$46,"Aprobada")>0),OR(P25="",COUNTIF($F$2:$F$46,P25)=0,COUNTIFS($F$2:$F$46,P25,$Q$2:$Q$46,"Aprobada")>0)),"Sí","No"),"") | U25: =IF(Q25="Aprobada",TRIM(IF(NOT(OR(L25="",COUNTIF($F$2:$F$46,L25)=0,COUNTIFS($F$2:$F$46,L25,$Q$2:$Q$46,"Aprobada")>0)),L25&" ","")&IF(NOT(OR(M25="",COUNTIF($F$2:$F$46,M25)=0,COUNTIFS($F$2:$F$46,M25,$Q$2:$Q$46,"Aprobada")>0)),M25&" ","")&IF(NOT(OR(N25="",COUNTIF($F$2:$F$46,N25)=0,COUNTIFS($F$2:$F$46,N25,$Q$2:$Q$46,"Aprobada")>0)),N25&" ","")&IF(NOT(OR(O25="",COUNTIF($F$2:$F$46,O25)=0,COUNTIFS($F$2:$F$46,O25,$Q$2:$Q$46,"Aprobada")>0)),O25&" ","")&IF(NOT(OR(P25="",COUNTIF($F$2:$F$46,P25)=0,COUNTIFS($F$2:$F$46,P25,$Q$2:$Q$46,"Aprobada")>0)),P25&" ","")),IF(Q25="Cursada aprobada",TRIM(IF(NOT(OR(L25="",COUNTIF($F$2:$F$46,L25)=0,COUNTIFS($F$2:$F$46,L25,$Q$2:$Q$46,"Aprobada")>0,AND(Resumen!$B$15="La cursada aprobada",COUNTIFS($F$2:$F$46,L25,$Q$2:$Q$46,"Cursada aprobada")>0))),L25&" ","")&IF(NOT(OR(M25="",COUNTIF($F$2:$F$46,M25)=0,COUNTIFS($F$2:$F$46,M25,$Q$2:$Q$46,"Aprobada")>0,AND(Resumen!$B$15="La cursada aprobada",COUNTIFS($F$2:$F$46,M25,$Q$2:$Q$46,"Cursada aprobada")>0))),M25&" ","")&IF(NOT(OR(N25="",COUNTIF($F$2:$F$46,N25)=0,COUNTIFS($F$2:$F$46,N25,$Q$2:$Q$46,"Aprobada")>0,AND(Resumen!$B$15="La cursada aprobada",COUNTIFS($F$2:$F$46,N25,$Q$2:$Q$46,"Cursada aprobada")>0))),N25&" ","")&IF(NOT(OR(O25="",COUNTIF($F$2:$F$46,O25)=0,COUNTIFS($F$2:$F$46,O25,$Q$2:$Q$46,"Aprobada")>0,AND(Resumen!$B$15="La cursada aprobada",COUNTIFS($F$2:$F$46,O25,$Q$2:$Q$46,"Cursada aprobada")>0))),O25&" ","")&IF(NOT(OR(P25="",COUNTIF($F$2:$F$46,P25)=0,COUNTIFS($F$2:$F$46,P25,$Q$2:$Q$46,"Aprobada")>0,AND(Resumen!$B$15="La cursada aprobada",COUNTIFS($F$2:$F$46,P25,$Q$2:$Q$46,"Cursada aprobada")>0))),P25&" ","")),""))
A26: Ciclo profesional | C26: 4 | D26: 1 | E26: CO | F26: 460 | G26: Impuestos I | H26: I | I26: 6 | K26: 96 | L26: 307 | M26: 402 | N26: 349 | Q26: No cursada | R26: =IF(Q26="Aprobada","Ya aprobada",IF(Q26="Cursada aprobada","Ya cursada",IF(AND(OR(L26="",COUNTIF($F$2:$F$46,L26)=0,COUNTIFS($F$2:$F$46,L26,$Q$2:$Q$46,"Aprobada")>0,AND(Resumen!$B$15="La cursada aprobada",COUNTIFS($F$2:$F$46,L26,$Q$2:$Q$46,"Cursada aprobada")>0)),OR(M26="",COUNTIF($F$2:$F$46,M26)=0,COUNTIFS($F$2:$F$46,M26,$Q$2:$Q$46,"Aprobada")>0,AND(Resumen!$B$15="La cursada aprobada",COUNTIFS($F$2:$F$46,M26,$Q$2:$Q$46,"Cursada aprobada")>0)),OR(N26="",COUNTIF($F$2:$F$46,N26)=0,COUNTIFS($F$2:$F$46,N26,$Q$2:$Q$46,"Aprobada")>0,AND(Resumen!$B$15="La cursada aprobada",COUNTIFS($F$2:$F$46,N26,$Q$2:$Q$46,"Cursada aprobada")>0)),OR(O26="",COUNTIF($F$2:$F$46,O26)=0,COUNTIFS($F$2:$F$46,O26,$Q$2:$Q$46,"Aprobada")>0,AND(Resumen!$B$15="La cursada aprobada",COUNTIFS($F$2:$F$46,O26,$Q$2:$Q$46,"Cursada aprobada")>0)),OR(P26="",COUNTIF($F$2:$F$46,P26)=0,COUNTIFS($F$2:$F$46,P26,$Q$2:$Q$46,"Aprobada")>0,AND(Resumen!$B$15="La cursada aprobada",COUNTIFS($F$2:$F$46,P26,$Q$2:$Q$46,"Cursada aprobada")>0))),"Sí","No"))) -> No | S26: =TRIM(IF(NOT(OR(L26="",COUNTIF($F$2:$F$46,L26)=0,COUNTIFS($F$2:$F$46,L26,$Q$2:$Q$46,"Aprobada")>0,AND(Resumen!$B$15="La cursada aprobada",COUNTIFS($F$2:$F$46,L26,$Q$2:$Q$46,"Cursada aprobada")>0))),L26&" ","")&IF(NOT(OR(M26="",COUNTIF($F$2:$F$46,M26)=0,COUNTIFS($F$2:$F$46,M26,$Q$2:$Q$46,"Aprobada")>0,AND(Resumen!$B$15="La cursada aprobada",COUNTIFS($F$2:$F$46,M26,$Q$2:$Q$46,"Cursada aprobada")>0))),M26&" ","")&IF(NOT(OR(N26="",COUNTIF($F$2:$F$46,N26)=0,COUNTIFS($F$2:$F$46,N26,$Q$2:$Q$46,"Aprobada")>0,AND(Resumen!$B$15="La cursada aprobada",COUNTIFS($F$2:$F$46,N26,$Q$2:$Q$46,"Cursada aprobada")>0))),N26&" ","")&IF(NOT(OR(O26="",COUNTIF($F$2:$F$46,O26)=0,COUNTIFS($F$2:$F$46,O26,$Q$2:$Q$46,"Aprobada")>0,AND(Resumen!$B$15="La cursada aprobada",COUNTIFS($F$2:$F$46,O26,$Q$2:$Q$46,"Cursada aprobada")>0))),O26&" ","")&IF(NOT(OR(P26="",COUNTIF($F$2:$F$46,P26)=0,COUNTIFS($F$2:$F$46,P26,$Q$2:$Q$46,"Aprobada")>0,AND(Resumen!$B$15="La cursada aprobada",COUNTIFS($F$2:$F$46,P26,$Q$2:$Q$46,"Cursada aprobada")>0))),P26&" ","")) -> 307 402 349 | T26: =IF(Q26="Cursada aprobada",IF(AND(OR(L26="",COUNTIF($F$2:$F$46,L26)=0,COUNTIFS($F$2:$F$46,L26,$Q$2:$Q$46,"Aprobada")>0),OR(M26="",COUNTIF($F$2:$F$46,M26)=0,COUNTIFS($F$2:$F$46,M26,$Q$2:$Q$46,"Aprobada")>0),OR(N26="",COUNTIF($F$2:$F$46,N26)=0,COUNTIFS($F$2:$F$46,N26,$Q$2:$Q$46,"Aprobada")>0),OR(O26="",COUNTIF($F$2:$F$46,O26)=0,COUNTIFS($F$2:$F$46,O26,$Q$2:$Q$46,"Aprobada")>0),OR(P26="",COUNTIF($F$2:$F$46,P26)=0,COUNTIFS($F$2:$F$46,P26,$Q$2:$Q$46,"Aprobada")>0)),"Sí","No"),"") | U26: =IF(Q26="Aprobada",TRIM(IF(NOT(OR(L26="",COUNTIF($F$2:$F$46,L26)=0,COUNTIFS($F$2:$F$46,L26,$Q$2:$Q$46,"Aprobada")>0)),L26&" ","")&IF(NOT(OR(M26="",COUNTIF($F$2:$F$46,M26)=0,COUNTIFS($F$2:$F$46,M26,$Q$2:$Q$46,"Aprobada")>0)),M26&" ","")&IF(NOT(OR(N26="",COUNTIF($F$2:$F$46,N26)=0,COUNTIFS($F$2:$F$46,N26,$Q$2:$Q$46,"Aprobada")>0)),N26&" ","")&IF(NOT(OR(O26="",COUNTIF($F$2:$F$46,O26)=0,COUNTIFS($F$2:$F$46,O26,$Q$2:$Q$46,"Aprobada")>0)),O26&" ","")&IF(NOT(OR(P26="",COUNTIF($F$2:$F$46,P26)=0,COUNTIFS($F$2:$F$46,P26,$Q$2:$Q$46,"Aprobada")>0)),P26&" ","")),IF(Q26="Cursada aprobada",TRIM(IF(NOT(OR(L26="",COUNTIF($F$2:$F$46,L26)=0,COUNTIFS($F$2:$F$46,L26,$Q$2:$Q$46,"Aprobada")>0,AND(Resumen!$B$15="La cursada aprobada",COUNTIFS($F$2:$F$46,L26,$Q$2:$Q$46,"Cursada aprobada")>0))),L26&" ","")&IF(NOT(OR(M26="",COUNTIF($F$2:$F$46,M26)=0,COUNTIFS($F$2:$F$46,M26,$Q$2:$Q$46,"Aprobada")>0,AND(Resumen!$B$15="La cursada aprobada",COUNTIFS($F$2:$F$46,M26,$Q$2:$Q$46,"Cursada aprobada")>0))),M26&" ","")&IF(NOT(OR(N26="",COUNTIF($F$2:$F$46,N26)=0,COUNTIFS($F$2:$F$46,N26,$Q$2:$Q$46,"Aprobada")>0,AND(Resumen!$B$15="La cursada aprobada",COUNTIFS($F$2:$F$46,N26,$Q$2:$Q$46,"Cursada aprobada")>0))),N26&" ","")&IF(NOT(OR(O26="",COUNTIF($F$2:$F$46,O26)=0,COUNTIFS($F$2:$F$46,O26,$Q$2:$Q$46,"Aprobada")>0,AND(Resumen!$B$15="La cursada aprobada",COUNTIFS($F$2:$F$46,O26,$Q$2:$Q$46,"Cursada aprobada")>0))),O26&" ","")&IF(NOT(OR(P26="",COUNTIF($F$2:$F$46,P26)=0,COUNTIFS($F$2:$F$46,P26,$Q$2:$Q$46,"Aprobada")>0,AND(Resumen!$B$15="La cursada aprobada",COUNTIFS($F$2:$F$46,P26,$Q$2:$Q$46,"Cursada aprobada")>0))),P26&" ","")),""))
A27: Ciclo profesional | C27: 4 | D27: 1 | E27: JU | F27: 425 | G27: Derecho del Trabajo y de la Seg. Social | H27: II | I27: 4 | K27: 64 | L27: 307 | M27: 340 | Q27: No cursada | R27: =IF(Q27="Aprobada","Ya aprobada",IF(Q27="Cursada aprobada","Ya cursada",IF(AND(OR(L27="",COUNTIF($F$2:$F$46,L27)=0,COUNTIFS($F$2:$F$46,L27,$Q$2:$Q$46,"Aprobada")>0,AND(Resumen!$B$15="La cursada aprobada",COUNTIFS($F$2:$F$46,L27,$Q$2:$Q$46,"Cursada aprobada")>0)),OR(M27="",COUNTIF($F$2:$F$46,M27)=0,COUNTIFS($F$2:$F$46,M27,$Q$2:$Q$46,"Aprobada")>0,AND(Resumen!$B$15="La cursada aprobada",COUNTIFS($F$2:$F$46,M27,$Q$2:$Q$46,"Cursada aprobada")>0)),OR(N27="",COUNTIF($F$2:$F$46,N27)=0,COUNTIFS($F$2:$F$46,N27,$Q$2:$Q$46,"Aprobada")>0,AND(Resumen!$B$15="La cursada aprobada",COUNTIFS($F$2:$F$46,N27,$Q$2:$Q$46,"Cursada aprobada")>0)),OR(O27="",COUNTIF($F$2:$F$46,O27)=0,COUNTIFS($F$2:$F$46,O27,$Q$2:$Q$46,"Aprobada")>0,AND(Resumen!$B$15="La cursada aprobada",COUNTIFS($F$2:$F$46,O27,$Q$2:$Q$46,"Cursada aprobada")>0)),OR(P27="",COUNTIF($F$2:$F$46,P27)=0,COUNTIFS($F$2:$F$46,P27,$Q$2:$Q$46,"Aprobada")>0,AND(Resumen!$B$15="La cursada aprobada",COUNTIFS($F$2:$F$46,P27,$Q$2:$Q$46,"Cursada aprobada")>0))),"Sí","No"))) -> No | S27: =TRIM(IF(NOT(OR(L27="",COUNTIF($F$2:$F$46,L27)=0,COUNTIFS($F$2:$F$46,L27,$Q$2:$Q$46,"Aprobada")>0,AND(Resumen!$B$15="La cursada aprobada",COUNTIFS($F$2:$F$46,L27,$Q$2:$Q$46,"Cursada aprobada")>0))),L27&" ","")&IF(NOT(OR(M27="",COUNTIF($F$2:$F$46,M27)=0,COUNTIFS($F$2:$F$46,M27,$Q$2:$Q$46,"Aprobada")>0,AND(Resumen!$B$15="La cursada aprobada",COUNTIFS($F$2:$F$46,M27,$Q$2:$Q$46,"Cursada aprobada")>0))),M27&" ","")&IF(NOT(OR(N27="",COUNTIF($F$2:$F$46,N27)=0,COUNTIFS($F$2:$F$46,N27,$Q$2:$Q$46,"Aprobada")>0,AND(Resumen!$B$15="La cursada aprobada",COUNTIFS($F$2:$F$46,N27,$Q$2:$Q$46,"Cursada aprobada")>0))),N27&" ","")&IF(NOT(OR(O27="",COUNTIF($F$2:$F$46,O27)=0,COUNTIFS($F$2:$F$46,O27,$Q$2:$Q$46,"Aprobada")>0,AND(Resumen!$B$15="La cursada aprobada",COUNTIFS($F$2:$F$46,O27,$Q$2:$Q$46,"Cursada aprobada")>0))),O27&" ","")&IF(NOT(OR(P27="",COUNTIF($F$2:$F$46,P27)=0,COUNTIFS($F$2:$F$46,P27,$Q$2:$Q$46,"Aprobada")>0,AND(Resumen!$B$15="La cursada aprobada",COUNTIFS($F$2:$F$46,P27,$Q$2:$Q$46,"Cursada aprobada")>0))),P27&" ","")) -> 307 340 | T27: =IF(Q27="Cursada aprobada",IF(AND(OR(L27="",COUNTIF($F$2:$F$46,L27)=0,COUNTIFS($F$2:$F$46,L27,$Q$2:$Q$46,"Aprobada")>0),OR(M27="",COUNTIF($F$2:$F$46,M27)=0,COUNTIFS($F$2:$F$46,M27,$Q$2:$Q$46,"Aprobada")>0),OR(N27="",COUNTIF($F$2:$F$46,N27)=0,COUNTIFS($F$2:$F$46,N27,$Q$2:$Q$46,"Aprobada")>0),OR(O27="",COUNTIF($F$2:$F$46,O27)=0,COUNTIFS($F$2:$F$46,O27,$Q$2:$Q$46,"Aprobada")>0),OR(P27="",COUNTIF($F$2:$F$46,P27)=0,COUNTIFS($F$2:$F$46,P27,$Q$2:$Q$46,"Aprobada")>0)),"Sí","No"),"") | U27: =IF(Q27="Aprobada",TRIM(IF(NOT(OR(L27="",COUNTIF($F$2:$F$46,L27)=0,COUNTIFS($F$2:$F$46,L27,$Q$2:$Q$46,"Aprobada")>0)),L27&" ","")&IF(NOT(OR(M27="",COUNTIF($F$2:$F$46,M27)=0,COUNTIFS($F$2:$F$46,M27,$Q$2:$Q$46,"Aprobada")>0)),M27&" ","")&IF(NOT(OR(N27="",COUNTIF($F$2:$F$46,N27)=0,COUNTIFS($F$2:$F$46,N27,$Q$2:$Q$46,"Aprobada")>0)),N27&" ","")&IF(NOT(OR(O27="",COUNTIF($F$2:$F$46,O27)=0,COUNTIFS($F$2:$F$46,O27,$Q$2:$Q$46,"Aprobada")>0)),O27&" ","")&IF(NOT(OR(P27="",COUNTIF($F$2:$F$46,P27)=0,COUNTIFS($F$2:$F$46,P27,$Q$2:$Q$46,"Aprobada")>0)),P27&" ","")),IF(Q27="Cursada aprobada",TRIM(IF(NOT(OR(L27="",COUNTIF($F$2:$F$46,L27)=0,COUNTIFS($F$2:$F$46,L27,$Q$2:$Q$46,"Aprobada")>0,AND(Resumen!$B$15="La cursada aprobada",COUNTIFS($F$2:$F$46,L27,$Q$2:$Q$46,"Cursada aprobada")>0))),L27&" ","")&IF(NOT(OR(M27="",COUNTIF($F$2:$F$46,M27)=0,COUNTIFS($F$2:$F$46,M27,$Q$2:$Q$46,"Aprobada")>0,AND(Resumen!$B$15="La cursada aprobada",COUNTIFS($F$2:$F$46,M27,$Q$2:$Q$46,"Cursada aprobada")>0))),M27&" ","")&IF(NOT(OR(N27="",COUNTIF($F$2:$F$46,N27)=0,COUNTIFS($F$2:$F$46,N27,$Q$2:$Q$46,"Aprobada")>0,AND(Resumen!$B$15="La cursada aprobada",COUNTIFS($F$2:$F$46,N27,$Q$2:$Q$46,"Cursada aprobada")>0))),N27&" ","")&IF(NOT(OR(O27="",COUNTIF($F$2:$F$46,O27)=0,COUNTIFS($F$2:$F$46,O27,$Q$2:$Q$46,"Aprobada")>0,AND(Resumen!$B$15="La cursada aprobada",COUNTIFS($F$2:$F$46,O27,$Q$2:$Q$46,"Cursada aprobada")>0))),O27&" ","")&IF(NOT(OR(P27="",COUNTIF($F$2:$F$46,P27)=0,COUNTIFS($F$2:$F$46,P27,$Q$2:$Q$46,"Aprobada")>0,AND(Resumen!$B$15="La cursada aprobada",COUNTIFS($F$2:$F$46,P27,$Q$2:$Q$46,"Cursada aprobada")>0))),P27&" ","")),""))
A28: Ciclo profesional | C28: 4 | D28: 2 | E28: AD | F28: 490 | G28: Elementos de Adm. de Personal | H28: I | I28: 4 | J28: 32 | L28: 308 | Q28: No cursada | R28: =IF(Q28="Aprobada","Ya aprobada",IF(Q28="Cursada aprobada","Ya cursada",IF(AND(OR(L28="",COUNTIF($F$2:$F$46,L28)=0,COUNTIFS($F$2:$F$46,L28,$Q$2:$Q$46,"Aprobada")>0,AND(Resumen!$B$15="La cursada aprobada",COUNTIFS($F$2:$F$46,L28,$Q$2:$Q$46,"Cursada aprobada")>0)),OR(M28="",COUNTIF($F$2:$F$46,M28)=0,COUNTIFS($F$2:$F$46,M28,$Q$2:$Q$46,"Aprobada")>0,AND(Resumen!$B$15="La cursada aprobada",COUNTIFS($F$2:$F$46,M28,$Q$2:$Q$46,"Cursada aprobada")>0)),OR(N28="",COUNTIF($F$2:$F$46,N28)=0,COUNTIFS($F$2:$F$46,N28,$Q$2:$Q$46,"Aprobada")>0,AND(Resumen!$B$15="La cursada aprobada",COUNTIFS($F$2:$F$46,N28,$Q$2:$Q$46,"Cursada aprobada")>0)),OR(O28="",COUNTIF($F$2:$F$46,O28)=0,COUNTIFS($F$2:$F$46,O28,$Q$2:$Q$46,"Aprobada")>0,AND(Resumen!$B$15="La cursada aprobada",COUNTIFS($F$2:$F$46,O28,$Q$2:$Q$46,"Cursada aprobada")>0)),OR(P28="",COUNTIF($F$2:$F$46,P28)=0,COUNTIFS($F$2:$F$46,P28,$Q$2:$Q$46,"Aprobada")>0,AND(Resumen!$B$15="La cursada aprobada",COUNTIFS($F$2:$F$46,P28,$Q$2:$Q$46,"Cursada aprobada")>0))),"Sí","No"))) -> No | S28: =TRIM(IF(NOT(OR(L28="",COUNTIF($F$2:$F$46,L28)=0,COUNTIFS($F$2:$F$46,L28,$Q$2:$Q$46,"Aprobada")>0,AND(Resumen!$B$15="La cursada aprobada",COUNTIFS($F$2:$F$46,L28,$Q$2:$Q$46,"Cursada aprobada")>0))),L28&" ","")&IF(NOT(OR(M28="",COUNTIF($F$2:$F$46,M28)=0,COUNTIFS($F$2:$F$46,M28,$Q$2:$Q$46,"Aprobada")>0,AND(Resumen!$B$15="La cursada aprobada",COUNTIFS($F$2:$F$46,M28,$Q$2:$Q$46,"Cursada aprobada")>0))),M28&" ","")&IF(NOT(OR(N28="",COUNTIF($F$2:$F$46,N28)=0,COUNTIFS($F$2:$F$46,N28,$Q$2:$Q$46,"Aprobada")>0,AND(Resumen!$B$15="La cursada aprobada",COUNTIFS($F$2:$F$46,N28,$Q$2:$Q$46,"Cursada aprobada")>0))),N28&" ","")&IF(NOT(OR(O28="",COUNTIF($F$2:$F$46,O28)=0,COUNTIFS($F$2:$F$46,O28,$Q$2:$Q$46,"Aprobada")>0,AND(Resumen!$B$15="La cursada aprobada",COUNTIFS($F$2:$F$46,O28,$Q$2:$Q$46,"Cursada aprobada")>0))),O28&" ","")&IF(NOT(OR(P28="",COUNTIF($F$2:$F$46,P28)=0,COUNTIFS($F$2:$F$46,P28,$Q$2:$Q$46,"Aprobada")>0,AND(Resumen!$B$15="La cursada aprobada",COUNTIFS($F$2:$F$46,P28,$Q$2:$Q$46,"Cursada aprobada")>0))),P28&" ","")) -> 308 | T28: =IF(Q28="Cursada aprobada",IF(AND(OR(L28="",COUNTIF($F$2:$F$46,L28)=0,COUNTIFS($F$2:$F$46,L28,$Q$2:$Q$46,"Aprobada")>0),OR(M28="",COUNTIF($F$2:$F$46,M28)=0,COUNTIFS($F$2:$F$46,M28,$Q$2:$Q$46,"Aprobada")>0),OR(N28="",COUNTIF($F$2:$F$46,N28)=0,COUNTIFS($F$2:$F$46,N28,$Q$2:$Q$46,"Aprobada")>0),OR(O28="",COUNTIF($F$2:$F$46,O28)=0,COUNTIFS($F$2:$F$46,O28,$Q$2:$Q$46,"Aprobada")>0),OR(P28="",COUNTIF($F$2:$F$46,P28)=0,COUNTIFS($F$2:$F$46,P28,$Q$2:$Q$46,"Aprobada")>0)),"Sí","No"),"") | U28: =IF(Q28="Aprobada",TRIM(IF(NOT(OR(L28="",COUNTIF($F$2:$F$46,L28)=0,COUNTIFS($F$2:$F$46,L28,$Q$2:$Q$46,"Aprobada")>0)),L28&" ","")&IF(NOT(OR(M28="",COUNTIF($F$2:$F$46,M28)=0,COUNTIFS($F$2:$F$46,M28,$Q$2:$Q$46,"Aprobada")>0)),M28&" ","")&IF(NOT(OR(N28="",COUNTIF($F$2:$F$46,N28)=0,COUNTIFS($F$2:$F$46,N28,$Q$2:$Q$46,"Aprobada")>0)),N28&" ","")&IF(NOT(OR(O28="",COUNTIF($F$2:$F$46,O28)=0,COUNTIFS($F$2:$F$46,O28,$Q$2:$Q$46,"Aprobada")>0)),O28&" ","")&IF(NOT(OR(P28="",COUNTIF($F$2:$F$46,P28)=0,COUNTIFS($F$2:$F$46,P28,$Q$2:$Q$46,"Aprobada")>0)),P28&" ","")),IF(Q28="Cursada aprobada",TRIM(IF(NOT(OR(L28="",COUNTIF($F$2:$F$46,L28)=0,COUNTIFS($F$2:$F$46,L28,$Q$2:$Q$46,"Aprobada")>0,AND(Resumen!$B$15="La cursada aprobada",COUNTIFS($F$2:$F$46,L28,$Q$2:$Q$46,"Cursada aprobada")>0))),L28&" ","")&IF(NOT(OR(M28="",COUNTIF($F$2:$F$46,M28)=0,COUNTIFS($F$2:$F$46,M28,$Q$2:$Q$46,"Aprobada")>0,AND(Resumen!$B$15="La cursada aprobada",COUNTIFS($F$2:$F$46,M28,$Q$2:$Q$46,"Cursada aprobada")>0))),M28&" ","")&IF(NOT(OR(N28="",COUNTIF($F$2:$F$46,N28)=0,COUNTIFS($F$2:$F$46,N28,$Q$2:$Q$46,"Aprobada")>0,AND(Resumen!$B$15="La cursada aprobada",COUNTIFS($F$2:$F$46,N28,$Q$2:$Q$46,"Cursada aprobada")>0))),N28&" ","")&IF(NOT(OR(O28="",COUNTIF($F$2:$F$46,O28)=0,COUNTIFS($F$2:$F$46,O28,$Q$2:$Q$46,"Aprobada")>0,AND(Resumen!$B$15="La cursada aprobada",COUNTIFS($F$2:$F$46,O28,$Q$2:$Q$46,"Cursada aprobada")>0))),O28&" ","")&IF(NOT(OR(P28="",COUNTIF($F$2:$F$46,P28)=0,COUNTIFS($F$2:$F$46,P28,$Q$2:$Q$46,"Aprobada")>0,AND(Resumen!$B$15="La cursada aprobada",COUNTIFS($F$2:$F$46,P28,$Q$2:$Q$46,"Cursada aprobada")>0))),P28&" ","")),""))
A29: Ciclo profesional | C29: 4 | D29: 2 | E29: AD | F29: 491 | G29: Elementos de Adm. de Comercialización | H29: I | I29: 4 | J29: 32 | L29: 308 | M29: 314 | N29: 250 | Q29: No cursada | R29: =IF(Q29="Aprobada","Ya aprobada",IF(Q29="Cursada aprobada","Ya cursada",IF(AND(OR(L29="",COUNTIF($F$2:$F$46,L29)=0,COUNTIFS($F$2:$F$46,L29,$Q$2:$Q$46,"Aprobada")>0,AND(Resumen!$B$15="La cursada aprobada",COUNTIFS($F$2:$F$46,L29,$Q$2:$Q$46,"Cursada aprobada")>0)),OR(M29="",COUNTIF($F$2:$F$46,M29)=0,COUNTIFS($F$2:$F$46,M29,$Q$2:$Q$46,"Aprobada")>0,AND(Resumen!$B$15="La cursada aprobada",COUNTIFS($F$2:$F$46,M29,$Q$2:$Q$46,"Cursada aprobada")>0)),OR(N29="",COUNTIF($F$2:$F$46,N29)=0,COUNTIFS($F$2:$F$46,N29,$Q$2:$Q$46,"Aprobada")>0,AND(Resumen!$B$15="La cursada aprobada",COUNTIFS($F$2:$F$46,N29,$Q$2:$Q$46,"Cursada aprobada")>0)),OR(O29="",COUNTIF($F$2:$F$46,O29)=0,COUNTIFS($F$2:$F$46,O29,$Q$2:$Q$46,"Aprobada")>0,AND(Resumen!$B$15="La cursada aprobada",COUNTIFS($F$2:$F$46,O29,$Q$2:$Q$46,"Cursada aprobada")>0)),OR(P29="",COUNTIF($F$2:$F$46,P29)=0,COUNTIFS($F$2:$F$46,P29,$Q$2:$Q$46,"Aprobada")>0,AND(Resumen!$B$15="La cursada aprobada",COUNTIFS($F$2:$F$46,P29,$Q$2:$Q$46,"Cursada aprobada")>0))),"Sí","No"))) -> No | S29: =TRIM(IF(NOT(OR(L29="",COUNTIF($F$2:$F$46,L29)=0,COUNTIFS($F$2:$F$46,L29,$Q$2:$Q$46,"Aprobada")>0,AND(Resumen!$B$15="La cursada aprobada",COUNTIFS($F$2:$F$46,L29,$Q$2:$Q$46,"Cursada aprobada")>0))),L29&" ","")&IF(NOT(OR(M29="",COUNTIF($F$2:$F$46,M29)=0,COUNTIFS($F$2:$F$46,M29,$Q$2:$Q$46,"Aprobada")>0,AND(Resumen!$B$15="La cursada aprobada",COUNTIFS($F$2:$F$46,M29,$Q$2:$Q$46,"Cursada aprobada")>0))),M29&" ","")&IF(NOT(OR(N29="",COUNTIF($F$2:$F$46,N29)=0,COUNTIFS($F$2:$F$46,N29,$Q$2:$Q$46,"Aprobada")>0,AND(Resumen!$B$15="La cursada aprobada",COUNTIFS($F$2:$F$46,N29,$Q$2:$Q$46,"Cursada aprobada")>0))),N29&" ","")&IF(NOT(OR(O29="",COUNTIF($F$2:$F$46,O29)=0,COUNTIFS($F$2:$F$46,O29,$Q$2:$Q$46,"Aprobada")>0,AND(Resumen!$B$15="La cursada aprobada",COUNTIFS($F$2:$F$46,O29,$Q$2:$Q$46,"Cursada aprobada")>0))),O29&" ","")&IF(NOT(OR(P29="",COUNTIF($F$2:$F$46,P29)=0,COUNTIFS($F$2:$F$46,P29,$Q$2:$Q$46,"Aprobada")>0,AND(Resumen!$B$15="La cursada aprobada",COUNTIFS($F$2:$F$46,P29,$Q$2:$Q$46,"Cursada aprobada")>0))),P29&" ","")) -> 308 314 250 | T29: =IF(Q29="Cursada aprobada",IF(AND(OR(L29="",COUNTIF($F$2:$F$46,L29)=0,COUNTIFS($F$2:$F$46,L29,$Q$2:$Q$46,"Aprobada")>0),OR(M29="",COUNTIF($F$2:$F$46,M29)=0,COUNTIFS($F$2:$F$46,M29,$Q$2:$Q$46,"Aprobada")>0),OR(N29="",COUNTIF($F$2:$F$46,N29)=0,COUNTIFS($F$2:$F$46,N29,$Q$2:$Q$46,"Aprobada")>0),OR(O29="",COUNTIF($F$2:$F$46,O29)=0,COUNTIFS($F$2:$F$46,O29,$Q$2:$Q$46,"Aprobada")>0),OR(P29="",COUNTIF($F$2:$F$46,P29)=0,COUNTIFS($F$2:$F$46,P29,$Q$2:$Q$46,"Aprobada")>0)),"Sí","No"),"") | U29: =IF(Q29="Aprobada",TRIM(IF(NOT(OR(L29="",COUNTIF($F$2:$F$46,L29)=0,COUNTIFS($F$2:$F$46,L29,$Q$2:$Q$46,"Aprobada")>0)),L29&" ","")&IF(NOT(OR(M29="",COUNTIF($F$2:$F$46,M29)=0,COUNTIFS($F$2:$F$46,M29,$Q$2:$Q$46,"Aprobada")>0)),M29&" ","")&IF(NOT(OR(N29="",COUNTIF($F$2:$F$46,N29)=0,COUNTIFS($F$2:$F$46,N29,$Q$2:$Q$46,"Aprobada")>0)),N29&" ","")&IF(NOT(OR(O29="",COUNTIF($F$2:$F$46,O29)=0,COUNTIFS($F$2:$F$46,O29,$Q$2:$Q$46,"Aprobada")>0)),O29&" ","")&IF(NOT(OR(P29="",COUNTIF($F$2:$F$46,P29)=0,COUNTIFS($F$2:$F$46,P29,$Q$2:$Q$46,"Aprobada")>0)),P29&" ","")),IF(Q29="Cursada aprobada",TRIM(IF(NOT(OR(L29="",COUNTIF($F$2:$F$46,L29)=0,COUNTIFS($F$2:$F$46,L29,$Q$2:$Q$46,"Aprobada")>0,AND(Resumen!$B$15="La cursada aprobada",COUNTIFS($F$2:$F$46,L29,$Q$2:$Q$46,"Cursada aprobada")>0))),L29&" ","")&IF(NOT(OR(M29="",COUNTIF($F$2:$F$46,M29)=0,COUNTIFS($F$2:$F$46,M29,$Q$2:$Q$46,"Aprobada")>0,AND(Resumen!$B$15="La cursada aprobada",COUNTIFS($F$2:$F$46,M29,$Q$2:$Q$46,"Cursada aprobada")>0))),M29&" ","")&IF(NOT(OR(N29="",COUNTIF($F$2:$F$46,N29)=0,COUNTIFS($F$2:$F$46,N29,$Q$2:$Q$46,"Aprobada")>0,AND(Resumen!$B$15="La cursada aprobada",COUNTIFS($F$2:$F$46,N29,$Q$2:$Q$46,"Cursada aprobada")>0))),N29&" ","")&IF(NOT(OR(O29="",COUNTIF($F$2:$F$46,O29)=0,COUNTIFS($F$2:$F$46,O29,$Q$2:$Q$46,"Aprobada")>0,AND(Resumen!$B$15="La cursada aprobada",COUNTIFS($F$2:$F$46,O29,$Q$2:$Q$46,"Cursada aprobada")>0))),O29&" ","")&IF(NOT(OR(P29="",COUNTIF($F$2:$F$46,P29)=0,COUNTIFS($F$2:$F$46,P29,$Q$2:$Q$46,"Aprobada")>0,AND(Resumen!$B$15="La cursada aprobada",COUNTIFS($F$2:$F$46,P29,$Q$2:$Q$46,"Cursada aprobada")>0))),P29&" ","")),""))
A30: Ciclo profesional | C30: 4 | D30: 2 | E30: CO | F30: 527 | G30: Auditoría | H30: I | I30: 6 | K30: 96 | L30: 402 | M30: 330 | N30: 401 | O30: 503 | Q30: No cursada | R30: =IF(Q30="Aprobada","Ya aprobada",IF(Q30="Cursada aprobada","Ya cursada",IF(AND(OR(L30="",COUNTIF($F$2:$F$46,L30)=0,COUNTIFS($F$2:$F$46,L30,$Q$2:$Q$46,"Aprobada")>0,AND(Resumen!$B$15="La cursada aprobada",COUNTIFS($F$2:$F$46,L30,$Q$2:$Q$46,"Cursada aprobada")>0)),OR(M30="",COUNTIF($F$2:$F$46,M30)=0,COUNTIFS($F$2:$F$46,M30,$Q$2:$Q$46,"Aprobada")>0,AND(Resumen!$B$15="La cursada aprobada",COUNTIFS($F$2:$F$46,M30,$Q$2:$Q$46,"Cursada aprobada")>0)),OR(N30="",COUNTIF($F$2:$F$46,N30)=0,COUNTIFS($F$2:$F$46,N30,$Q$2:$Q$46,"Aprobada")>0,AND(Resumen!$B$15="La cursada aprobada",COUNTIFS($F$2:$F$46,N30,$Q$2:$Q$46,"Cursada aprobada")>0)),OR(O30="",COUNTIF($F$2:$F$46,O30)=0,COUNTIFS($F$2:$F$46,O30,$Q$2:$Q$46,"Aprobada")>0,AND(Resumen!$B$15="La cursada aprobada",COUNTIFS($F$2:$F$46,O30,$Q$2:$Q$46,"Cursada aprobada")>0)),OR(P30="",COUNTIF($F$2:$F$46,P30)=0,COUNTIFS($F$2:$F$46,P30,$Q$2:$Q$46,"Aprobada")>0,AND(Resumen!$B$15="La cursada aprobada",COUNTIFS($F$2:$F$46,P30,$Q$2:$Q$46,"Cursada aprobada")>0))),"Sí","No"))) -> No | S30: =TRIM(IF(NOT(OR(L30="",COUNTIF($F$2:$F$46,L30)=0,COUNTIFS($F$2:$F$46,L30,$Q$2:$Q$46,"Aprobada")>0,AND(Resumen!$B$15="La cursada aprobada",COUNTIFS($F$2:$F$46,L30,$Q$2:$Q$46,"Cursada aprobada")>0))),L30&" ","")&IF(NOT(OR(M30="",COUNTIF($F$2:$F$46,M30)=0,COUNTIFS($F$2:$F$46,M30,$Q$2:$Q$46,"Aprobada")>0,AND(Resumen!$B$15="La cursada aprobada",COUNTIFS($F$2:$F$46,M30,$Q$2:$Q$46,"Cursada aprobada")>0))),M30&" ","")&IF(NOT(OR(N30="",COUNTIF($F$2:$F$46,N30)=0,COUNTIFS($F$2:$F$46,N30,$Q$2:$Q$46,"Aprobada")>0,AND(Resumen!$B$15="La cursada aprobada",COUNTIFS($F$2:$F$46,N30,$Q$2:$Q$46,"Cursada aprobada")>0))),N30&" ","")&IF(NOT(OR(O30="",COUNTIF($F$2:$F$46,O30)=0,COUNTIFS($F$2:$F$46,O30,$Q$2:$Q$46,"Aprobada")>0,AND(Resumen!$B$15="La cursada aprobada",COUNTIFS($F$2:$F$46,O30,$Q$2:$Q$46,"Cursada aprobada")>0))),O30&" ","")&IF(NOT(OR(P30="",COUNTIF($F$2:$F$46,P30)=0,COUNTIFS($F$2:$F$46,P30,$Q$2:$Q$46,"Aprobada")>0,AND(Resumen!$B$15="La cursada aprobada",COUNTIFS($F$2:$F$46,P30,$Q$2:$Q$46,"Cursada aprobada")>0))),P30&" ","")) -> 402 330 401 503 | T30: =IF(Q30="Cursada aprobada",IF(AND(OR(L30="",COUNTIF($F$2:$F$46,L30)=0,COUNTIFS($F$2:$F$46,L30,$Q$2:$Q$46,"Aprobada")>0),OR(M30="",COUNTIF($F$2:$F$46,M30)=0,COUNTIFS($F$2:$F$46,M30,$Q$2:$Q$46,"Aprobada")>0),OR(N30="",COUNTIF($F$2:$F$46,N30)=0,COUNTIFS($F$2:$F$46,N30,$Q$2:$Q$46,"Aprobada")>0),OR(O30="",COUNTIF($F$2:$F$46,O30)=0,COUNTIFS($F$2:$F$46,O30,$Q$2:$Q$46,"Aprobada")>0),OR(P30="",COUNTIF($F$2:$F$46,P30)=0,COUNTIFS($F$2:$F$46,P30,$Q$2:$Q$46,"Aprobada")>0)),"Sí","No"),"") | U30: =IF(Q30="Aprobada",TRIM(IF(NOT(OR(L30="",COUNTIF($F$2:$F$46,L30)=0,COUNTIFS($F$2:$F$46,L30,$Q$2:$Q$46,"Aprobada")>0)),L30&" ","")&IF(NOT(OR(M30="",COUNTIF($F$2:$F$46,M30)=0,COUNTIFS($F$2:$F$46,M30,$Q$2:$Q$46,"Aprobada")>0)),M30&" ","")&IF(NOT(OR(N30="",COUNTIF($F$2:$F$46,N30)=0,COUNTIFS($F$2:$F$46,N30,$Q$2:$Q$46,"Aprobada")>0)),N30&" ","")&IF(NOT(OR(O30="",COUNTIF($F$2:$F$46,O30)=0,COUNTIFS($F$2:$F$46,O30,$Q$2:$Q$46,"Aprobada")>0)),O30&" ","")&IF(NOT(OR(P30="",COUNTIF($F$2:$F$46,P30)=0,COUNTIFS($F$2:$F$46,P30,$Q$2:$Q$46,"Aprobada")>0)),P30&" ","")),IF(Q30="Cursada aprobada",TRIM(IF(NOT(OR(L30="",COUNTIF($F$2:$F$46,L30)=0,COUNTIFS($F$2:$F$46,L30,$Q$2:$Q$46,"Aprobada")>0,AND(Resumen!$B$15="La cursada aprobada",COUNTIFS($F$2:$F$46,L30,$Q$2:$Q$46,"Cursada aprobada")>0))),L30&" ","")&IF(NOT(OR(M30="",COUNTIF($F$2:$F$46,M30)=0,COUNTIFS($F$2:$F$46,M30,$Q$2:$Q$46,"Aprobada")>0,AND(Resumen!$B$15="La cursada aprobada",COUNTIFS($F$2:$F$46,M30,$Q$2:$Q$46,"Cursada aprobada")>0))),M30&" ","")&IF(NOT(OR(N30="",COUNTIF($F$2:$F$46,N30)=0,COUNTIFS($F$2:$F$46,N30,$Q$2:$Q$46,"Aprobada")>0,AND(Resumen!$B$15="La cursada aprobada",COUNTIFS($F$2:$F$46,N30,$Q$2:$Q$46,"Cursada aprobada")>0))),N30&" ","")&IF(NOT(OR(O30="",COUNTIF($F$2:$F$46,O30)=0,COUNTIFS($F$2:$F$46,O30,$Q$2:$Q$46,"Aprobada")>0,AND(Resumen!$B$15="La cursada aprobada",COUNTIFS($F$2:$F$46,O30,$Q$2:$Q$46,"Cursada aprobada")>0))),O30&" ","")&IF(NOT(OR(P30="",COUNTIF($F$2:$F$46,P30)=0,COUNTIFS($F$2:$F$46,P30,$Q$2:$Q$46,"Aprobada")>0,AND(Resumen!$B$15="La cursada aprobada",COUNTIFS($F$2:$F$46,P30,$Q$2:$Q$46,"Cursada aprobada")>0))),P30&" ","")),""))
A31: Ciclo profesional | C31: 4 | D31: 2 | E31: SA | F31: 499 | G31: Ética y Responsabilidad Social | H31: III | I31: 2 | K31: 32 | Q31: No cursada | R31: =IF(Q31="Aprobada","Ya aprobada",IF(Q31="Cursada aprobada","Ya cursada",IF(AND(OR(L31="",COUNTIF($F$2:$F$46,L31)=0,COUNTIFS($F$2:$F$46,L31,$Q$2:$Q$46,"Aprobada")>0,AND(Resumen!$B$15="La cursada aprobada",COUNTIFS($F$2:$F$46,L31,$Q$2:$Q$46,"Cursada aprobada")>0)),OR(M31="",COUNTIF($F$2:$F$46,M31)=0,COUNTIFS($F$2:$F$46,M31,$Q$2:$Q$46,"Aprobada")>0,AND(Resumen!$B$15="La cursada aprobada",COUNTIFS($F$2:$F$46,M31,$Q$2:$Q$46,"Cursada aprobada")>0)),OR(N31="",COUNTIF($F$2:$F$46,N31)=0,COUNTIFS($F$2:$F$46,N31,$Q$2:$Q$46,"Aprobada")>0,AND(Resumen!$B$15="La cursada aprobada",COUNTIFS($F$2:$F$46,N31,$Q$2:$Q$46,"Cursada aprobada")>0)),OR(O31="",COUNTIF($F$2:$F$46,O31)=0,COUNTIFS($F$2:$F$46,O31,$Q$2:$Q$46,"Aprobada")>0,AND(Resumen!$B$15="La cursada aprobada",COUNTIFS($F$2:$F$46,O31,$Q$2:$Q$46,"Cursada aprobada")>0)),OR(P31="",COUNTIF($F$2:$F$46,P31)=0,COUNTIFS($F$2:$F$46,P31,$Q$2:$Q$46,"Aprobada")>0,AND(Resumen!$B$15="La cursada aprobada",COUNTIFS($F$2:$F$46,P31,$Q$2:$Q$46,"Cursada aprobada")>0))),"Sí","No"))) -> Sí | S31: =TRIM(IF(NOT(OR(L31="",COUNTIF($F$2:$F$46,L31)=0,COUNTIFS($F$2:$F$46,L31,$Q$2:$Q$46,"Aprobada")>0,AND(Resumen!$B$15="La cursada aprobada",COUNTIFS($F$2:$F$46,L31,$Q$2:$Q$46,"Cursada aprobada")>0))),L31&" ","")&IF(NOT(OR(M31="",COUNTIF($F$2:$F$46,M31)=0,COUNTIFS($F$2:$F$46,M31,$Q$2:$Q$46,"Aprobada")>0,AND(Resumen!$B$15="La cursada aprobada",COUNTIFS($F$2:$F$46,M31,$Q$2:$Q$46,"Cursada aprobada")>0))),M31&" ","")&IF(NOT(OR(N31="",COUNTIF($F$2:$F$46,N31)=0,COUNTIFS($F$2:$F$46,N31,$Q$2:$Q$46,"Aprobada")>0,AND(Resumen!$B$15="La cursada aprobada",COUNTIFS($F$2:$F$46,N31,$Q$2:$Q$46,"Cursada aprobada")>0))),N31&" ","")&IF(NOT(OR(O31="",COUNTIF($F$2:$F$46,O31)=0,COUNTIFS($F$2:$F$46,O31,$Q$2:$Q$46,"Aprobada")>0,AND(Resumen!$B$15="La cursada aprobada",COUNTIFS($F$2:$F$46,O31,$Q$2:$Q$46,"Cursada aprobada")>0))),O31&" ","")&IF(NOT(OR(P31="",COUNTIF($F$2:$F$46,P31)=0,COUNTIFS($F$2:$F$46,P31,$Q$2:$Q$46,"Aprobada")>0,AND(Resumen!$B$15="La cursada aprobada",COUNTIFS($F$2:$F$46,P31,$Q$2:$Q$46,"Cursada aprobada")>0))),P31&" ","")) | T31: =IF(Q31="Cursada aprobada",IF(AND(OR(L31="",COUNTIF($F$2:$F$46,L31)=0,COUNTIFS($F$2:$F$46,L31,$Q$2:$Q$46,"Aprobada")>0),OR(M31="",COUNTIF($F$2:$F$46,M31)=0,COUNTIFS($F$2:$F$46,M31,$Q$2:$Q$46,"Aprobada")>0),OR(N31="",COUNTIF($F$2:$F$46,N31)=0,COUNTIFS($F$2:$F$46,N31,$Q$2:$Q$46,"Aprobada")>0),OR(O31="",COUNTIF($F$2:$F$46,O31)=0,COUNTIFS($F$2:$F$46,O31,$Q$2:$Q$46,"Aprobada")>0),OR(P31="",COUNTIF($F$2:$F$46,P31)=0,COUNTIFS($F$2:$F$46,P31,$Q$2:$Q$46,"Aprobada")>0)),"Sí","No"),"") | U31: =IF(Q31="Aprobada",TRIM(IF(NOT(OR(L31="",COUNTIF($F$2:$F$46,L31)=0,COUNTIFS($F$2:$F$46,L31,$Q$2:$Q$46,"Aprobada")>0)),L31&" ","")&IF(NOT(OR(M31="",COUNTIF($F$2:$F$46,M31)=0,COUNTIFS($F$2:$F$46,M31,$Q$2:$Q$46,"Aprobada")>0)),M31&" ","")&IF(NOT(OR(N31="",COUNTIF($F$2:$F$46,N31)=0,COUNTIFS($F$2:$F$46,N31,$Q$2:$Q$46,"Aprobada")>0)),N31&" ","")&IF(NOT(OR(O31="",COUNTIF($F$2:$F$46,O31)=0,COUNTIFS($F$2:$F$46,O31,$Q$2:$Q$46,"Aprobada")>0)),O31&" ","")&IF(NOT(OR(P31="",COUNTIF($F$2:$F$46,P31)=0,COUNTIFS($F$2:$F$46,P31,$Q$2:$Q$46,"Aprobada")>0)),P31&" ","")),IF(Q31="Cursada aprobada",TRIM(IF(NOT(OR(L31="",COUNTIF($F$2:$F$46,L31)=0,COUNTIFS($F$2:$F$46,L31,$Q$2:$Q$46,"Aprobada")>0,AND(Resumen!$B$15="La cursada aprobada",COUNTIFS($F$2:$F$46,L31,$Q$2:$Q$46,"Cursada aprobada")>0))),L31&" ","")&IF(NOT(OR(M31="",COUNTIF($F$2:$F$46,M31)=0,COUNTIFS($F$2:$F$46,M31,$Q$2:$Q$46,"Aprobada")>0,AND(Resumen!$B$15="La cursada aprobada",COUNTIFS($F$2:$F$46,M31,$Q$2:$Q$46,"Cursada aprobada")>0))),M31&" ","")&IF(NOT(OR(N31="",COUNTIF($F$2:$F$46,N31)=0,COUNTIFS($F$2:$F$46,N31,$Q$2:$Q$46,"Aprobada")>0,AND(Resumen!$B$15="La cursada aprobada",COUNTIFS($F$2:$F$46,N31,$Q$2:$Q$46,"Cursada aprobada")>0))),N31&" ","")&IF(NOT(OR(O31="",COUNTIF($F$2:$F$46,O31)=0,COUNTIFS($F$2:$F$46,O31,$Q$2:$Q$46,"Aprobada")>0,AND(Resumen!$B$15="La cursada aprobada",COUNTIFS($F$2:$F$46,O31,$Q$2:$Q$46,"Cursada aprobada")>0))),O31&" ","")&IF(NOT(OR(P31="",COUNTIF($F$2:$F$46,P31)=0,COUNTIFS($F$2:$F$46,P31,$Q$2:$Q$46,"Aprobada")>0,AND(Resumen!$B$15="La cursada aprobada",COUNTIFS($F$2:$F$46,P31,$Q$2:$Q$46,"Cursada aprobada")>0))),P31&" ","")),""))
A32: Ciclo profesional | C32: 5 | D32: 1 | E32: CO | F32: 525 | G32: Impuestos II | H32: I | I32: 6 | K32: 96 | L32: 460 | Q32: No cursada | R32: =IF(Q32="Aprobada","Ya aprobada",IF(Q32="Cursada aprobada","Ya cursada",IF(AND(OR(L32="",COUNTIF($F$2:$F$46,L32)=0,COUNTIFS($F$2:$F$46,L32,$Q$2:$Q$46,"Aprobada")>0,AND(Resumen!$B$15="La cursada aprobada",COUNTIFS($F$2:$F$46,L32,$Q$2:$Q$46,"Cursada aprobada")>0)),OR(M32="",COUNTIF($F$2:$F$46,M32)=0,COUNTIFS($F$2:$F$46,M32,$Q$2:$Q$46,"Aprobada")>0,AND(Resumen!$B$15="La cursada aprobada",COUNTIFS($F$2:$F$46,M32,$Q$2:$Q$46,"Cursada aprobada")>0)),OR(N32="",COUNTIF($F$2:$F$46,N32)=0,COUNTIFS($F$2:$F$46,N32,$Q$2:$Q$46,"Aprobada")>0,AND(Resumen!$B$15="La cursada aprobada",COUNTIFS($F$2:$F$46,N32,$Q$2:$Q$46,"Cursada aprobada")>0)),OR(O32="",COUNTIF($F$2:$F$46,O32)=0,COUNTIFS($F$2:$F$46,O32,$Q$2:$Q$46,"Aprobada")>0,AND(Resumen!$B$15="La cursada aprobada",COUNTIFS($F$2:$F$46,O32,$Q$2:$Q$46,"Cursada aprobada")>0)),OR(P32="",COUNTIF($F$2:$F$46,P32)=0,COUNTIFS($F$2:$F$46,P32,$Q$2:$Q$46,"Aprobada")>0,AND(Resumen!$B$15="La cursada aprobada",COUNTIFS($F$2:$F$46,P32,$Q$2:$Q$46,"Cursada aprobada")>0))),"Sí","No"))) -> No | S32: =TRIM(IF(NOT(OR(L32="",COUNTIF($F$2:$F$46,L32)=0,COUNTIFS($F$2:$F$46,L32,$Q$2:$Q$46,"Aprobada")>0,AND(Resumen!$B$15="La cursada aprobada",COUNTIFS($F$2:$F$46,L32,$Q$2:$Q$46,"Cursada aprobada")>0))),L32&" ","")&IF(NOT(OR(M32="",COUNTIF($F$2:$F$46,M32)=0,COUNTIFS($F$2:$F$46,M32,$Q$2:$Q$46,"Aprobada")>0,AND(Resumen!$B$15="La cursada aprobada",COUNTIFS($F$2:$F$46,M32,$Q$2:$Q$46,"Cursada aprobada")>0))),M32&" ","")&IF(NOT(OR(N32="",COUNTIF($F$2:$F$46,N32)=0,COUNTIFS($F$2:$F$46,N32,$Q$2:$Q$46,"Aprobada")>0,AND(Resumen!$B$15="La cursada aprobada",COUNTIFS($F$2:$F$46,N32,$Q$2:$Q$46,"Cursada aprobada")>0))),N32&" ","")&IF(NOT(OR(O32="",COUNTIF($F$2:$F$46,O32)=0,COUNTIFS($F$2:$F$46,O32,$Q$2:$Q$46,"Aprobada")>0,AND(Resumen!$B$15="La cursada aprobada",COUNTIFS($F$2:$F$46,O32,$Q$2:$Q$46,"Cursada aprobada")>0))),O32&" ","")&IF(NOT(OR(P32="",COUNTIF($F$2:$F$46,P32)=0,COUNTIFS($F$2:$F$46,P32,$Q$2:$Q$46,"Aprobada")>0,AND(Resumen!$B$15="La cursada aprobada",COUNTIFS($F$2:$F$46,P32,$Q$2:$Q$46,"Cursada aprobada")>0))),P32&" ","")) -> 460 | T32: =IF(Q32="Cursada aprobada",IF(AND(OR(L32="",COUNTIF($F$2:$F$46,L32)=0,COUNTIFS($F$2:$F$46,L32,$Q$2:$Q$46,"Aprobada")>0),OR(M32="",COUNTIF($F$2:$F$46,M32)=0,COUNTIFS($F$2:$F$46,M32,$Q$2:$Q$46,"Aprobada")>0),OR(N32="",COUNTIF($F$2:$F$46,N32)=0,COUNTIFS($F$2:$F$46,N32,$Q$2:$Q$46,"Aprobada")>0),OR(O32="",COUNTIF($F$2:$F$46,O32)=0,COUNTIFS($F$2:$F$46,O32,$Q$2:$Q$46,"Aprobada")>0),OR(P32="",COUNTIF($F$2:$F$46,P32)=0,COUNTIFS($F$2:$F$46,P32,$Q$2:$Q$46,"Aprobada")>0)),"Sí","No"),"") | U32: =IF(Q32="Aprobada",TRIM(IF(NOT(OR(L32="",COUNTIF($F$2:$F$46,L32)=0,COUNTIFS($F$2:$F$46,L32,$Q$2:$Q$46,"Aprobada")>0)),L32&" ","")&IF(NOT(OR(M32="",COUNTIF($F$2:$F$46,M32)=0,COUNTIFS($F$2:$F$46,M32,$Q$2:$Q$46,"Aprobada")>0)),M32&" ","")&IF(NOT(OR(N32="",COUNTIF($F$2:$F$46,N32)=0,COUNTIFS($F$2:$F$46,N32,$Q$2:$Q$46,"Aprobada")>0)),N32&" ","")&IF(NOT(OR(O32="",COUNTIF($F$2:$F$46,O32)=0,COUNTIFS($F$2:$F$46,O32,$Q$2:$Q$46,"Aprobada")>0)),O32&" ","")&IF(NOT(OR(P32="",COUNTIF($F$2:$F$46,P32)=0,COUNTIFS($F$2:$F$46,P32,$Q$2:$Q$46,"Aprobada")>0)),P32&" ","")),IF(Q32="Cursada aprobada",TRIM(IF(NOT(OR(L32="",COUNTIF($F$2:$F$46,L32)=0,COUNTIFS($F$2:$F$46,L32,$Q$2:$Q$46,"Aprobada")>0,AND(Resumen!$B$15="La cursada aprobada",COUNTIFS($F$2:$F$46,L32,$Q$2:$Q$46,"Cursada aprobada")>0))),L32&" ","")&IF(NOT(OR(M32="",COUNTIF($F$2:$F$46,M32)=0,COUNTIFS($F$2:$F$46,M32,$Q$2:$Q$46,"Aprobada")>0,AND(Resumen!$B$15="La cursada aprobada",COUNTIFS($F$2:$F$46,M32,$Q$2:$Q$46,"Cursada aprobada")>0))),M32&" ","")&IF(NOT(OR(N32="",COUNTIF($F$2:$F$46,N32)=0,COUNTIFS($F$2:$F$46,N32,$Q$2:$Q$46,"Aprobada")>0,AND(Resumen!$B$15="La cursada aprobada",COUNTIFS($F$2:$F$46,N32,$Q$2:$Q$46,"Cursada aprobada")>0))),N32&" ","")&IF(NOT(OR(O32="",COUNTIF($F$2:$F$46,O32)=0,COUNTIFS($F$2:$F$46,O32,$Q$2:$Q$46,"Aprobada")>0,AND(Resumen!$B$15="La cursada aprobada",COUNTIFS($F$2:$F$46,O32,$Q$2:$Q$46,"Cursada aprobada")>0))),O32&" ","")&IF(NOT(OR(P32="",COUNTIF($F$2:$F$46,P32)=0,COUNTIFS($F$2:$F$46,P32,$Q$2:$Q$46,"Aprobada")>0,AND(Resumen!$B$15="La cursada aprobada",COUNTIFS($F$2:$F$46,P32,$Q$2:$Q$46,"Cursada aprobada")>0))),P32&" ","")),""))
A33: Ciclo profesional | C33: 5 | D33: 1 | E33: AD | F33: 602 | G33: Información para Control Gerencial | H33: I | I33: 6 | K33: 96 | L33: 330 | M33: 430 | Q33: No cursada | R33: =IF(Q33="Aprobada","Ya aprobada",IF(Q33="Cursada aprobada","Ya cursada",IF(AND(OR(L33="",COUNTIF($F$2:$F$46,L33)=0,COUNTIFS($F$2:$F$46,L33,$Q$2:$Q$46,"Aprobada")>0,AND(Resumen!$B$15="La cursada aprobada",COUNTIFS($F$2:$F$46,L33,$Q$2:$Q$46,"Cursada aprobada")>0)),OR(M33="",COUNTIF($F$2:$F$46,M33)=0,COUNTIFS($F$2:$F$46,M33,$Q$2:$Q$46,"Aprobada")>0,AND(Resumen!$B$15="La cursada aprobada",COUNTIFS($F$2:$F$46,M33,$Q$2:$Q$46,"Cursada aprobada")>0)),OR(N33="",COUNTIF($F$2:$F$46,N33)=0,COUNTIFS($F$2:$F$46,N33,$Q$2:$Q$46,"Aprobada")>0,AND(Resumen!$B$15="La cursada aprobada",COUNTIFS($F$2:$F$46,N33,$Q$2:$Q$46,"Cursada aprobada")>0)),OR(O33="",COUNTIF($F$2:$F$46,O33)=0,COUNTIFS($F$2:$F$46,O33,$Q$2:$Q$46,"Aprobada")>0,AND(Resumen!$B$15="La cursada aprobada",COUNTIFS($F$2:$F$46,O33,$Q$2:$Q$46,"Cursada aprobada")>0)),OR(P33="",COUNTIF($F$2:$F$46,P33)=0,COUNTIFS($F$2:$F$46,P33,$Q$2:$Q$46,"Aprobada")>0,AND(Resumen!$B$15="La cursada aprobada",COUNTIFS($F$2:$F$46,P33,$Q$2:$Q$46,"Cursada aprobada")>0))),"Sí","No"))) -> No | S33: =TRIM(IF(NOT(OR(L33="",COUNTIF($F$2:$F$46,L33)=0,COUNTIFS($F$2:$F$46,L33,$Q$2:$Q$46,"Aprobada")>0,AND(Resumen!$B$15="La cursada aprobada",COUNTIFS($F$2:$F$46,L33,$Q$2:$Q$46,"Cursada aprobada")>0))),L33&" ","")&IF(NOT(OR(M33="",COUNTIF($F$2:$F$46,M33)=0,COUNTIFS($F$2:$F$46,M33,$Q$2:$Q$46,"Aprobada")>0,AND(Resumen!$B$15="La cursada aprobada",COUNTIFS($F$2:$F$46,M33,$Q$2:$Q$46,"Cursada aprobada")>0))),M33&" ","")&IF(NOT(OR(N33="",COUNTIF($F$2:$F$46,N33)=0,COUNTIFS($F$2:$F$46,N33,$Q$2:$Q$46,"Aprobada")>0,AND(Resumen!$B$15="La cursada aprobada",COUNTIFS($F$2:$F$46,N33,$Q$2:$Q$46,"Cursada aprobada")>0))),N33&" ","")&IF(NOT(OR(O33="",COUNTIF($F$2:$F$46,O33)=0,COUNTIFS($F$2:$F$46,O33,$Q$2:$Q$46,"Aprobada")>0,AND(Resumen!$B$15="La cursada aprobada",COUNTIFS($F$2:$F$46,O33,$Q$2:$Q$46,"Cursada aprobada")>0))),O33&" ","")&IF(NOT(OR(P33="",COUNTIF($F$2:$F$46,P33)=0,COUNTIFS($F$2:$F$46,P33,$Q$2:$Q$46,"Aprobada")>0,AND(Resumen!$B$15="La cursada aprobada",COUNTIFS($F$2:$F$46,P33,$Q$2:$Q$46,"Cursada aprobada")>0))),P33&" ","")) -> 330 430 | T33: =IF(Q33="Cursada aprobada",IF(AND(OR(L33="",COUNTIF($F$2:$F$46,L33)=0,COUNTIFS($F$2:$F$46,L33,$Q$2:$Q$46,"Aprobada")>0),OR(M33="",COUNTIF($F$2:$F$46,M33)=0,COUNTIFS($F$2:$F$46,M33,$Q$2:$Q$46,"Aprobada")>0),OR(N33="",COUNTIF($F$2:$F$46,N33)=0,COUNTIFS($F$2:$F$46,N33,$Q$2:$Q$46,"Aprobada")>0),OR(O33="",COUNTIF($F$2:$F$46,O33)=0,COUNTIFS($F$2:$F$46,O33,$Q$2:$Q$46,"Aprobada")>0),OR(P33="",COUNTIF($F$2:$F$46,P33)=0,COUNTIFS($F$2:$F$46,P33,$Q$2:$Q$46,"Aprobada")>0)),"Sí","No"),"") | U33: =IF(Q33="Aprobada",TRIM(IF(NOT(OR(L33="",COUNTIF($F$2:$F$46,L33)=0,COUNTIFS($F$2:$F$46,L33,$Q$2:$Q$46,"Aprobada")>0)),L33&" ","")&IF(NOT(OR(M33="",COUNTIF($F$2:$F$46,M33)=0,COUNTIFS($F$2:$F$46,M33,$Q$2:$Q$46,"Aprobada")>0)),M33&" ","")&IF(NOT(OR(N33="",COUNTIF($F$2:$F$46,N33)=0,COUNTIFS($F$2:$F$46,N33,$Q$2:$Q$46,"Aprobada")>0)),N33&" ","")&IF(NOT(OR(O33="",COUNTIF($F$2:$F$46,O33)=0,COUNTIFS($F$2:$F$46,O33,$Q$2:$Q$46,"Aprobada")>0)),O33&" ","")&IF(NOT(OR(P33="",COUNTIF($F$2:$F$46,P33)=0,COUNTIFS($F$2:$F$46,P33,$Q$2:$Q$46,"Aprobada")>0)),P33&" ","")),IF(Q33="Cursada aprobada",TRIM(IF(NOT(OR(L33="",COUNTIF($F$2:$F$46,L33)=0,COUNTIFS($F$2:$F$46,L33,$Q$2:$Q$46,"Aprobada")>0,AND(Resumen!$B$15="La cursada aprobada",COUNTIFS($F$2:$F$46,L33,$Q$2:$Q$46,"Cursada aprobada")>0))),L33&" ","")&IF(NOT(OR(M33="",COUNTIF($F$2:$F$46,M33)=0,COUNTIFS($F$2:$F$46,M33,$Q$2:$Q$46,"Aprobada")>0,AND(Resumen!$B$15="La cursada aprobada",COUNTIFS($F$2:$F$46,M33,$Q$2:$Q$46,"Cursada aprobada")>0))),M33&" ","")&IF(NOT(OR(N33="",COUNTIF($F$2:$F$46,N33)=0,COUNTIFS($F$2:$F$46,N33,$Q$2:$Q$46,"Aprobada")>0,AND(Resumen!$B$15="La cursada aprobada",COUNTIFS($F$2:$F$46,N33,$Q$2:$Q$46,"Cursada aprobada")>0))),N33&" ","")&IF(NOT(OR(O33="",COUNTIF($F$2:$F$46,O33)=0,COUNTIFS($F$2:$F$46,O33,$Q$2:$Q$46,"Aprobada")>0,AND(Resumen!$B$15="La cursada aprobada",COUNTIFS($F$2:$F$46,O33,$Q$2:$Q$46,"Cursada aprobada")>0))),O33&" ","")&IF(NOT(OR(P33="",COUNTIF($F$2:$F$46,P33)=0,COUNTIFS($F$2:$F$46,P33,$Q$2:$Q$46,"Aprobada")>0,AND(Resumen!$B$15="La cursada aprobada",COUNTIFS($F$2:$F$46,P33,$Q$2:$Q$46,"Cursada aprobada")>0))),P33&" ","")),""))
A34: Ciclo profesional | C34: 5 | D34: 1 | E34: JU | F34: 590 | G34: Empresas en Crisis. Títulos de Créd. | H34: II | I34: 4 | K34: 64 | L34: 503 | M34: 430 | N34: 425 | O34: 527 | Q34: No cursada | R34: =IF(Q34="Aprobada","Ya aprobada",IF(Q34="Cursada aprobada","Ya cursada",IF(AND(OR(L34="",COUNTIF($F$2:$F$46,L34)=0,COUNTIFS($F$2:$F$46,L34,$Q$2:$Q$46,"Aprobada")>0,AND(Resumen!$B$15="La cursada aprobada",COUNTIFS($F$2:$F$46,L34,$Q$2:$Q$46,"Cursada aprobada")>0)),OR(M34="",COUNTIF($F$2:$F$46,M34)=0,COUNTIFS($F$2:$F$46,M34,$Q$2:$Q$46,"Aprobada")>0,AND(Resumen!$B$15="La cursada aprobada",COUNTIFS($F$2:$F$46,M34,$Q$2:$Q$46,"Cursada aprobada")>0)),OR(N34="",COUNTIF($F$2:$F$46,N34)=0,COUNTIFS($F$2:$F$46,N34,$Q$2:$Q$46,"Aprobada")>0,AND(Resumen!$B$15="La cursada aprobada",COUNTIFS($F$2:$F$46,N34,$Q$2:$Q$46,"Cursada aprobada")>0)),OR(O34="",COUNTIF($F$2:$F$46,O34)=0,COUNTIFS($F$2:$F$46,O34,$Q$2:$Q$46,"Aprobada")>0,AND(Resumen!$B$15="La cursada aprobada",COUNTIFS($F$2:$F$46,O34,$Q$2:$Q$46,"Cursada aprobada")>0)),OR(P34="",COUNTIF($F$2:$F$46,P34)=0,COUNTIFS($F$2:$F$46,P34,$Q$2:$Q$46,"Aprobada")>0,AND(Resumen!$B$15="La cursada aprobada",COUNTIFS($F$2:$F$46,P34,$Q$2:$Q$46,"Cursada aprobada")>0))),"Sí","No"))) -> No | S34: =TRIM(IF(NOT(OR(L34="",COUNTIF($F$2:$F$46,L34)=0,COUNTIFS($F$2:$F$46,L34,$Q$2:$Q$46,"Aprobada")>0,AND(Resumen!$B$15="La cursada aprobada",COUNTIFS($F$2:$F$46,L34,$Q$2:$Q$46,"Cursada aprobada")>0))),L34&" ","")&IF(NOT(OR(M34="",COUNTIF($F$2:$F$46,M34)=0,COUNTIFS($F$2:$F$46,M34,$Q$2:$Q$46,"Aprobada")>0,AND(Resumen!$B$15="La cursada aprobada",COUNTIFS($F$2:$F$46,M34,$Q$2:$Q$46,"Cursada aprobada")>0))),M34&" ","")&IF(NOT(OR(N34="",COUNTIF($F$2:$F$46,N34)=0,COUNTIFS($F$2:$F$46,N34,$Q$2:$Q$46,"Aprobada")>0,AND(Resumen!$B$15="La cursada aprobada",COUNTIFS($F$2:$F$46,N34,$Q$2:$Q$46,"Cursada aprobada")>0))),N34&" ","")&IF(NOT(OR(O34="",COUNTIF($F$2:$F$46,O34)=0,COUNTIFS($F$2:$F$46,O34,$Q$2:$Q$46,"Aprobada")>0,AND(Resumen!$B$15="La cursada aprobada",COUNTIFS($F$2:$F$46,O34,$Q$2:$Q$46,"Cursada aprobada")>0))),O34&" ","")&IF(NOT(OR(P34="",COUNTIF($F$2:$F$46,P34)=0,COUNTIFS($F$2:$F$46,P34,$Q$2:$Q$46,"Aprobada")>0,AND(Resumen!$B$15="La cursada aprobada",COUNTIFS($F$2:$F$46,P34,$Q$2:$Q$46,"Cursada aprobada")>0))),P34&" ","")) -> 503 430 425 527 | T34: =IF(Q34="Cursada aprobada",IF(AND(OR(L34="",COUNTIF($F$2:$F$46,L34)=0,COUNTIFS($F$2:$F$46,L34,$Q$2:$Q$46,"Aprobada")>0),OR(M34="",COUNTIF($F$2:$F$46,M34)=0,COUNTIFS($F$2:$F$46,M34,$Q$2:$Q$46,"Aprobada")>0),OR(N34="",COUNTIF($F$2:$F$46,N34)=0,COUNTIFS($F$2:$F$46,N34,$Q$2:$Q$46,"Aprobada")>0),OR(O34="",COUNTIF($F$2:$F$46,O34)=0,COUNTIFS($F$2:$F$46,O34,$Q$2:$Q$46,"Aprobada")>0),OR(P34="",COUNTIF($F$2:$F$46,P34)=0,COUNTIFS($F$2:$F$46,P34,$Q$2:$Q$46,"Aprobada")>0)),"Sí","No"),"") | U34: =IF(Q34="Aprobada",TRIM(IF(NOT(OR(L34="",COUNTIF($F$2:$F$46,L34)=0,COUNTIFS($F$2:$F$46,L34,$Q$2:$Q$46,"Aprobada")>0)),L34&" ","")&IF(NOT(OR(M34="",COUNTIF($F$2:$F$46,M34)=0,COUNTIFS($F$2:$F$46,M34,$Q$2:$Q$46,"Aprobada")>0)),M34&" ","")&IF(NOT(OR(N34="",COUNTIF($F$2:$F$46,N34)=0,COUNTIFS($F$2:$F$46,N34,$Q$2:$Q$46,"Aprobada")>0)),N34&" ","")&IF(NOT(OR(O34="",COUNTIF($F$2:$F$46,O34)=0,COUNTIFS($F$2:$F$46,O34,$Q$2:$Q$46,"Aprobada")>0)),O34&" ","")&IF(NOT(OR(P34="",COUNTIF($F$2:$F$46,P34)=0,COUNTIFS($F$2:$F$46,P34,$Q$2:$Q$46,"Aprobada")>0)),P34&" ","")),IF(Q34="Cursada aprobada",TRIM(IF(NOT(OR(L34="",COUNTIF($F$2:$F$46,L34)=0,COUNTIFS($F$2:$F$46,L34,$Q$2:$Q$46,"Aprobada")>0,AND(Resumen!$B$15="La cursada aprobada",COUNTIFS($F$2:$F$46,L34,$Q$2:$Q$46,"Cursada aprobada")>0))),L34&" ","")&IF(NOT(OR(M34="",COUNTIF($F$2:$F$46,M34)=0,COUNTIFS($F$2:$F$46,M34,$Q$2:$Q$46,"Aprobada")>0,AND(Resumen!$B$15="La cursada aprobada",COUNTIFS($F$2:$F$46,M34,$Q$2:$Q$46,"Cursada aprobada")>0))),M34&" ","")&IF(NOT(OR(N34="",COUNTIF($F$2:$F$46,N34)=0,COUNTIFS($F$2:$F$46,N34,$Q$2:$Q$46,"Aprobada")>0,AND(Resumen!$B$15="La cursada aprobada",COUNTIFS($F$2:$F$46,N34,$Q$2:$Q$46,"Cursada aprobada")>0))),N34&" ","")&IF(NOT(OR(O34="",COUNTIF($F$2:$F$46,O34)=0,COUNTIFS($F$2:$F$46,O34,$Q$2:$Q$46,"Aprobada")>0,AND(Resumen!$B$15="La cursada aprobada",COUNTIFS($F$2:$F$46,O34,$Q$2:$Q$46,"Cursada aprobada")>0))),O34&" ","")&IF(NOT(OR(P34="",COUNTIF($F$2:$F$46,P34)=0,COUNTIFS($F$2:$F$46,P34,$Q$2:$Q$46,"Aprobada")>0,AND(Resumen!$B$15="La cursada aprobada",COUNTIFS($F$2:$F$46,P34,$Q$2:$Q$46,"Cursada aprobada")>0))),P34&" ","")),""))
A35: Ciclo profesional | C35: 5 | D35: 2 | E35: CO | F35: 805 | G35: Práctica Profesional | H35: III | I35: 6 | K35: 100 | L35: 527 | M35: 590 | N35: 525 | Q35: No cursada | R35: =IF(Q35="Aprobada","Ya aprobada",IF(Q35="Cursada aprobada","Ya cursada",IF(AND(OR(L35="",COUNTIF($F$2:$F$46,L35)=0,COUNTIFS($F$2:$F$46,L35,$Q$2:$Q$46,"Aprobada")>0,AND(Resumen!$B$15="La cursada aprobada",COUNTIFS($F$2:$F$46,L35,$Q$2:$Q$46,"Cursada aprobada")>0)),OR(M35="",COUNTIF($F$2:$F$46,M35)=0,COUNTIFS($F$2:$F$46,M35,$Q$2:$Q$46,"Aprobada")>0,AND(Resumen!$B$15="La cursada aprobada",COUNTIFS($F$2:$F$46,M35,$Q$2:$Q$46,"Cursada aprobada")>0)),OR(N35="",COUNTIF($F$2:$F$46,N35)=0,COUNTIFS($F$2:$F$46,N35,$Q$2:$Q$46,"Aprobada")>0,AND(Resumen!$B$15="La cursada aprobada",COUNTIFS($F$2:$F$46,N35,$Q$2:$Q$46,"Cursada aprobada")>0)),OR(O35="",COUNTIF($F$2:$F$46,O35)=0,COUNTIFS($F$2:$F$46,O35,$Q$2:$Q$46,"Aprobada")>0,AND(Resumen!$B$15="La cursada aprobada",COUNTIFS($F$2:$F$46,O35,$Q$2:$Q$46,"Cursada aprobada")>0)),OR(P35="",COUNTIF($F$2:$F$46,P35)=0,COUNTIFS($F$2:$F$46,P35,$Q$2:$Q$46,"Aprobada")>0,AND(Resumen!$B$15="La cursada aprobada",COUNTIFS($F$2:$F$46,P35,$Q$2:$Q$46,"Cursada aprobada")>0))),"Sí","No"))) -> No | S35: =TRIM(IF(NOT(OR(L35="",COUNTIF($F$2:$F$46,L35)=0,COUNTIFS($F$2:$F$46,L35,$Q$2:$Q$46,"Aprobada")>0,AND(Resumen!$B$15="La cursada aprobada",COUNTIFS($F$2:$F$46,L35,$Q$2:$Q$46,"Cursada aprobada")>0))),L35&" ","")&IF(NOT(OR(M35="",COUNTIF($F$2:$F$46,M35)=0,COUNTIFS($F$2:$F$46,M35,$Q$2:$Q$46,"Aprobada")>0,AND(Resumen!$B$15="La cursada aprobada",COUNTIFS($F$2:$F$46,M35,$Q$2:$Q$46,"Cursada aprobada")>0))),M35&" ","")&IF(NOT(OR(N35="",COUNTIF($F$2:$F$46,N35)=0,COUNTIFS($F$2:$F$46,N35,$Q$2:$Q$46,"Aprobada")>0,AND(Resumen!$B$15="La cursada aprobada",COUNTIFS($F$2:$F$46,N35,$Q$2:$Q$46,"Cursada aprobada")>0))),N35&" ","")&IF(NOT(OR(O35="",COUNTIF($F$2:$F$46,O35)=0,COUNTIFS($F$2:$F$46,O35,$Q$2:$Q$46,"Aprobada")>0,AND(Resumen!$B$15="La cursada aprobada",COUNTIFS($F$2:$F$46,O35,$Q$2:$Q$46,"Cursada aprobada")>0))),O35&" ","")&IF(NOT(OR(P35="",COUNTIF($F$2:$F$46,P35)=0,COUNTIFS($F$2:$F$46,P35,$Q$2:$Q$46,"Aprobada")>0,AND(Resumen!$B$15="La cursada aprobada",COUNTIFS($F$2:$F$46,P35,$Q$2:$Q$46,"Cursada aprobada")>0))),P35&" ","")) -> 527 590 525 | T35: =IF(Q35="Cursada aprobada",IF(AND(OR(L35="",COUNTIF($F$2:$F$46,L35)=0,COUNTIFS($F$2:$F$46,L35,$Q$2:$Q$46,"Aprobada")>0),OR(M35="",COUNTIF($F$2:$F$46,M35)=0,COUNTIFS($F$2:$F$46,M35,$Q$2:$Q$46,"Aprobada")>0),OR(N35="",COUNTIF($F$2:$F$46,N35)=0,COUNTIFS($F$2:$F$46,N35,$Q$2:$Q$46,"Aprobada")>0),OR(O35="",COUNTIF($F$2:$F$46,O35)=0,COUNTIFS($F$2:$F$46,O35,$Q$2:$Q$46,"Aprobada")>0),OR(P35="",COUNTIF($F$2:$F$46,P35)=0,COUNTIFS($F$2:$F$46,P35,$Q$2:$Q$46,"Aprobada")>0)),"Sí","No"),"") | U35: =IF(Q35="Aprobada",TRIM(IF(NOT(OR(L35="",COUNTIF($F$2:$F$46,L35)=0,COUNTIFS($F$2:$F$46,L35,$Q$2:$Q$46,"Aprobada")>0)),L35&" ","")&IF(NOT(OR(M35="",COUNTIF($F$2:$F$46,M35)=0,COUNTIFS($F$2:$F$46,M35,$Q$2:$Q$46,"Aprobada")>0)),M35&" ","")&IF(NOT(OR(N35="",COUNTIF($F$2:$F$46,N35)=0,COUNTIFS($F$2:$F$46,N35,$Q$2:$Q$46,"Aprobada")>0)),N35&" ","")&IF(NOT(OR(O35="",COUNTIF($F$2:$F$46,O35)=0,COUNTIFS($F$2:$F$46,O35,$Q$2:$Q$46,"Aprobada")>0)),O35&" ","")&IF(NOT(OR(P35="",COUNTIF($F$2:$F$46,P35)=0,COUNTIFS($F$2:$F$46,P35,$Q$2:$Q$46,"Aprobada")>0)),P35&" ","")),IF(Q35="Cursada aprobada",TRIM(IF(NOT(OR(L35="",COUNTIF($F$2:$F$46,L35)=0,COUNTIFS($F$2:$F$46,L35,$Q$2:$Q$46,"Aprobada")>0,AND(Resumen!$B$15="La cursada aprobada",COUNTIFS($F$2:$F$46,L35,$Q$2:$Q$46,"Cursada aprobada")>0))),L35&" ","")&IF(NOT(OR(M35="",COUNTIF($F$2:$F$46,M35)=0,COUNTIFS($F$2:$F$46,M35,$Q$2:$Q$46,"Aprobada")>0,AND(Resumen!$B$15="La cursada aprobada",COUNTIFS($F$2:$F$46,M35,$Q$2:$Q$46,"Cursada aprobada")>0))),M35&" ","")&IF(NOT(OR(N35="",COUNTIF($F$2:$F$46,N35)=0,COUNTIFS($F$2:$F$46,N35,$Q$2:$Q$46,"Aprobada")>0,AND(Resumen!$B$15="La cursada aprobada",COUNTIFS($F$2:$F$46,N35,$Q$2:$Q$46,"Cursada aprobada")>0))),N35&" ","")&IF(NOT(OR(O35="",COUNTIF($F$2:$F$46,O35)=0,COUNTIFS($F$2:$F$46,O35,$Q$2:$Q$46,"Aprobada")>0,AND(Resumen!$B$15="La cursada aprobada",COUNTIFS($F$2:$F$46,O35,$Q$2:$Q$46,"Cursada aprobada")>0))),O35&" ","")&IF(NOT(OR(P35="",COUNTIF($F$2:$F$46,P35)=0,COUNTIFS($F$2:$F$46,P35,$Q$2:$Q$46,"Aprobada")>0,AND(Resumen!$B$15="La cursada aprobada",COUNTIFS($F$2:$F$46,P35,$Q$2:$Q$46,"Cursada aprobada")>0))),P35&" ","")),""))
A36: Ciclo de orientación | B36: Teoría Contable Avanzada | C36: 5 | D36: 2 | E36: CO | F36: 510 | G36: Normas Contables Comparadas | I36: 4 | K36: 64 | L36: 525 | M36: 527 | Q36: No cursada | R36: =IF(Q36="Aprobada","Ya aprobada",IF(Q36="Cursada aprobada","Ya cursada",IF(AND(OR(L36="",COUNTIF($F$2:$F$46,L36)=0,COUNTIFS($F$2:$F$46,L36,$Q$2:$Q$46,"Aprobada")>0,AND(Resumen!$B$15="La cursada aprobada",COUNTIFS($F$2:$F$46,L36,$Q$2:$Q$46,"Cursada aprobada")>0)),OR(M36="",COUNTIF($F$2:$F$46,M36)=0,COUNTIFS($F$2:$F$46,M36,$Q$2:$Q$46,"Aprobada")>0,AND(Resumen!$B$15="La cursada aprobada",COUNTIFS($F$2:$F$46,M36,$Q$2:$Q$46,"Cursada aprobada")>0)),OR(N36="",COUNTIF($F$2:$F$46,N36)=0,COUNTIFS($F$2:$F$46,N36,$Q$2:$Q$46,"Aprobada")>0,AND(Resumen!$B$15="La cursada aprobada",COUNTIFS($F$2:$F$46,N36,$Q$2:$Q$46,"Cursada aprobada")>0)),OR(O36="",COUNTIF($F$2:$F$46,O36)=0,COUNTIFS($F$2:$F$46,O36,$Q$2:$Q$46,"Aprobada")>0,AND(Resumen!$B$15="La cursada aprobada",COUNTIFS($F$2:$F$46,O36,$Q$2:$Q$46,"Cursada aprobada")>0)),OR(P36="",COUNTIF($F$2:$F$46,P36)=0,COUNTIFS($F$2:$F$46,P36,$Q$2:$Q$46,"Aprobada")>0,AND(Resumen!$B$15="La cursada aprobada",COUNTIFS($F$2:$F$46,P36,$Q$2:$Q$46,"Cursada aprobada")>0))),"Sí","No"))) -> No | S36: =TRIM(IF(NOT(OR(L36="",COUNTIF($F$2:$F$46,L36)=0,COUNTIFS($F$2:$F$46,L36,$Q$2:$Q$46,"Aprobada")>0,AND(Resumen!$B$15="La cursada aprobada",COUNTIFS($F$2:$F$46,L36,$Q$2:$Q$46,"Cursada aprobada")>0))),L36&" ","")&IF(NOT(OR(M36="",COUNTIF($F$2:$F$46,M36)=0,COUNTIFS($F$2:$F$46,M36,$Q$2:$Q$46,"Aprobada")>0,AND(Resumen!$B$15="La cursada aprobada",COUNTIFS($F$2:$F$46,M36,$Q$2:$Q$46,"Cursada aprobada")>0))),M36&" ","")&IF(NOT(OR(N36="",COUNTIF($F$2:$F$46,N36)=0,COUNTIFS($F$2:$F$46,N36,$Q$2:$Q$46,"Aprobada")>0,AND(Resumen!$B$15="La cursada aprobada",COUNTIFS($F$2:$F$46,N36,$Q$2:$Q$46,"Cursada aprobada")>0))),N36&" ","")&IF(NOT(OR(O36="",COUNTIF($F$2:$F$46,O36)=0,COUNTIFS($F$2:$F$46,O36,$Q$2:$Q$46,"Aprobada")>0,AND(Resumen!$B$15="La cursada aprobada",COUNTIFS($F$2:$F$46,O36,$Q$2:$Q$46,"Cursada aprobada")>0))),O36&" ","")&IF(NOT(OR(P36="",COUNTIF($F$2:$F$46,P36)=0,COUNTIFS($F$2:$F$46,P36,$Q$2:$Q$46,"Aprobada")>0,AND(Resumen!$B$15="La cursada aprobada",COUNTIFS($F$2:$F$46,P36,$Q$2:$Q$46,"Cursada aprobada")>0))),P36&" ","")) -> 525 527 | T36: =IF(Q36="Cursada aprobada",IF(AND(OR(L36="",COUNTIF($F$2:$F$46,L36)=0,COUNTIFS($F$2:$F$46,L36,$Q$2:$Q$46,"Aprobada")>0),OR(M36="",COUNTIF($F$2:$F$46,M36)=0,COUNTIFS($F$2:$F$46,M36,$Q$2:$Q$46,"Aprobada")>0),OR(N36="",COUNTIF($F$2:$F$46,N36)=0,COUNTIFS($F$2:$F$46,N36,$Q$2:$Q$46,"Aprobada")>0),OR(O36="",COUNTIF($F$2:$F$46,O36)=0,COUNTIFS($F$2:$F$46,O36,$Q$2:$Q$46,"Aprobada")>0),OR(P36="",COUNTIF($F$2:$F$46,P36)=0,COUNTIFS($F$2:$F$46,P36,$Q$2:$Q$46,"Aprobada")>0)),"Sí","No"),"") | U36: =IF(Q36="Aprobada",TRIM(IF(NOT(OR(L36="",COUNTIF($F$2:$F$46,L36)=0,COUNTIFS($F$2:$F$46,L36,$Q$2:$Q$46,"Aprobada")>0)),L36&" ","")&IF(NOT(OR(M36="",COUNTIF($F$2:$F$46,M36)=0,COUNTIFS($F$2:$F$46,M36,$Q$2:$Q$46,"Aprobada")>0)),M36&" ","")&IF(NOT(OR(N36="",COUNTIF($F$2:$F$46,N36)=0,COUNTIFS($F$2:$F$46,N36,$Q$2:$Q$46,"Aprobada")>0)),N36&" ","")&IF(NOT(OR(O36="",COUNTIF($F$2:$F$46,O36)=0,COUNTIFS($F$2:$F$46,O36,$Q$2:$Q$46,"Aprobada")>0)),O36&" ","")&IF(NOT(OR(P36="",COUNTIF($F$2:$F$46,P36)=0,COUNTIFS($F$2:$F$46,P36,$Q$2:$Q$46,"Aprobada")>0)),P36&" ","")),IF(Q36="Cursada aprobada",TRIM(IF(NOT(OR(L36="",COUNTIF($F$2:$F$46,L36)=0,COUNTIFS($F$2:$F$46,L36,$Q$2:$Q$46,"Aprobada")>0,AND(Resumen!$B$15="La cursada aprobada",COUNTIFS($F$2:$F$46,L36,$Q$2:$Q$46,"Cursada aprobada")>0))),L36&" ","")&IF(NOT(OR(M36="",COUNTIF($F$2:$F$46,M36)=0,COUNTIFS($F$2:$F$46,M36,$Q$2:$Q$46,"Aprobada")>0,AND(Resumen!$B$15="La cursada aprobada",COUNTIFS($F$2:$F$46,M36,$Q$2:$Q$46,"Cursada aprobada")>0))),M36&" ","")&IF(NOT(OR(N36="",COUNTIF($F$2:$F$46,N36)=0,COUNTIFS($F$2:$F$46,N36,$Q$2:$Q$46,"Aprobada")>0,AND(Resumen!$B$15="La cursada aprobada",COUNTIFS($F$2:$F$46,N36,$Q$2:$Q$46,"Cursada aprobada")>0))),N36&" ","")&IF(NOT(OR(O36="",COUNTIF($F$2:$F$46,O36)=0,COUNTIFS($F$2:$F$46,O36,$Q$2:$Q$46,"Aprobada")>0,AND(Resumen!$B$15="La cursada aprobada",COUNTIFS($F$2:$F$46,O36,$Q$2:$Q$46,"Cursada aprobada")>0))),O36&" ","")&IF(NOT(OR(P36="",COUNTIF($F$2:$F$46,P36)=0,COUNTIFS($F$2:$F$46,P36,$Q$2:$Q$46,"Aprobada")>0,AND(Resumen!$B$15="La cursada aprobada",COUNTIFS($F$2:$F$46,P36,$Q$2:$Q$46,"Cursada aprobada")>0))),P36&" ","")),""))
A37: Ciclo de orientación | B37: Gestión Pública | C37: 5 | D37: 2 | E37: AD | F37: 560 | G37: Org. y Adm. Financiera del Estado | I37: 4 | K37: 64 | L37: 349 | M37: 460 | Q37: No cursada | R37: =IF(Q37="Aprobada","Ya aprobada",IF(Q37="Cursada aprobada","Ya cursada",IF(AND(OR(L37="",COUNTIF($F$2:$F$46,L37)=0,COUNTIFS($F$2:$F$46,L37,$Q$2:$Q$46,"Aprobada")>0,AND(Resumen!$B$15="La cursada aprobada",COUNTIFS($F$2:$F$46,L37,$Q$2:$Q$46,"Cursada aprobada")>0)),OR(M37="",COUNTIF($F$2:$F$46,M37)=0,COUNTIFS($F$2:$F$46,M37,$Q$2:$Q$46,"Aprobada")>0,AND(Resumen!$B$15="La cursada aprobada",COUNTIFS($F$2:$F$46,M37,$Q$2:$Q$46,"Cursada aprobada")>0)),OR(N37="",COUNTIF($F$2:$F$46,N37)=0,COUNTIFS($F$2:$F$46,N37,$Q$2:$Q$46,"Aprobada")>0,AND(Resumen!$B$15="La cursada aprobada",COUNTIFS($F$2:$F$46,N37,$Q$2:$Q$46,"Cursada aprobada")>0)),OR(O37="",COUNTIF($F$2:$F$46,O37)=0,COUNTIFS($F$2:$F$46,O37,$Q$2:$Q$46,"Aprobada")>0,AND(Resumen!$B$15="La cursada aprobada",COUNTIFS($F$2:$F$46,O37,$Q$2:$Q$46,"Cursada aprobada")>0)),OR(P37="",COUNTIF($F$2:$F$46,P37)=0,COUNTIFS($F$2:$F$46,P37,$Q$2:$Q$46,"Aprobada")>0,AND(Resumen!$B$15="La cursada aprobada",COUNTIFS($F$2:$F$46,P37,$Q$2:$Q$46,"Cursada aprobada")>0))),"Sí","No"))) -> No | S37: =TRIM(IF(NOT(OR(L37="",COUNTIF($F$2:$F$46,L37)=0,COUNTIFS($F$2:$F$46,L37,$Q$2:$Q$46,"Aprobada")>0,AND(Resumen!$B$15="La cursada aprobada",COUNTIFS($F$2:$F$46,L37,$Q$2:$Q$46,"Cursada aprobada")>0))),L37&" ","")&IF(NOT(OR(M37="",COUNTIF($F$2:$F$46,M37)=0,COUNTIFS($F$2:$F$46,M37,$Q$2:$Q$46,"Aprobada")>0,AND(Resumen!$B$15="La cursada aprobada",COUNTIFS($F$2:$F$46,M37,$Q$2:$Q$46,"Cursada aprobada")>0))),M37&" ","")&IF(NOT(OR(N37="",COUNTIF($F$2:$F$46,N37)=0,COUNTIFS($F$2:$F$46,N37,$Q$2:$Q$46,"Aprobada")>0,AND(Resumen!$B$15="La cursada aprobada",COUNTIFS($F$2:$F$46,N37,$Q$2:$Q$46,"Cursada aprobada")>0))),N37&" ","")&IF(NOT(OR(O37="",COUNTIF($F$2:$F$46,O37)=0,COUNTIFS($F$2:$F$46,O37,$Q$2:$Q$46,"Aprobada")>0,AND(Resumen!$B$15="La cursada aprobada",COUNTIFS($F$2:$F$46,O37,$Q$2:$Q$46,"Cursada aprobada")>0))),O37&" ","")&IF(NOT(OR(P37="",COUNTIF($F$2:$F$46,P37)=0,COUNTIFS($F$2:$F$46,P37,$Q$2:$Q$46,"Aprobada")>0,AND(Resumen!$B$15="La cursada aprobada",COUNTIFS($F$2:$F$46,P37,$Q$2:$Q$46,"Cursada aprobada")>0))),P37&" ","")) -> 349 460 | T37: =IF(Q37="Cursada aprobada",IF(AND(OR(L37="",COUNTIF($F$2:$F$46,L37)=0,COUNTIFS($F$2:$F$46,L37,$Q$2:$Q$46,"Aprobada")>0),OR(M37="",COUNTIF($F$2:$F$46,M37)=0,COUNTIFS($F$2:$F$46,M37,$Q$2:$Q$46,"Aprobada")>0),OR(N37="",COUNTIF($F$2:$F$46,N37)=0,COUNTIFS($F$2:$F$46,N37,$Q$2:$Q$46,"Aprobada")>0),OR(O37="",COUNTIF($F$2:$F$46,O37)=0,COUNTIFS($F$2:$F$46,O37,$Q$2:$Q$46,"Aprobada")>0),OR(P37="",COUNTIF($F$2:$F$46,P37)=0,COUNTIFS($F$2:$F$46,P37,$Q$2:$Q$46,"Aprobada")>0)),"Sí","No"),"") | U37: =IF(Q37="Aprobada",TRIM(IF(NOT(OR(L37="",COUNTIF($F$2:$F$46,L37)=0,COUNTIFS($F$2:$F$46,L37,$Q$2:$Q$46,"Aprobada")>0)),L37&" ","")&IF(NOT(OR(M37="",COUNTIF($F$2:$F$46,M37)=0,COUNTIFS($F$2:$F$46,M37,$Q$2:$Q$46,"Aprobada")>0)),M37&" ","")&IF(NOT(OR(N37="",COUNTIF($F$2:$F$46,N37)=0,COUNTIFS($F$2:$F$46,N37,$Q$2:$Q$46,"Aprobada")>0)),N37&" ","")&IF(NOT(OR(O37="",COUNTIF($F$2:$F$46,O37)=0,COUNTIFS($F$2:$F$46,O37,$Q$2:$Q$46,"Aprobada")>0)),O37&" ","")&IF(NOT(OR(P37="",COUNTIF($F$2:$F$46,P37)=0,COUNTIFS($F$2:$F$46,P37,$Q$2:$Q$46,"Aprobada")>0)),P37&" ","")),IF(Q37="Cursada aprobada",TRIM(IF(NOT(OR(L37="",COUNTIF($F$2:$F$46,L37)=0,COUNTIFS($F$2:$F$46,L37,$Q$2:$Q$46,"Aprobada")>0,AND(Resumen!$B$15="La cursada aprobada",COUNTIFS($F$2:$F$46,L37,$Q$2:$Q$46,"Cursada aprobada")>0))),L37&" ","")&IF(NOT(OR(M37="",COUNTIF($F$2:$F$46,M37)=0,COUNTIFS($F$2:$F$46,M37,$Q$2:$Q$46,"Aprobada")>0,AND(Resumen!$B$15="La cursada aprobada",COUNTIFS($F$2:$F$46,M37,$Q$2:$Q$46,"Cursada aprobada")>0))),M37&" ","")&IF(NOT(OR(N37="",COUNTIF($F$2:$F$46,N37)=0,COUNTIFS($F$2:$F$46,N37,$Q$2:$Q$46,"Aprobada")>0,AND(Resumen!$B$15="La cursada aprobada",COUNTIFS($F$2:$F$46,N37,$Q$2:$Q$46,"Cursada aprobada")>0))),N37&" ","")&IF(NOT(OR(O37="",COUNTIF($F$2:$F$46,O37)=0,COUNTIFS($F$2:$F$46,O37,$Q$2:$Q$46,"Aprobada")>0,AND(Resumen!$B$15="La cursada aprobada",COUNTIFS($F$2:$F$46,O37,$Q$2:$Q$46,"Cursada aprobada")>0))),O37&" ","")&IF(NOT(OR(P37="",COUNTIF($F$2:$F$46,P37)=0,COUNTIFS($F$2:$F$46,P37,$Q$2:$Q$46,"Aprobada")>0,AND(Resumen!$B$15="La cursada aprobada",COUNTIFS($F$2:$F$46,P37,$Q$2:$Q$46,"Cursada aprobada")>0))),P37&" ","")),""))
A38: Ciclo de orientación | B38: Gestión de Org. de la Economía Regional | C38: 5 | D38: 2 | E38: AD | F38: 565 | G38: Creación de Empresas | I38: 4 | K38: 64 | L38: 430 | M38: 425 | N38: 490 | O38: 491 | Q38: No cursada | R38: =IF(Q38="Aprobada","Ya aprobada",IF(Q38="Cursada aprobada","Ya cursada",IF(AND(OR(L38="",COUNTIF($F$2:$F$46,L38)=0,COUNTIFS($F$2:$F$46,L38,$Q$2:$Q$46,"Aprobada")>0,AND(Resumen!$B$15="La cursada aprobada",COUNTIFS($F$2:$F$46,L38,$Q$2:$Q$46,"Cursada aprobada")>0)),OR(M38="",COUNTIF($F$2:$F$46,M38)=0,COUNTIFS($F$2:$F$46,M38,$Q$2:$Q$46,"Aprobada")>0,AND(Resumen!$B$15="La cursada aprobada",COUNTIFS($F$2:$F$46,M38,$Q$2:$Q$46,"Cursada aprobada")>0)),OR(N38="",COUNTIF($F$2:$F$46,N38)=0,COUNTIFS($F$2:$F$46,N38,$Q$2:$Q$46,"Aprobada")>0,AND(Resumen!$B$15="La cursada aprobada",COUNTIFS($F$2:$F$46,N38,$Q$2:$Q$46,"Cursada aprobada")>0)),OR(O38="",COUNTIF($F$2:$F$46,O38)=0,COUNTIFS($F$2:$F$46,O38,$Q$2:$Q$46,"Aprobada")>0,AND(Resumen!$B$15="La cursada aprobada",COUNTIFS($F$2:$F$46,O38,$Q$2:$Q$46,"Cursada aprobada")>0)),OR(P38="",COUNTIF($F$2:$F$46,P38)=0,COUNTIFS($F$2:$F$46,P38,$Q$2:$Q$46,"Aprobada")>0,AND(Resumen!$B$15="La cursada aprobada",COUNTIFS($F$2:$F$46,P38,$Q$2:$Q$46,"Cursada aprobada")>0))),"Sí","No"))) -> No | S38: =TRIM(IF(NOT(OR(L38="",COUNTIF($F$2:$F$46,L38)=0,COUNTIFS($F$2:$F$46,L38,$Q$2:$Q$46,"Aprobada")>0,AND(Resumen!$B$15="La cursada aprobada",COUNTIFS($F$2:$F$46,L38,$Q$2:$Q$46,"Cursada aprobada")>0))),L38&" ","")&IF(NOT(OR(M38="",COUNTIF($F$2:$F$46,M38)=0,COUNTIFS($F$2:$F$46,M38,$Q$2:$Q$46,"Aprobada")>0,AND(Resumen!$B$15="La cursada aprobada",COUNTIFS($F$2:$F$46,M38,$Q$2:$Q$46,"Cursada aprobada")>0))),M38&" ","")&IF(NOT(OR(N38="",COUNTIF($F$2:$F$46,N38)=0,COUNTIFS($F$2:$F$46,N38,$Q$2:$Q$46,"Aprobada")>0,AND(Resumen!$B$15="La cursada aprobada",COUNTIFS($F$2:$F$46,N38,$Q$2:$Q$46,"Cursada aprobada")>0))),N38&" ","")&IF(NOT(OR(O38="",COUNTIF($F$2:$F$46,O38)=0,COUNTIFS($F$2:$F$46,O38,$Q$2:$Q$46,"Aprobada")>0,AND(Resumen!$B$15="La cursada aprobada",COUNTIFS($F$2:$F$46,O38,$Q$2:$Q$46,"Cursada aprobada")>0))),O38&" ","")&IF(NOT(OR(P38="",COUNTIF($F$2:$F$46,P38)=0,COUNTIFS($F$2:$F$46,P38,$Q$2:$Q$46,"Aprobada")>0,AND(Resumen!$B$15="La cursada aprobada",COUNTIFS($F$2:$F$46,P38,$Q$2:$Q$46,"Cursada aprobada")>0))),P38&" ","")) -> 430 425 490 491 | T38: =IF(Q38="Cursada aprobada",IF(AND(OR(L38="",COUNTIF($F$2:$F$46,L38)=0,COUNTIFS($F$2:$F$46,L38,$Q$2:$Q$46,"Aprobada")>0),OR(M38="",COUNTIF($F$2:$F$46,M38)=0,COUNTIFS($F$2:$F$46,M38,$Q$2:$Q$46,"Aprobada")>0),OR(N38="",COUNTIF($F$2:$F$46,N38)=0,COUNTIFS($F$2:$F$46,N38,$Q$2:$Q$46,"Aprobada")>0),OR(O38="",COUNTIF($F$2:$F$46,O38)=0,COUNTIFS($F$2:$F$46,O38,$Q$2:$Q$46,"Aprobada")>0),OR(P38="",COUNTIF($F$2:$F$46,P38)=0,COUNTIFS($F$2:$F$46,P38,$Q$2:$Q$46,"Aprobada")>0)),"Sí","No"),"") | U38: =IF(Q38="Aprobada",TRIM(IF(NOT(OR(L38="",COUNTIF($F$2:$F$46,L38)=0,COUNTIFS($F$2:$F$46,L38,$Q$2:$Q$46,"Aprobada")>0)),L38&" ","")&IF(NOT(OR(M38="",COUNTIF($F$2:$F$46,M38)=0,COUNTIFS($F$2:$F$46,M38,$Q$2:$Q$46,"Aprobada")>0)),M38&" ","")&IF(NOT(OR(N38="",COUNTIF($F$2:$F$46,N38)=0,COUNTIFS($F$2:$F$46,N38,$Q$2:$Q$46,"Aprobada")>0)),N38&" ","")&IF(NOT(OR(O38="",COUNTIF($F$2:$F$46,O38)=0,COUNTIFS($F$2:$F$46,O38,$Q$2:$Q$46,"Aprobada")>0)),O38&" ","")&IF(NOT(OR(P38="",COUNTIF($F$2:$F$46,P38)=0,COUNTIFS($F$2:$F$46,P38,$Q$2:$Q$46,"Aprobada")>0)),P38&" ","")),IF(Q38="Cursada aprobada",TRIM(IF(NOT(OR(L38="",COUNTIF($F$2:$F$46,L38)=0,COUNTIFS($F$2:$F$46,L38,$Q$2:$Q$46,"Aprobada")>0,AND(Resumen!$B$15="La cursada aprobada",COUNTIFS($F$2:$F$46,L38,$Q$2:$Q$46,"Cursada aprobada")>0))),L38&" ","")&IF(NOT(OR(M38="",COUNTIF($F$2:$F$46,M38)=0,COUNTIFS($F$2:$F$46,M38,$Q$2:$Q$46,"Aprobada")>0,AND(Resumen!$B$15="La cursada aprobada",COUNTIFS($F$2:$F$46,M38,$Q$2:$Q$46,"Cursada aprobada")>0))),M38&" ","")&IF(NOT(OR(N38="",COUNTIF($F$2:$F$46,N38)=0,COUNTIFS($F$2:$F$46,N38,$Q$2:$Q$46,"Aprobada")>0,AND(Resumen!$B$15="La cursada aprobada",COUNTIFS($F$2:$F$46,N38,$Q$2:$Q$46,"Cursada aprobada")>0))),N38&" ","")&IF(NOT(OR(O38="",COUNTIF($F$2:$F$46,O38)=0,COUNTIFS($F$2:$F$46,O38,$Q$2:$Q$46,"Aprobada")>0,AND(Resumen!$B$15="La cursada aprobada",COUNTIFS($F$2:$F$46,O38,$Q$2:$Q$46,"Cursada aprobada")>0))),O38&" ","")&IF(NOT(OR(P38="",COUNTIF($F$2:$F$46,P38)=0,COUNTIFS($F$2:$F$46,P38,$Q$2:$Q$46,"Aprobada")>0,AND(Resumen!$B$15="La cursada aprobada",COUNTIFS($F$2:$F$46,P38,$Q$2:$Q$46,"Cursada aprobada")>0))),P38&" ","")),""))
A39: Ciclo de orientación | B39: Derecho Empresario (Jurídico-Contable) | C39: 5 | D39: 2 | E39: JU | F39: 592 | G39: Contratos Especiales | I39: 4 | K39: 64 | Q39: No cursada | R39: =IF(Q39="Aprobada","Ya aprobada",IF(Q39="Cursada aprobada","Ya cursada",IF(AND(OR(L39="",COUNTIF($F$2:$F$46,L39)=0,COUNTIFS($F$2:$F$46,L39,$Q$2:$Q$46,"Aprobada")>0,AND(Resumen!$B$15="La cursada aprobada",COUNTIFS($F$2:$F$46,L39,$Q$2:$Q$46,"Cursada aprobada")>0)),OR(M39="",COUNTIF($F$2:$F$46,M39)=0,COUNTIFS($F$2:$F$46,M39,$Q$2:$Q$46,"Aprobada")>0,AND(Resumen!$B$15="La cursada aprobada",COUNTIFS($F$2:$F$46,M39,$Q$2:$Q$46,"Cursada aprobada")>0)),OR(N39="",COUNTIF($F$2:$F$46,N39)=0,COUNTIFS($F$2:$F$46,N39,$Q$2:$Q$46,"Aprobada")>0,AND(Resumen!$B$15="La cursada aprobada",COUNTIFS($F$2:$F$46,N39,$Q$2:$Q$46,"Cursada aprobada")>0)),OR(O39="",COUNTIF($F$2:$F$46,O39)=0,COUNTIFS($F$2:$F$46,O39,$Q$2:$Q$46,"Aprobada")>0,AND(Resumen!$B$15="La cursada aprobada",COUNTIFS($F$2:$F$46,O39,$Q$2:$Q$46,"Cursada aprobada")>0)),OR(P39="",COUNTIF($F$2:$F$46,P39)=0,COUNTIFS($F$2:$F$46,P39,$Q$2:$Q$46,"Aprobada")>0,AND(Resumen!$B$15="La cursada aprobada",COUNTIFS($F$2:$F$46,P39,$Q$2:$Q$46,"Cursada aprobada")>0))),"Sí","No"))) -> Sí | S39: =TRIM(IF(NOT(OR(L39="",COUNTIF($F$2:$F$46,L39)=0,COUNTIFS($F$2:$F$46,L39,$Q$2:$Q$46,"Aprobada")>0,AND(Resumen!$B$15="La cursada aprobada",COUNTIFS($F$2:$F$46,L39,$Q$2:$Q$46,"Cursada aprobada")>0))),L39&" ","")&IF(NOT(OR(M39="",COUNTIF($F$2:$F$46,M39)=0,COUNTIFS($F$2:$F$46,M39,$Q$2:$Q$46,"Aprobada")>0,AND(Resumen!$B$15="La cursada aprobada",COUNTIFS($F$2:$F$46,M39,$Q$2:$Q$46,"Cursada aprobada")>0))),M39&" ","")&IF(NOT(OR(N39="",COUNTIF($F$2:$F$46,N39)=0,COUNTIFS($F$2:$F$46,N39,$Q$2:$Q$46,"Aprobada")>0,AND(Resumen!$B$15="La cursada aprobada",COUNTIFS($F$2:$F$46,N39,$Q$2:$Q$46,"Cursada aprobada")>0))),N39&" ","")&IF(NOT(OR(O39="",COUNTIF($F$2:$F$46,O39)=0,COUNTIFS($F$2:$F$46,O39,$Q$2:$Q$46,"Aprobada")>0,AND(Resumen!$B$15="La cursada aprobada",COUNTIFS($F$2:$F$46,O39,$Q$2:$Q$46,"Cursada aprobada")>0))),O39&" ","")&IF(NOT(OR(P39="",COUNTIF($F$2:$F$46,P39)=0,COUNTIFS($F$2:$F$46,P39,$Q$2:$Q$46,"Aprobada")>0,AND(Resumen!$B$15="La cursada aprobada",COUNTIFS($F$2:$F$46,P39,$Q$2:$Q$46,"Cursada aprobada")>0))),P39&" ","")) | T39: =IF(Q39="Cursada aprobada",IF(AND(OR(L39="",COUNTIF($F$2:$F$46,L39)=0,COUNTIFS($F$2:$F$46,L39,$Q$2:$Q$46,"Aprobada")>0),OR(M39="",COUNTIF($F$2:$F$46,M39)=0,COUNTIFS($F$2:$F$46,M39,$Q$2:$Q$46,"Aprobada")>0),OR(N39="",COUNTIF($F$2:$F$46,N39)=0,COUNTIFS($F$2:$F$46,N39,$Q$2:$Q$46,"Aprobada")>0),OR(O39="",COUNTIF($F$2:$F$46,O39)=0,COUNTIFS($F$2:$F$46,O39,$Q$2:$Q$46,"Aprobada")>0),OR(P39="",COUNTIF($F$2:$F$46,P39)=0,COUNTIFS($F$2:$F$46,P39,$Q$2:$Q$46,"Aprobada")>0)),"Sí","No"),"") | U39: =IF(Q39="Aprobada",TRIM(IF(NOT(OR(L39="",COUNTIF($F$2:$F$46,L39)=0,COUNTIFS($F$2:$F$46,L39,$Q$2:$Q$46,"Aprobada")>0)),L39&" ","")&IF(NOT(OR(M39="",COUNTIF($F$2:$F$46,M39)=0,COUNTIFS($F$2:$F$46,M39,$Q$2:$Q$46,"Aprobada")>0)),M39&" ","")&IF(NOT(OR(N39="",COUNTIF($F$2:$F$46,N39)=0,COUNTIFS($F$2:$F$46,N39,$Q$2:$Q$46,"Aprobada")>0)),N39&" ","")&IF(NOT(OR(O39="",COUNTIF($F$2:$F$46,O39)=0,COUNTIFS($F$2:$F$46,O39,$Q$2:$Q$46,"Aprobada")>0)),O39&" ","")&IF(NOT(OR(P39="",COUNTIF($F$2:$F$46,P39)=0,COUNTIFS($F$2:$F$46,P39,$Q$2:$Q$46,"Aprobada")>0)),P39&" ","")),IF(Q39="Cursada aprobada",TRIM(IF(NOT(OR(L39="",COUNTIF($F$2:$F$46,L39)=0,COUNTIFS($F$2:$F$46,L39,$Q$2:$Q$46,"Aprobada")>0,AND(Resumen!$B$15="La cursada aprobada",COUNTIFS($F$2:$F$46,L39,$Q$2:$Q$46,"Cursada aprobada")>0))),L39&" ","")&IF(NOT(OR(M39="",COUNTIF($F$2:$F$46,M39)=0,COUNTIFS($F$2:$F$46,M39,$Q$2:$Q$46,"Aprobada")>0,AND(Resumen!$B$15="La cursada aprobada",COUNTIFS($F$2:$F$46,M39,$Q$2:$Q$46,"Cursada aprobada")>0))),M39&" ","")&IF(NOT(OR(N39="",COUNTIF($F$2:$F$46,N39)=0,COUNTIFS($F$2:$F$46,N39,$Q$2:$Q$46,"Aprobada")>0,AND(Resumen!$B$15="La cursada aprobada",COUNTIFS($F$2:$F$46,N39,$Q$2:$Q$46,"Cursada aprobada")>0))),N39&" ","")&IF(NOT(OR(O39="",COUNTIF($F$2:$F$46,O39)=0,COUNTIFS($F$2:$F$46,O39,$Q$2:$Q$46,"Aprobada")>0,AND(Resumen!$B$15="La cursada aprobada",COUNTIFS($F$2:$F$46,O39,$Q$2:$Q$46,"Cursada aprobada")>0))),O39&" ","")&IF(NOT(OR(P39="",COUNTIF($F$2:$F$46,P39)=0,COUNTIFS($F$2:$F$46,P39,$Q$2:$Q$46,"Aprobada")>0,AND(Resumen!$B$15="La cursada aprobada",COUNTIFS($F$2:$F$46,P39,$Q$2:$Q$46,"Cursada aprobada")>0))),P39&" ","")),""))
A40: Ciclo de orientación | B40: Gestión Financiera | C40: 5 | D40: 2 | E40: EC | F40: 504 | G40: Análisis y Evaluación de Proyectos | I40: 4 | K40: 64 | L40: 430 | Q40: No cursada | R40: =IF(Q40="Aprobada","Ya aprobada",IF(Q40="Cursada aprobada","Ya cursada",IF(AND(OR(L40="",COUNTIF($F$2:$F$46,L40)=0,COUNTIFS($F$2:$F$46,L40,$Q$2:$Q$46,"Aprobada")>0,AND(Resumen!$B$15="La cursada aprobada",COUNTIFS($F$2:$F$46,L40,$Q$2:$Q$46,"Cursada aprobada")>0)),OR(M40="",COUNTIF($F$2:$F$46,M40)=0,COUNTIFS($F$2:$F$46,M40,$Q$2:$Q$46,"Aprobada")>0,AND(Resumen!$B$15="La cursada aprobada",COUNTIFS($F$2:$F$46,M40,$Q$2:$Q$46,"Cursada aprobada")>0)),OR(N40="",COUNTIF($F$2:$F$46,N40)=0,COUNTIFS($F$2:$F$46,N40,$Q$2:$Q$46,"Aprobada")>0,AND(Resumen!$B$15="La cursada aprobada",COUNTIFS($F$2:$F$46,N40,$Q$2:$Q$46,"Cursada aprobada")>0)),OR(O40="",COUNTIF($F$2:$F$46,O40)=0,COUNTIFS($F$2:$F$46,O40,$Q$2:$Q$46,"Aprobada")>0,AND(Resumen!$B$15="La cursada aprobada",COUNTIFS($F$2:$F$46,O40,$Q$2:$Q$46,"Cursada aprobada")>0)),OR(P40="",COUNTIF($F$2:$F$46,P40)=0,COUNTIFS($F$2:$F$46,P40,$Q$2:$Q$46,"Aprobada")>0,AND(Resumen!$B$15="La cursada aprobada",COUNTIFS($F$2:$F$46,P40,$Q$2:$Q$46,"Cursada aprobada")>0))),"Sí","No"))) -> No | S40: =TRIM(IF(NOT(OR(L40="",COUNTIF($F$2:$F$46,L40)=0,COUNTIFS($F$2:$F$46,L40,$Q$2:$Q$46,"Aprobada")>0,AND(Resumen!$B$15="La cursada aprobada",COUNTIFS($F$2:$F$46,L40,$Q$2:$Q$46,"Cursada aprobada")>0))),L40&" ","")&IF(NOT(OR(M40="",COUNTIF($F$2:$F$46,M40)=0,COUNTIFS($F$2:$F$46,M40,$Q$2:$Q$46,"Aprobada")>0,AND(Resumen!$B$15="La cursada aprobada",COUNTIFS($F$2:$F$46,M40,$Q$2:$Q$46,"Cursada aprobada")>0))),M40&" ","")&IF(NOT(OR(N40="",COUNTIF($F$2:$F$46,N40)=0,COUNTIFS($F$2:$F$46,N40,$Q$2:$Q$46,"Aprobada")>0,AND(Resumen!$B$15="La cursada aprobada",COUNTIFS($F$2:$F$46,N40,$Q$2:$Q$46,"Cursada aprobada")>0))),N40&" ","")&IF(NOT(OR(O40="",COUNTIF($F$2:$F$46,O40)=0,COUNTIFS($F$2:$F$46,O40,$Q$2:$Q$46,"Aprobada")>0,AND(Resumen!$B$15="La cursada aprobada",COUNTIFS($F$2:$F$46,O40,$Q$2:$Q$46,"Cursada aprobada")>0))),O40&" ","")&IF(NOT(OR(P40="",COUNTIF($F$2:$F$46,P40)=0,COUNTIFS($F$2:$F$46,P40,$Q$2:$Q$46,"Aprobada")>0,AND(Resumen!$B$15="La cursada aprobada",COUNTIFS($F$2:$F$46,P40,$Q$2:$Q$46,"Cursada aprobada")>0))),P40&" ","")) -> 430 | T40: =IF(Q40="Cursada aprobada",IF(AND(OR(L40="",COUNTIF($F$2:$F$46,L40)=0,COUNTIFS($F$2:$F$46,L40,$Q$2:$Q$46,"Aprobada")>0),OR(M40="",COUNTIF($F$2:$F$46,M40)=0,COUNTIFS($F$2:$F$46,M40,$Q$2:$Q$46,"Aprobada")>0),OR(N40="",COUNTIF($F$2:$F$46,N40)=0,COUNTIFS($F$2:$F$46,N40,$Q$2:$Q$46,"Aprobada")>0),OR(O40="",COUNTIF($F$2:$F$46,O40)=0,COUNTIFS($F$2:$F$46,O40,$Q$2:$Q$46,"Aprobada")>0),OR(P40="",COUNTIF($F$2:$F$46,P40)=0,COUNTIFS($F$2:$F$46,P40,$Q$2:$Q$46,"Aprobada")>0)),"Sí","No"),"") | U40: =IF(Q40="Aprobada",TRIM(IF(NOT(OR(L40="",COUNTIF($F$2:$F$46,L40)=0,COUNTIFS($F$2:$F$46,L40,$Q$2:$Q$46,"Aprobada")>0)),L40&" ","")&IF(NOT(OR(M40="",COUNTIF($F$2:$F$46,M40)=0,COUNTIFS($F$2:$F$46,M40,$Q$2:$Q$46,"Aprobada")>0)),M40&" ","")&IF(NOT(OR(N40="",COUNTIF($F$2:$F$46,N40)=0,COUNTIFS($F$2:$F$46,N40,$Q$2:$Q$46,"Aprobada")>0)),N40&" ","")&IF(NOT(OR(O40="",COUNTIF($F$2:$F$46,O40)=0,COUNTIFS($F$2:$F$46,O40,$Q$2:$Q$46,"Aprobada")>0)),O40&" ","")&IF(NOT(OR(P40="",COUNTIF($F$2:$F$46,P40)=0,COUNTIFS($F$2:$F$46,P40,$Q$2:$Q$46,"Aprobada")>0)),P40&" ","")),IF(Q40="Cursada aprobada",TRIM(IF(NOT(OR(L40="",COUNTIF($F$2:$F$46,L40)=0,COUNTIFS($F$2:$F$46,L40,$Q$2:$Q$46,"Aprobada")>0,AND(Resumen!$B$15="La cursada aprobada",COUNTIFS($F$2:$F$46,L40,$Q$2:$Q$46,"Cursada aprobada")>0))),L40&" ","")&IF(NOT(OR(M40="",COUNTIF($F$2:$F$46,M40)=0,COUNTIFS($F$2:$F$46,M40,$Q$2:$Q$46,"Aprobada")>0,AND(Resumen!$B$15="La cursada aprobada",COUNTIFS($F$2:$F$46,M40,$Q$2:$Q$46,"Cursada aprobada")>0))),M40&" ","")&IF(NOT(OR(N40="",COUNTIF($F$2:$F$46,N40)=0,COUNTIFS($F$2:$F$46,N40,$Q$2:$Q$46,"Aprobada")>0,AND(Resumen!$B$15="La cursada aprobada",COUNTIFS($F$2:$F$46,N40,$Q$2:$Q$46,"Cursada aprobada")>0))),N40&" ","")&IF(NOT(OR(O40="",COUNTIF($F$2:$F$46,O40)=0,COUNTIFS($F$2:$F$46,O40,$Q$2:$Q$46,"Aprobada")>0,AND(Resumen!$B$15="La cursada aprobada",COUNTIFS($F$2:$F$46,O40,$Q$2:$Q$46,"Cursada aprobada")>0))),O40&" ","")&IF(NOT(OR(P40="",COUNTIF($F$2:$F$46,P40)=0,COUNTIFS($F$2:$F$46,P40,$Q$2:$Q$46,"Aprobada")>0,AND(Resumen!$B$15="La cursada aprobada",COUNTIFS($F$2:$F$46,P40,$Q$2:$Q$46,"Cursada aprobada")>0))),P40&" ","")),""))
A41: Requisitos instrumentales | E41: SA | F41: 595 | G41: Nivel de Inglés Técnico I | Q41: No cursada | R41: =IF(Q41="Aprobada","Ya aprobada",IF(Q41="Cursada aprobada","Ya cursada",IF(AND(OR(L41="",COUNTIF($F$2:$F$46,L41)=0,COUNTIFS($F$2:$F$46,L41,$Q$2:$Q$46,"Aprobada")>0,AND(Resumen!$B$15="La cursada aprobada",COUNTIFS($F$2:$F$46,L41,$Q$2:$Q$46,"Cursada aprobada")>0)),OR(M41="",COUNTIF($F$2:$F$46,M41)=0,COUNTIFS($F$2:$F$46,M41,$Q$2:$Q$46,"Aprobada")>0,AND(Resumen!$B$15="La cursada aprobada",COUNTIFS($F$2:$F$46,M41,$Q$2:$Q$46,"Cursada aprobada")>0)),OR(N41="",COUNTIF($F$2:$F$46,N41)=0,COUNTIFS($F$2:$F$46,N41,$Q$2:$Q$46,"Aprobada")>0,AND(Resumen!$B$15="La cursada aprobada",COUNTIFS($F$2:$F$46,N41,$Q$2:$Q$46,"Cursada aprobada")>0)),OR(O41="",COUNTIF($F$2:$F$46,O41)=0,COUNTIFS($F$2:$F$46,O41,$Q$2:$Q$46,"Aprobada")>0,AND(Resumen!$B$15="La cursada aprobada",COUNTIFS($F$2:$F$46,O41,$Q$2:$Q$46,"Cursada aprobada")>0)),OR(P41="",COUNTIF($F$2:$F$46,P41)=0,COUNTIFS($F$2:$F$46,P41,$Q$2:$Q$46,"Aprobada")>0,AND(Resumen!$B$15="La cursada aprobada",COUNTIFS($F$2:$F$46,P41,$Q$2:$Q$46,"Cursada aprobada")>0))),"Sí","No"))) -> Sí | S41: =TRIM(IF(NOT(OR(L41="",COUNTIF($F$2:$F$46,L41)=0,COUNTIFS($F$2:$F$46,L41,$Q$2:$Q$46,"Aprobada")>0,AND(Resumen!$B$15="La cursada aprobada",COUNTIFS($F$2:$F$46,L41,$Q$2:$Q$46,"Cursada aprobada")>0))),L41&" ","")&IF(NOT(OR(M41="",COUNTIF($F$2:$F$46,M41)=0,COUNTIFS($F$2:$F$46,M41,$Q$2:$Q$46,"Aprobada")>0,AND(Resumen!$B$15="La cursada aprobada",COUNTIFS($F$2:$F$46,M41,$Q$2:$Q$46,"Cursada aprobada")>0))),M41&" ","")&IF(NOT(OR(N41="",COUNTIF($F$2:$F$46,N41)=0,COUNTIFS($F$2:$F$46,N41,$Q$2:$Q$46,"Aprobada")>0,AND(Resumen!$B$15="La cursada aprobada",COUNTIFS($F$2:$F$46,N41,$Q$2:$Q$46,"Cursada aprobada")>0))),N41&" ","")&IF(NOT(OR(O41="",COUNTIF($F$2:$F$46,O41)=0,COUNTIFS($F$2:$F$46,O41,$Q$2:$Q$46,"Aprobada")>0,AND(Resumen!$B$15="La cursada aprobada",COUNTIFS($F$2:$F$46,O41,$Q$2:$Q$46,"Cursada aprobada")>0))),O41&" ","")&IF(NOT(OR(P41="",COUNTIF($F$2:$F$46,P41)=0,COUNTIFS($F$2:$F$46,P41,$Q$2:$Q$46,"Aprobada")>0,AND(Resumen!$B$15="La cursada aprobada",COUNTIFS($F$2:$F$46,P41,$Q$2:$Q$46,"Cursada aprobada")>0))),P41&" ","")) | T41: =IF(Q41="Cursada aprobada",IF(AND(OR(L41="",COUNTIF($F$2:$F$46,L41)=0,COUNTIFS($F$2:$F$46,L41,$Q$2:$Q$46,"Aprobada")>0),OR(M41="",COUNTIF($F$2:$F$46,M41)=0,COUNTIFS($F$2:$F$46,M41,$Q$2:$Q$46,"Aprobada")>0),OR(N41="",COUNTIF($F$2:$F$46,N41)=0,COUNTIFS($F$2:$F$46,N41,$Q$2:$Q$46,"Aprobada")>0),OR(O41="",COUNTIF($F$2:$F$46,O41)=0,COUNTIFS($F$2:$F$46,O41,$Q$2:$Q$46,"Aprobada")>0),OR(P41="",COUNTIF($F$2:$F$46,P41)=0,COUNTIFS($F$2:$F$46,P41,$Q$2:$Q$46,"Aprobada")>0)),"Sí","No"),"") | U41: =IF(Q41="Aprobada",TRIM(IF(NOT(OR(L41="",COUNTIF($F$2:$F$46,L41)=0,COUNTIFS($F$2:$F$46,L41,$Q$2:$Q$46,"Aprobada")>0)),L41&" ","")&IF(NOT(OR(M41="",COUNTIF($F$2:$F$46,M41)=0,COUNTIFS($F$2:$F$46,M41,$Q$2:$Q$46,"Aprobada")>0)),M41&" ","")&IF(NOT(OR(N41="",COUNTIF($F$2:$F$46,N41)=0,COUNTIFS($F$2:$F$46,N41,$Q$2:$Q$46,"Aprobada")>0)),N41&" ","")&IF(NOT(OR(O41="",COUNTIF($F$2:$F$46,O41)=0,COUNTIFS($F$2:$F$46,O41,$Q$2:$Q$46,"Aprobada")>0)),O41&" ","")&IF(NOT(OR(P41="",COUNTIF($F$2:$F$46,P41)=0,COUNTIFS($F$2:$F$46,P41,$Q$2:$Q$46,"Aprobada")>0)),P41&" ","")),IF(Q41="Cursada aprobada",TRIM(IF(NOT(OR(L41="",COUNTIF($F$2:$F$46,L41)=0,COUNTIFS($F$2:$F$46,L41,$Q$2:$Q$46,"Aprobada")>0,AND(Resumen!$B$15="La cursada aprobada",COUNTIFS($F$2:$F$46,L41,$Q$2:$Q$46,"Cursada aprobada")>0))),L41&" ","")&IF(NOT(OR(M41="",COUNTIF($F$2:$F$46,M41)=0,COUNTIFS($F$2:$F$46,M41,$Q$2:$Q$46,"Aprobada")>0,AND(Resumen!$B$15="La cursada aprobada",COUNTIFS($F$2:$F$46,M41,$Q$2:$Q$46,"Cursada aprobada")>0))),M41&" ","")&IF(NOT(OR(N41="",COUNTIF($F$2:$F$46,N41)=0,COUNTIFS($F$2:$F$46,N41,$Q$2:$Q$46,"Aprobada")>0,AND(Resumen!$B$15="La cursada aprobada",COUNTIFS($F$2:$F$46,N41,$Q$2:$Q$46,"Cursada aprobada")>0))),N41&" ","")&IF(NOT(OR(O41="",COUNTIF($F$2:$F$46,O41)=0,COUNTIFS($F$2:$F$46,O41,$Q$2:$Q$46,"Aprobada")>0,AND(Resumen!$B$15="La cursada aprobada",COUNTIFS($F$2:$F$46,O41,$Q$2:$Q$46,"Cursada aprobada")>0))),O41&" ","")&IF(NOT(OR(P41="",COUNTIF($F$2:$F$46,P41)=0,COUNTIFS($F$2:$F$46,P41,$Q$2:$Q$46,"Aprobada")>0,AND(Resumen!$B$15="La cursada aprobada",COUNTIFS($F$2:$F$46,P41,$Q$2:$Q$46,"Cursada aprobada")>0))),P41&" ","")),""))
A42: Requisitos instrumentales | E42: AD | F42: 300 | G42: Nivel de Computación | Q42: No cursada | R42: =IF(Q42="Aprobada","Ya aprobada",IF(Q42="Cursada aprobada","Ya cursada",IF(AND(OR(L42="",COUNTIF($F$2:$F$46,L42)=0,COUNTIFS($F$2:$F$46,L42,$Q$2:$Q$46,"Aprobada")>0,AND(Resumen!$B$15="La cursada aprobada",COUNTIFS($F$2:$F$46,L42,$Q$2:$Q$46,"Cursada aprobada")>0)),OR(M42="",COUNTIF($F$2:$F$46,M42)=0,COUNTIFS($F$2:$F$46,M42,$Q$2:$Q$46,"Aprobada")>0,AND(Resumen!$B$15="La cursada aprobada",COUNTIFS($F$2:$F$46,M42,$Q$2:$Q$46,"Cursada aprobada")>0)),OR(N42="",COUNTIF($F$2:$F$46,N42)=0,COUNTIFS($F$2:$F$46,N42,$Q$2:$Q$46,"Aprobada")>0,AND(Resumen!$B$15="La cursada aprobada",COUNTIFS($F$2:$F$46,N42,$Q$2:$Q$46,"Cursada aprobada")>0)),OR(O42="",COUNTIF($F$2:$F$46,O42)=0,COUNTIFS($F$2:$F$46,O42,$Q$2:$Q$46,"Aprobada")>0,AND(Resumen!$B$15="La cursada aprobada",COUNTIFS($F$2:$F$46,O42,$Q$2:$Q$46,"Cursada aprobada")>0)),OR(P42="",COUNTIF($F$2:$F$46,P42)=0,COUNTIFS($F$2:$F$46,P42,$Q$2:$Q$46,"Aprobada")>0,AND(Resumen!$B$15="La cursada aprobada",COUNTIFS($F$2:$F$46,P42,$Q$2:$Q$46,"Cursada aprobada")>0))),"Sí","No"))) -> Sí | S42: =TRIM(IF(NOT(OR(L42="",COUNTIF($F$2:$F$46,L42)=0,COUNTIFS($F$2:$F$46,L42,$Q$2:$Q$46,"Aprobada")>0,AND(Resumen!$B$15="La cursada aprobada",COUNTIFS($F$2:$F$46,L42,$Q$2:$Q$46,"Cursada aprobada")>0))),L42&" ","")&IF(NOT(OR(M42="",COUNTIF($F$2:$F$46,M42)=0,COUNTIFS($F$2:$F$46,M42,$Q$2:$Q$46,"Aprobada")>0,AND(Resumen!$B$15="La cursada aprobada",COUNTIFS($F$2:$F$46,M42,$Q$2:$Q$46,"Cursada aprobada")>0))),M42&" ","")&IF(NOT(OR(N42="",COUNTIF($F$2:$F$46,N42)=0,COUNTIFS($F$2:$F$46,N42,$Q$2:$Q$46,"Aprobada")>0,AND(Resumen!$B$15="La cursada aprobada",COUNTIFS($F$2:$F$46,N42,$Q$2:$Q$46,"Cursada aprobada")>0))),N42&" ","")&IF(NOT(OR(O42="",COUNTIF($F$2:$F$46,O42)=0,COUNTIFS($F$2:$F$46,O42,$Q$2:$Q$46,"Aprobada")>0,AND(Resumen!$B$15="La cursada aprobada",COUNTIFS($F$2:$F$46,O42,$Q$2:$Q$46,"Cursada aprobada")>0))),O42&" ","")&IF(NOT(OR(P42="",COUNTIF($F$2:$F$46,P42)=0,COUNTIFS($F$2:$F$46,P42,$Q$2:$Q$46,"Aprobada")>0,AND(Resumen!$B$15="La cursada aprobada",COUNTIFS($F$2:$F$46,P42,$Q$2:$Q$46,"Cursada aprobada")>0))),P42&" ","")) | T42: =IF(Q42="Cursada aprobada",IF(AND(OR(L42="",COUNTIF($F$2:$F$46,L42)=0,COUNTIFS($F$2:$F$46,L42,$Q$2:$Q$46,"Aprobada")>0),OR(M42="",COUNTIF($F$2:$F$46,M42)=0,COUNTIFS($F$2:$F$46,M42,$Q$2:$Q$46,"Aprobada")>0),OR(N42="",COUNTIF($F$2:$F$46,N42)=0,COUNTIFS($F$2:$F$46,N42,$Q$2:$Q$46,"Aprobada")>0),OR(O42="",COUNTIF($F$2:$F$46,O42)=0,COUNTIFS($F$2:$F$46,O42,$Q$2:$Q$46,"Aprobada")>0),OR(P42="",COUNTIF($F$2:$F$46,P42)=0,COUNTIFS($F$2:$F$46,P42,$Q$2:$Q$46,"Aprobada")>0)),"Sí","No"),"") | U42: =IF(Q42="Aprobada",TRIM(IF(NOT(OR(L42="",COUNTIF($F$2:$F$46,L42)=0,COUNTIFS($F$2:$F$46,L42,$Q$2:$Q$46,"Aprobada")>0)),L42&" ","")&IF(NOT(OR(M42="",COUNTIF($F$2:$F$46,M42)=0,COUNTIFS($F$2:$F$46,M42,$Q$2:$Q$46,"Aprobada")>0)),M42&" ","")&IF(NOT(OR(N42="",COUNTIF($F$2:$F$46,N42)=0,COUNTIFS($F$2:$F$46,N42,$Q$2:$Q$46,"Aprobada")>0)),N42&" ","")&IF(NOT(OR(O42="",COUNTIF($F$2:$F$46,O42)=0,COUNTIFS($F$2:$F$46,O42,$Q$2:$Q$46,"Aprobada")>0)),O42&" ","")&IF(NOT(OR(P42="",COUNTIF($F$2:$F$46,P42)=0,COUNTIFS($F$2:$F$46,P42,$Q$2:$Q$46,"Aprobada")>0)),P42&" ","")),IF(Q42="Cursada aprobada",TRIM(IF(NOT(OR(L42="",COUNTIF($F$2:$F$46,L42)=0,COUNTIFS($F$2:$F$46,L42,$Q$2:$Q$46,"Aprobada")>0,AND(Resumen!$B$15="La cursada aprobada",COUNTIFS($F$2:$F$46,L42,$Q$2:$Q$46,"Cursada aprobada")>0))),L42&" ","")&IF(NOT(OR(M42="",COUNTIF($F$2:$F$46,M42)=0,COUNTIFS($F$2:$F$46,M42,$Q$2:$Q$46,"Aprobada")>0,AND(Resumen!$B$15="La cursada aprobada",COUNTIFS($F$2:$F$46,M42,$Q$2:$Q$46,"Cursada aprobada")>0))),M42&" ","")&IF(NOT(OR(N42="",COUNTIF($F$2:$F$46,N42)=0,COUNTIFS($F$2:$F$46,N42,$Q$2:$Q$46,"Aprobada")>0,AND(Resumen!$B$15="La cursada aprobada",COUNTIFS($F$2:$F$46,N42,$Q$2:$Q$46,"Cursada aprobada")>0))),N42&" ","")&IF(NOT(OR(O42="",COUNTIF($F$2:$F$46,O42)=0,COUNTIFS($F$2:$F$46,O42,$Q$2:$Q$46,"Aprobada")>0,AND(Resumen!$B$15="La cursada aprobada",COUNTIFS($F$2:$F$46,O42,$Q$2:$Q$46,"Cursada aprobada")>0))),O42&" ","")&IF(NOT(OR(P42="",COUNTIF($F$2:$F$46,P42)=0,COUNTIFS($F$2:$F$46,P42,$Q$2:$Q$46,"Aprobada")>0,AND(Resumen!$B$15="La cursada aprobada",COUNTIFS($F$2:$F$46,P42,$Q$2:$Q$46,"Cursada aprobada")>0))),P42&" ","")),""))
A43: Requisitos instrumentales | E43: SA | F43: 299 | G43: Taller Uso de Programas de Computación | Q43: No cursada | R43: =IF(Q43="Aprobada","Ya aprobada",IF(Q43="Cursada aprobada","Ya cursada",IF(AND(OR(L43="",COUNTIF($F$2:$F$46,L43)=0,COUNTIFS($F$2:$F$46,L43,$Q$2:$Q$46,"Aprobada")>0,AND(Resumen!$B$15="La cursada aprobada",COUNTIFS($F$2:$F$46,L43,$Q$2:$Q$46,"Cursada aprobada")>0)),OR(M43="",COUNTIF($F$2:$F$46,M43)=0,COUNTIFS($F$2:$F$46,M43,$Q$2:$Q$46,"Aprobada")>0,AND(Resumen!$B$15="La cursada aprobada",COUNTIFS($F$2:$F$46,M43,$Q$2:$Q$46,"Cursada aprobada")>0)),OR(N43="",COUNTIF($F$2:$F$46,N43)=0,COUNTIFS($F$2:$F$46,N43,$Q$2:$Q$46,"Aprobada")>0,AND(Resumen!$B$15="La cursada aprobada",COUNTIFS($F$2:$F$46,N43,$Q$2:$Q$46,"Cursada aprobada")>0)),OR(O43="",COUNTIF($F$2:$F$46,O43)=0,COUNTIFS($F$2:$F$46,O43,$Q$2:$Q$46,"Aprobada")>0,AND(Resumen!$B$15="La cursada aprobada",COUNTIFS($F$2:$F$46,O43,$Q$2:$Q$46,"Cursada aprobada")>0)),OR(P43="",COUNTIF($F$2:$F$46,P43)=0,COUNTIFS($F$2:$F$46,P43,$Q$2:$Q$46,"Aprobada")>0,AND(Resumen!$B$15="La cursada aprobada",COUNTIFS($F$2:$F$46,P43,$Q$2:$Q$46,"Cursada aprobada")>0))),"Sí","No"))) -> Sí | S43: =TRIM(IF(NOT(OR(L43="",COUNTIF($F$2:$F$46,L43)=0,COUNTIFS($F$2:$F$46,L43,$Q$2:$Q$46,"Aprobada")>0,AND(Resumen!$B$15="La cursada aprobada",COUNTIFS($F$2:$F$46,L43,$Q$2:$Q$46,"Cursada aprobada")>0))),L43&" ","")&IF(NOT(OR(M43="",COUNTIF($F$2:$F$46,M43)=0,COUNTIFS($F$2:$F$46,M43,$Q$2:$Q$46,"Aprobada")>0,AND(Resumen!$B$15="La cursada aprobada",COUNTIFS($F$2:$F$46,M43,$Q$2:$Q$46,"Cursada aprobada")>0))),M43&" ","")&IF(NOT(OR(N43="",COUNTIF($F$2:$F$46,N43)=0,COUNTIFS($F$2:$F$46,N43,$Q$2:$Q$46,"Aprobada")>0,AND(Resumen!$B$15="La cursada aprobada",COUNTIFS($F$2:$F$46,N43,$Q$2:$Q$46,"Cursada aprobada")>0))),N43&" ","")&IF(NOT(OR(O43="",COUNTIF($F$2:$F$46,O43)=0,COUNTIFS($F$2:$F$46,O43,$Q$2:$Q$46,"Aprobada")>0,AND(Resumen!$B$15="La cursada aprobada",COUNTIFS($F$2:$F$46,O43,$Q$2:$Q$46,"Cursada aprobada")>0))),O43&" ","")&IF(NOT(OR(P43="",COUNTIF($F$2:$F$46,P43)=0,COUNTIFS($F$2:$F$46,P43,$Q$2:$Q$46,"Aprobada")>0,AND(Resumen!$B$15="La cursada aprobada",COUNTIFS($F$2:$F$46,P43,$Q$2:$Q$46,"Cursada aprobada")>0))),P43&" ","")) | T43: =IF(Q43="Cursada aprobada",IF(AND(OR(L43="",COUNTIF($F$2:$F$46,L43)=0,COUNTIFS($F$2:$F$46,L43,$Q$2:$Q$46,"Aprobada")>0),OR(M43="",COUNTIF($F$2:$F$46,M43)=0,COUNTIFS($F$2:$F$46,M43,$Q$2:$Q$46,"Aprobada")>0),OR(N43="",COUNTIF($F$2:$F$46,N43)=0,COUNTIFS($F$2:$F$46,N43,$Q$2:$Q$46,"Aprobada")>0),OR(O43="",COUNTIF($F$2:$F$46,O43)=0,COUNTIFS($F$2:$F$46,O43,$Q$2:$Q$46,"Aprobada")>0),OR(P43="",COUNTIF($F$2:$F$46,P43)=0,COUNTIFS($F$2:$F$46,P43,$Q$2:$Q$46,"Aprobada")>0)),"Sí","No"),"") | U43: =IF(Q43="Aprobada",TRIM(IF(NOT(OR(L43="",COUNTIF($F$2:$F$46,L43)=0,COUNTIFS($F$2:$F$46,L43,$Q$2:$Q$46,"Aprobada")>0)),L43&" ","")&IF(NOT(OR(M43="",COUNTIF($F$2:$F$46,M43)=0,COUNTIFS($F$2:$F$46,M43,$Q$2:$Q$46,"Aprobada")>0)),M43&" ","")&IF(NOT(OR(N43="",COUNTIF($F$2:$F$46,N43)=0,COUNTIFS($F$2:$F$46,N43,$Q$2:$Q$46,"Aprobada")>0)),N43&" ","")&IF(NOT(OR(O43="",COUNTIF($F$2:$F$46,O43)=0,COUNTIFS($F$2:$F$46,O43,$Q$2:$Q$46,"Aprobada")>0)),O43&" ","")&IF(NOT(OR(P43="",COUNTIF($F$2:$F$46,P43)=0,COUNTIFS($F$2:$F$46,P43,$Q$2:$Q$46,"Aprobada")>0)),P43&" ","")),IF(Q43="Cursada aprobada",TRIM(IF(NOT(OR(L43="",COUNTIF($F$2:$F$46,L43)=0,COUNTIFS($F$2:$F$46,L43,$Q$2:$Q$46,"Aprobada")>0,AND(Resumen!$B$15="La cursada aprobada",COUNTIFS($F$2:$F$46,L43,$Q$2:$Q$46,"Cursada aprobada")>0))),L43&" ","")&IF(NOT(OR(M43="",COUNTIF($F$2:$F$46,M43)=0,COUNTIFS($F$2:$F$46,M43,$Q$2:$Q$46,"Aprobada")>0,AND(Resumen!$B$15="La cursada aprobada",COUNTIFS($F$2:$F$46,M43,$Q$2:$Q$46,"Cursada aprobada")>0))),M43&" ","")&IF(NOT(OR(N43="",COUNTIF($F$2:$F$46,N43)=0,COUNTIFS($F$2:$F$46,N43,$Q$2:$Q$46,"Aprobada")>0,AND(Resumen!$B$15="La cursada aprobada",COUNTIFS($F$2:$F$46,N43,$Q$2:$Q$46,"Cursada aprobada")>0))),N43&" ","")&IF(NOT(OR(O43="",COUNTIF($F$2:$F$46,O43)=0,COUNTIFS($F$2:$F$46,O43,$Q$2:$Q$46,"Aprobada")>0,AND(Resumen!$B$15="La cursada aprobada",COUNTIFS($F$2:$F$46,O43,$Q$2:$Q$46,"Cursada aprobada")>0))),O43&" ","")&IF(NOT(OR(P43="",COUNTIF($F$2:$F$46,P43)=0,COUNTIFS($F$2:$F$46,P43,$Q$2:$Q$46,"Aprobada")>0,AND(Resumen!$B$15="La cursada aprobada",COUNTIFS($F$2:$F$46,P43,$Q$2:$Q$46,"Cursada aprobada")>0))),P43&" ","")),""))
A44: Requisitos instrumentales | E44: SI | F44: 296 | G44: Acreditar 30 horas de Investigación | Q44: No cursada | R44: =IF(Q44="Aprobada","Ya aprobada",IF(Q44="Cursada aprobada","Ya cursada",IF(AND(OR(L44="",COUNTIF($F$2:$F$46,L44)=0,COUNTIFS($F$2:$F$46,L44,$Q$2:$Q$46,"Aprobada")>0,AND(Resumen!$B$15="La cursada aprobada",COUNTIFS($F$2:$F$46,L44,$Q$2:$Q$46,"Cursada aprobada")>0)),OR(M44="",COUNTIF($F$2:$F$46,M44)=0,COUNTIFS($F$2:$F$46,M44,$Q$2:$Q$46,"Aprobada")>0,AND(Resumen!$B$15="La cursada aprobada",COUNTIFS($F$2:$F$46,M44,$Q$2:$Q$46,"Cursada aprobada")>0)),OR(N44="",COUNTIF($F$2:$F$46,N44)=0,COUNTIFS($F$2:$F$46,N44,$Q$2:$Q$46,"Aprobada")>0,AND(Resumen!$B$15="La cursada aprobada",COUNTIFS($F$2:$F$46,N44,$Q$2:$Q$46,"Cursada aprobada")>0)),OR(O44="",COUNTIF($F$2:$F$46,O44)=0,COUNTIFS($F$2:$F$46,O44,$Q$2:$Q$46,"Aprobada")>0,AND(Resumen!$B$15="La cursada aprobada",COUNTIFS($F$2:$F$46,O44,$Q$2:$Q$46,"Cursada aprobada")>0)),OR(P44="",COUNTIF($F$2:$F$46,P44)=0,COUNTIFS($F$2:$F$46,P44,$Q$2:$Q$46,"Aprobada")>0,AND(Resumen!$B$15="La cursada aprobada",COUNTIFS($F$2:$F$46,P44,$Q$2:$Q$46,"Cursada aprobada")>0))),"Sí","No"))) -> Sí | S44: =TRIM(IF(NOT(OR(L44="",COUNTIF($F$2:$F$46,L44)=0,COUNTIFS($F$2:$F$46,L44,$Q$2:$Q$46,"Aprobada")>0,AND(Resumen!$B$15="La cursada aprobada",COUNTIFS($F$2:$F$46,L44,$Q$2:$Q$46,"Cursada aprobada")>0))),L44&" ","")&IF(NOT(OR(M44="",COUNTIF($F$2:$F$46,M44)=0,COUNTIFS($F$2:$F$46,M44,$Q$2:$Q$46,"Aprobada")>0,AND(Resumen!$B$15="La cursada aprobada",COUNTIFS($F$2:$F$46,M44,$Q$2:$Q$46,"Cursada aprobada")>0))),M44&" ","")&IF(NOT(OR(N44="",COUNTIF($F$2:$F$46,N44)=0,COUNTIFS($F$2:$F$46,N44,$Q$2:$Q$46,"Aprobada")>0,AND(Resumen!$B$15="La cursada aprobada",COUNTIFS($F$2:$F$46,N44,$Q$2:$Q$46,"Cursada aprobada")>0))),N44&" ","")&IF(NOT(OR(O44="",COUNTIF($F$2:$F$46,O44)=0,COUNTIFS($F$2:$F$46,O44,$Q$2:$Q$46,"Aprobada")>0,AND(Resumen!$B$15="La cursada aprobada",COUNTIFS($F$2:$F$46,O44,$Q$2:$Q$46,"Cursada aprobada")>0))),O44&" ","")&IF(NOT(OR(P44="",COUNTIF($F$2:$F$46,P44)=0,COUNTIFS($F$2:$F$46,P44,$Q$2:$Q$46,"Aprobada")>0,AND(Resumen!$B$15="La cursada aprobada",COUNTIFS($F$2:$F$46,P44,$Q$2:$Q$46,"Cursada aprobada")>0))),P44&" ","")) | T44: =IF(Q44="Cursada aprobada",IF(AND(OR(L44="",COUNTIF($F$2:$F$46,L44)=0,COUNTIFS($F$2:$F$46,L44,$Q$2:$Q$46,"Aprobada")>0),OR(M44="",COUNTIF($F$2:$F$46,M44)=0,COUNTIFS($F$2:$F$46,M44,$Q$2:$Q$46,"Aprobada")>0),OR(N44="",COUNTIF($F$2:$F$46,N44)=0,COUNTIFS($F$2:$F$46,N44,$Q$2:$Q$46,"Aprobada")>0),OR(O44="",COUNTIF($F$2:$F$46,O44)=0,COUNTIFS($F$2:$F$46,O44,$Q$2:$Q$46,"Aprobada")>0),OR(P44="",COUNTIF($F$2:$F$46,P44)=0,COUNTIFS($F$2:$F$46,P44,$Q$2:$Q$46,"Aprobada")>0)),"Sí","No"),"") | U44: =IF(Q44="Aprobada",TRIM(IF(NOT(OR(L44="",COUNTIF($F$2:$F$46,L44)=0,COUNTIFS($F$2:$F$46,L44,$Q$2:$Q$46,"Aprobada")>0)),L44&" ","")&IF(NOT(OR(M44="",COUNTIF($F$2:$F$46,M44)=0,COUNTIFS($F$2:$F$46,M44,$Q$2:$Q$46,"Aprobada")>0)),M44&" ","")&IF(NOT(OR(N44="",COUNTIF($F$2:$F$46,N44)=0,COUNTIFS($F$2:$F$46,N44,$Q$2:$Q$46,"Aprobada")>0)),N44&" ","")&IF(NOT(OR(O44="",COUNTIF($F$2:$F$46,O44)=0,COUNTIFS($F$2:$F$46,O44,$Q$2:$Q$46,"Aprobada")>0)),O44&" ","")&IF(NOT(OR(P44="",COUNTIF($F$2:$F$46,P44)=0,COUNTIFS($F$2:$F$46,P44,$Q$2:$Q$46,"Aprobada")>0)),P44&" ","")),IF(Q44="Cursada aprobada",TRIM(IF(NOT(OR(L44="",COUNTIF($F$2:$F$46,L44)=0,COUNTIFS($F$2:$F$46,L44,$Q$2:$Q$46,"Aprobada")>0,AND(Resumen!$B$15="La cursada aprobada",COUNTIFS($F$2:$F$46,L44,$Q$2:$Q$46,"Cursada aprobada")>0))),L44&" ","")&IF(NOT(OR(M44="",COUNTIF($F$2:$F$46,M44)=0,COUNTIFS($F$2:$F$46,M44,$Q$2:$Q$46,"Aprobada")>0,AND(Resumen!$B$15="La cursada aprobada",COUNTIFS($F$2:$F$46,M44,$Q$2:$Q$46,"Cursada aprobada")>0))),M44&" ","")&IF(NOT(OR(N44="",COUNTIF($F$2:$F$46,N44)=0,COUNTIFS($F$2:$F$46,N44,$Q$2:$Q$46,"Aprobada")>0,AND(Resumen!$B$15="La cursada aprobada",COUNTIFS($F$2:$F$46,N44,$Q$2:$Q$46,"Cursada aprobada")>0))),N44&" ","")&IF(NOT(OR(O44="",COUNTIF($F$2:$F$46,O44)=0,COUNTIFS($F$2:$F$46,O44,$Q$2:$Q$46,"Aprobada")>0,AND(Resumen!$B$15="La cursada aprobada",COUNTIFS($F$2:$F$46,O44,$Q$2:$Q$46,"Cursada aprobada")>0))),O44&" ","")&IF(NOT(OR(P44="",COUNTIF($F$2:$F$46,P44)=0,COUNTIFS($F$2:$F$46,P44,$Q$2:$Q$46,"Aprobada")>0,AND(Resumen!$B$15="La cursada aprobada",COUNTIFS($F$2:$F$46,P44,$Q$2:$Q$46,"Cursada aprobada")>0))),P44&" ","")),""))
A45: Requisitos instrumentales | E45: SE | F45: 368 | G45: Seminario de Práctica Sociocomunitaria | Q45: No cursada | R45: =IF(Q45="Aprobada","Ya aprobada",IF(Q45="Cursada aprobada","Ya cursada",IF(AND(OR(L45="",COUNTIF($F$2:$F$46,L45)=0,COUNTIFS($F$2:$F$46,L45,$Q$2:$Q$46,"Aprobada")>0,AND(Resumen!$B$15="La cursada aprobada",COUNTIFS($F$2:$F$46,L45,$Q$2:$Q$46,"Cursada aprobada")>0)),OR(M45="",COUNTIF($F$2:$F$46,M45)=0,COUNTIFS($F$2:$F$46,M45,$Q$2:$Q$46,"Aprobada")>0,AND(Resumen!$B$15="La cursada aprobada",COUNTIFS($F$2:$F$46,M45,$Q$2:$Q$46,"Cursada aprobada")>0)),OR(N45="",COUNTIF($F$2:$F$46,N45)=0,COUNTIFS($F$2:$F$46,N45,$Q$2:$Q$46,"Aprobada")>0,AND(Resumen!$B$15="La cursada aprobada",COUNTIFS($F$2:$F$46,N45,$Q$2:$Q$46,"Cursada aprobada")>0)),OR(O45="",COUNTIF($F$2:$F$46,O45)=0,COUNTIFS($F$2:$F$46,O45,$Q$2:$Q$46,"Aprobada")>0,AND(Resumen!$B$15="La cursada aprobada",COUNTIFS($F$2:$F$46,O45,$Q$2:$Q$46,"Cursada aprobada")>0)),OR(P45="",COUNTIF($F$2:$F$46,P45)=0,COUNTIFS($F$2:$F$46,P45,$Q$2:$Q$46,"Aprobada")>0,AND(Resumen!$B$15="La cursada aprobada",COUNTIFS($F$2:$F$46,P45,$Q$2:$Q$46,"Cursada aprobada")>0))),"Sí","No"))) -> Sí | S45: =TRIM(IF(NOT(OR(L45="",COUNTIF($F$2:$F$46,L45)=0,COUNTIFS($F$2:$F$46,L45,$Q$2:$Q$46,"Aprobada")>0,AND(Resumen!$B$15="La cursada aprobada",COUNTIFS($F$2:$F$46,L45,$Q$2:$Q$46,"Cursada aprobada")>0))),L45&" ","")&IF(NOT(OR(M45="",COUNTIF($F$2:$F$46,M45)=0,COUNTIFS($F$2:$F$46,M45,$Q$2:$Q$46,"Aprobada")>0,AND(Resumen!$B$15="La cursada aprobada",COUNTIFS($F$2:$F$46,M45,$Q$2:$Q$46,"Cursada aprobada")>0))),M45&" ","")&IF(NOT(OR(N45="",COUNTIF($F$2:$F$46,N45)=0,COUNTIFS($F$2:$F$46,N45,$Q$2:$Q$46,"Aprobada")>0,AND(Resumen!$B$15="La cursada aprobada",COUNTIFS($F$2:$F$46,N45,$Q$2:$Q$46,"Cursada aprobada")>0))),N45&" ","")&IF(NOT(OR(O45="",COUNTIF($F$2:$F$46,O45)=0,COUNTIFS($F$2:$F$46,O45,$Q$2:$Q$46,"Aprobada")>0,AND(Resumen!$B$15="La cursada aprobada",COUNTIFS($F$2:$F$46,O45,$Q$2:$Q$46,"Cursada aprobada")>0))),O45&" ","")&IF(NOT(OR(P45="",COUNTIF($F$2:$F$46,P45)=0,COUNTIFS($F$2:$F$46,P45,$Q$2:$Q$46,"Aprobada")>0,AND(Resumen!$B$15="La cursada aprobada",COUNTIFS($F$2:$F$46,P45,$Q$2:$Q$46,"Cursada aprobada")>0))),P45&" ","")) | T45: =IF(Q45="Cursada aprobada",IF(AND(OR(L45="",COUNTIF($F$2:$F$46,L45)=0,COUNTIFS($F$2:$F$46,L45,$Q$2:$Q$46,"Aprobada")>0),OR(M45="",COUNTIF($F$2:$F$46,M45)=0,COUNTIFS($F$2:$F$46,M45,$Q$2:$Q$46,"Aprobada")>0),OR(N45="",COUNTIF($F$2:$F$46,N45)=0,COUNTIFS($F$2:$F$46,N45,$Q$2:$Q$46,"Aprobada")>0),OR(O45="",COUNTIF($F$2:$F$46,O45)=0,COUNTIFS($F$2:$F$46,O45,$Q$2:$Q$46,"Aprobada")>0),OR(P45="",COUNTIF($F$2:$F$46,P45)=0,COUNTIFS($F$2:$F$46,P45,$Q$2:$Q$46,"Aprobada")>0)),"Sí","No"),"") | U45: =IF(Q45="Aprobada",TRIM(IF(NOT(OR(L45="",COUNTIF($F$2:$F$46,L45)=0,COUNTIFS($F$2:$F$46,L45,$Q$2:$Q$46,"Aprobada")>0)),L45&" ","")&IF(NOT(OR(M45="",COUNTIF($F$2:$F$46,M45)=0,COUNTIFS($F$2:$F$46,M45,$Q$2:$Q$46,"Aprobada")>0)),M45&" ","")&IF(NOT(OR(N45="",COUNTIF($F$2:$F$46,N45)=0,COUNTIFS($F$2:$F$46,N45,$Q$2:$Q$46,"Aprobada")>0)),N45&" ","")&IF(NOT(OR(O45="",COUNTIF($F$2:$F$46,O45)=0,COUNTIFS($F$2:$F$46,O45,$Q$2:$Q$46,"Aprobada")>0)),O45&" ","")&IF(NOT(OR(P45="",COUNTIF($F$2:$F$46,P45)=0,COUNTIFS($F$2:$F$46,P45,$Q$2:$Q$46,"Aprobada")>0)),P45&" ","")),IF(Q45="Cursada aprobada",TRIM(IF(NOT(OR(L45="",COUNTIF($F$2:$F$46,L45)=0,COUNTIFS($F$2:$F$46,L45,$Q$2:$Q$46,"Aprobada")>0,AND(Resumen!$B$15="La cursada aprobada",COUNTIFS($F$2:$F$46,L45,$Q$2:$Q$46,"Cursada aprobada")>0))),L45&" ","")&IF(NOT(OR(M45="",COUNTIF($F$2:$F$46,M45)=0,COUNTIFS($F$2:$F$46,M45,$Q$2:$Q$46,"Aprobada")>0,AND(Resumen!$B$15="La cursada aprobada",COUNTIFS($F$2:$F$46,M45,$Q$2:$Q$46,"Cursada aprobada")>0))),M45&" ","")&IF(NOT(OR(N45="",COUNTIF($F$2:$F$46,N45)=0,COUNTIFS($F$2:$F$46,N45,$Q$2:$Q$46,"Aprobada")>0,AND(Resumen!$B$15="La cursada aprobada",COUNTIFS($F$2:$F$46,N45,$Q$2:$Q$46,"Cursada aprobada")>0))),N45&" ","")&IF(NOT(OR(O45="",COUNTIF($F$2:$F$46,O45)=0,COUNTIFS($F$2:$F$46,O45,$Q$2:$Q$46,"Aprobada")>0,AND(Resumen!$B$15="La cursada aprobada",COUNTIFS($F$2:$F$46,O45,$Q$2:$Q$46,"Cursada aprobada")>0))),O45&" ","")&IF(NOT(OR(P45="",COUNTIF($F$2:$F$46,P45)=0,COUNTIFS($F$2:$F$46,P45,$Q$2:$Q$46,"Aprobada")>0,AND(Resumen!$B$15="La cursada aprobada",COUNTIFS($F$2:$F$46,P45,$Q$2:$Q$46,"Cursada aprobada")>0))),P45&" ","")),""))
A46: Requisitos instrumentales | E46: SA | F46: 298 | G46: Acreditar 30 hs Pasantías o Prácticas Profesionales Académicas | Q46: No cursada | R46: =IF(Q46="Aprobada","Ya aprobada",IF(Q46="Cursada aprobada","Ya cursada",IF(AND(OR(L46="",COUNTIF($F$2:$F$46,L46)=0,COUNTIFS($F$2:$F$46,L46,$Q$2:$Q$46,"Aprobada")>0,AND(Resumen!$B$15="La cursada aprobada",COUNTIFS($F$2:$F$46,L46,$Q$2:$Q$46,"Cursada aprobada")>0)),OR(M46="",COUNTIF($F$2:$F$46,M46)=0,COUNTIFS($F$2:$F$46,M46,$Q$2:$Q$46,"Aprobada")>0,AND(Resumen!$B$15="La cursada aprobada",COUNTIFS($F$2:$F$46,M46,$Q$2:$Q$46,"Cursada aprobada")>0)),OR(N46="",COUNTIF($F$2:$F$46,N46)=0,COUNTIFS($F$2:$F$46,N46,$Q$2:$Q$46,"Aprobada")>0,AND(Resumen!$B$15="La cursada aprobada",COUNTIFS($F$2:$F$46,N46,$Q$2:$Q$46,"Cursada aprobada")>0)),OR(O46="",COUNTIF($F$2:$F$46,O46)=0,COUNTIFS($F$2:$F$46,O46,$Q$2:$Q$46,"Aprobada")>0,AND(Resumen!$B$15="La cursada aprobada",COUNTIFS($F$2:$F$46,O46,$Q$2:$Q$46,"Cursada aprobada")>0)),OR(P46="",COUNTIF($F$2:$F$46,P46)=0,COUNTIFS($F$2:$F$46,P46,$Q$2:$Q$46,"Aprobada")>0,AND(Resumen!$B$15="La cursada aprobada",COUNTIFS($F$2:$F$46,P46,$Q$2:$Q$46,"Cursada aprobada")>0))),"Sí","No"))) -> Sí | S46: =TRIM(IF(NOT(OR(L46="",COUNTIF($F$2:$F$46,L46)=0,COUNTIFS($F$2:$F$46,L46,$Q$2:$Q$46,"Aprobada")>0,AND(Resumen!$B$15="La cursada aprobada",COUNTIFS($F$2:$F$46,L46,$Q$2:$Q$46,"Cursada aprobada")>0))),L46&" ","")&IF(NOT(OR(M46="",COUNTIF($F$2:$F$46,M46)=0,COUNTIFS($F$2:$F$46,M46,$Q$2:$Q$46,"Aprobada")>0,AND(Resumen!$B$15="La cursada aprobada",COUNTIFS($F$2:$F$46,M46,$Q$2:$Q$46,"Cursada aprobada")>0))),M46&" ","")&IF(NOT(OR(N46="",COUNTIF($F$2:$F$46,N46)=0,COUNTIFS($F$2:$F$46,N46,$Q$2:$Q$46,"Aprobada")>0,AND(Resumen!$B$15="La cursada aprobada",COUNTIFS($F$2:$F$46,N46,$Q$2:$Q$46,"Cursada aprobada")>0))),N46&" ","")&IF(NOT(OR(O46="",COUNTIF($F$2:$F$46,O46)=0,COUNTIFS($F$2:$F$46,O46,$Q$2:$Q$46,"Aprobada")>0,AND(Resumen!$B$15="La cursada aprobada",COUNTIFS($F$2:$F$46,O46,$Q$2:$Q$46,"Cursada aprobada")>0))),O46&" ","")&IF(NOT(OR(P46="",COUNTIF($F$2:$F$46,P46)=0,COUNTIFS($F$2:$F$46,P46,$Q$2:$Q$46,"Aprobada")>0,AND(Resumen!$B$15="La cursada aprobada",COUNTIFS($F$2:$F$46,P46,$Q$2:$Q$46,"Cursada aprobada")>0))),P46&" ","")) | T46: =IF(Q46="Cursada aprobada",IF(AND(OR(L46="",COUNTIF($F$2:$F$46,L46)=0,COUNTIFS($F$2:$F$46,L46,$Q$2:$Q$46,"Aprobada")>0),OR(M46="",COUNTIF($F$2:$F$46,M46)=0,COUNTIFS($F$2:$F$46,M46,$Q$2:$Q$46,"Aprobada")>0),OR(N46="",COUNTIF($F$2:$F$46,N46)=0,COUNTIFS($F$2:$F$46,N46,$Q$2:$Q$46,"Aprobada")>0),OR(O46="",COUNTIF($F$2:$F$46,O46)=0,COUNTIFS($F$2:$F$46,O46,$Q$2:$Q$46,"Aprobada")>0),OR(P46="",COUNTIF($F$2:$F$46,P46)=0,COUNTIFS($F$2:$F$46,P46,$Q$2:$Q$46,"Aprobada")>0)),"Sí","No"),"") | U46: =IF(Q46="Aprobada",TRIM(IF(NOT(OR(L46="",COUNTIF($F$2:$F$46,L46)=0,COUNTIFS($F$2:$F$46,L46,$Q$2:$Q$46,"Aprobada")>0)),L46&" ","")&IF(NOT(OR(M46="",COUNTIF($F$2:$F$46,M46)=0,COUNTIFS($F$2:$F$46,M46,$Q$2:$Q$46,"Aprobada")>0)),M46&" ","")&IF(NOT(OR(N46="",COUNTIF($F$2:$F$46,N46)=0,COUNTIFS($F$2:$F$46,N46,$Q$2:$Q$46,"Aprobada")>0)),N46&" ","")&IF(NOT(OR(O46="",COUNTIF($F$2:$F$46,O46)=0,COUNTIFS($F$2:$F$46,O46,$Q$2:$Q$46,"Aprobada")>0)),O46&" ","")&IF(NOT(OR(P46="",COUNTIF($F$2:$F$46,P46)=0,COUNTIFS($F$2:$F$46,P46,$Q$2:$Q$46,"Aprobada")>0)),P46&" ","")),IF(Q46="Cursada aprobada",TRIM(IF(NOT(OR(L46="",COUNTIF($F$2:$F$46,L46)=0,COUNTIFS($F$2:$F$46,L46,$Q$2:$Q$46,"Aprobada")>0,AND(Resumen!$B$15="La cursada aprobada",COUNTIFS($F$2:$F$46,L46,$Q$2:$Q$46,"Cursada aprobada")>0))),L46&" ","")&IF(NOT(OR(M46="",COUNTIF($F$2:$F$46,M46)=0,COUNTIFS($F$2:$F$46,M46,$Q$2:$Q$46,"Aprobada")>0,AND(Resumen!$B$15="La cursada aprobada",COUNTIFS($F$2:$F$46,M46,$Q$2:$Q$46,"Cursada aprobada")>0))),M46&" ","")&IF(NOT(OR(N46="",COUNTIF($F$2:$F$46,N46)=0,COUNTIFS($F$2:$F$46,N46,$Q$2:$Q$46,"Aprobada")>0,AND(Resumen!$B$15="La cursada aprobada",COUNTIFS($F$2:$F$46,N46,$Q$2:$Q$46,"Cursada aprobada")>0))),N46&" ","")&IF(NOT(OR(O46="",COUNTIF($F$2:$F$46,O46)=0,COUNTIFS($F$2:$F$46,O46,$Q$2:$Q$46,"Aprobada")>0,AND(Resumen!$B$15="La cursada aprobada",COUNTIFS($F$2:$F$46,O46,$Q$2:$Q$46,"Cursada aprobada")>0))),O46&" ","")&IF(NOT(OR(P46="",COUNTIF($F$2:$F$46,P46)=0,COUNTIFS($F$2:$F$46,P46,$Q$2:$Q$46,"Aprobada")>0,AND(Resumen!$B$15="La cursada aprobada",COUNTIFS($F$2:$F$46,P46,$Q$2:$Q$46,"Cursada aprobada")>0))),P46&" ","")),""))

Sheet Lic. Administración
A1: Ciclo | B1: Orientación / Grupo | C1: Año | D1: Cuat. | E1: Área | F1: Cód. | G1: Denominación | H1: Grupo | I1: Hs/s | J1: Hs Bim | K1: Hs Cuat | L1: Corr. 1 | M1: Corr. 2 | N1: Corr. 3 | O1: Corr. 4 | P1: Corr. 5 | Q1: Estado | R1: ¿Puedo cursar? | S1: Correlativas pendientes | T1: ¿Puedo rendir el final? | U1: Correlativas a revisar
